Workbook

Sheet Read Me
A1: Premium Indian Specialty Coffee — Outreach Leads (North, West, Central, East & Northeast India)
A2: Research date: 27 Oct 2026. South India deliberately excluded (Goa is included as West coast).
A4: TIERS
A5: Premium — origin-driven specialty: single-origin / single-estate or micro-lot menus, manual brew bar (V60, Chemex, AeroPress, siphon), multi-roaster or guest-roast programmes, or imports international single origins. Core market for premium beans.
A6: Normal — better than regular: specialty-leaning, espresso-led cafes with a quality house blend, maybe one filter option; food/dessert-led concepts with a deliberate coffee programme. Market for a premium house blend + one rotating estate.
A7: Regular — commodity / chain cafes. Not targeted; listed only in 'Excluded (Regular tier)' for reference.
A9: PRIORITY
A10: A — act this week: upcoming or just-opened cafes still choosing suppliers, multi-roaster cafes, and cafes known to buy from outside roasters.
A11: B — strong fit: established Premium/Normal independents that do not roast in-house.
A12: C — nurture: roaster-owned cafes (collab/guest lot only), chains, or thin evidence.
A14: STATUS
A15: Upcoming / Coming soon — announced or 'opening soon' on social/press but not open (the pre-launch hype window).
... A34: COUNTS
A35: Cafes — total (Premium + Normal) | B35: =COUNTA('All Cafes (Premium+Normal)'!$A$2:$A$281) -> 280
A36: Cafes — Premium | B36: =COUNTIF('All Cafes (Premium+Normal)'!$D$2:$D$281,"Premium") -> 109
A37: Cafes — Normal | B37: =COUNTIF('All Cafes (Premium+Normal)'!$D$2:$D$281,"Normal") -> 171
A38: Cafes — Priority A | B38: =COUNTIF('All Cafes (Premium+Normal)'!$B$2:$B$281,"A") -> 60
A39: Hot leads (new & upcoming) | B39: =COUNTA('Hot Leads (New & Upcoming)'!$A$2:$A$91) -> 90
A40: Upcoming / coming soon | B40: =COUNTIF('All Cafes (Premium+Normal)'!$C$2:$C$281,"Upcoming / Coming soon") -> 4
A41: Opened in 2026 | B41: =COUNTIF('All Cafes (Premium+Normal)'!$C$2:$C$281,"New (opened 2026)") -> 82
A42: Multi-roaster cafes | B42: =COUNTIF('All Cafes (Premium+Normal)'!$F$2:$F$281,"Multi-roaster cafe") -> 6
A43: Cafes that roast in-house | B43: =COUNTIF('All Cafes (Premium+Normal)'!$K$2:$K$281,"Yes*") -> 12
A44: Supplier / roaster identified (not own roastery) | B44: =COUNTA('Supply Map'!$A$2:$A$51)-COUNTIF('Supply Map'!$A$2:$A$51,"Own roastery*") -> 37
A45: With an Instagram handle | B45: =COUNTIF('All Cafes (Premium+Normal)'!$U$2:$U$281,"@*") -> 110
A46: Roasters | B46: =COUNTA(Roasters!$A$2:$A$95) -> 94
A47: Channel partners | B47: =COUNTA('Channel Partners'!$A$2:$A$31) -> 30
A48: Cafes with a web check | B48: =COUNTIF('All Cafes (Premium+Normal)'!$AG$2:$AG$281,"?*") -> 262
A49: Cafe–roaster pairs from the web check | B49: =COUNTA('Web Check — Supplier Leads'!$A$2:$A$19) -> 18

Sheet Hot Leads (New & Upcoming)
A1: ID | B1: Priority | C1: Status | D1: Tier | E1: Name | F1: Type | G1: Region | H1: State | I1: City | J1: Area / address | K1: Roasts in-house? | L1: Current coffee roster | M1: Supplier / roaster | N1: Price signals | O1: Gap in their roster | P1: What we can offer | Q1: Approach strategy | R1: Evidence (why this tier) | S1: Pitch angle | T1: Best first contact | U1: Instagram | V1: Instagram URL | W1: Website | X1: Email | Y1: Phone | Z1: LinkedIn | AA1: Listing (Zomato / EazyDiner / Reddit) | AB1: Key people (public) | AC1: Source | AD1: Verify / notes | AE1: Web check: roster evidence (auto — verify) | AF1: Contacts on its own pages | AG1: Pages read (web check)
A2: C071 | B2: A | C2: Upcoming / Coming soon | D2: Premium | E2: Unnamed specialty cafe — Viman Nagar (in planning) | F2: Independent specialty cafe | G2: West | H2: Maharashtra | I2: Pune | J2: Viman Nagar | K2: Unknown | L2: Plans Coorg-sourced beans | M2: Not published — ask on first contact (look at the retail shelf / bag on the bar) | P2: Rotating single-estate / micro-lot for the filter bar + a single-origin espresso option. | Q2: Pre-launch: send a 3-estate tasting kit and offer a menu-development session before the menu locks; 90-day launch exclusivity in their micro-market; fixed price for the first 6 months. | R2: Founder posted on r/PuneCoffee (mid-2026) about opening a specialty cafe with Coorg beans and board-game nights. | S2: Pre-launch — reach founder via r/PuneCoffee before supplier is locked. | T2: Walk-in / Google Maps listing | AA2: https://www.reddit.com/r/PuneCoffee/new/ | AC2: r/PuneCoffee (via mirror redlib.groet-infra.nl/r/PuneCoffee/new) | AD2: Name unknown; Reddit post | AG2: 0 of 1 read:
A3: C174 | B3: A | C3: Upcoming / Coming soon | D3: Normal | E3: Coffee Bond (Cafe Bond) — CP & Karkardooma | F3: Cafe chain / multi-outlet | G3: North | H3: Delhi | I3: New Delhi | J3: Uday Park (South Ex II) + Saket; CP/Karkardooma outlets not confirmed | K3: Unknown | L3: Not published | M3: Not published — ask on first contact (look at the retail shelf / bag on the bar) | P3: Premium house espresso blend of Indian estates + one rotating single estate + cold-brew lot. | Q3: Pre-launch: send a 3-estate tasting kit and offer a menu-development session before the menu locks; 90-day launch exclusivity in their micro-market; fixed price for the first 6 months. | R3: Instagram bio announces 'opening soon' at Connaught Place and Karkardooma; Time Out called it an Australian import. Second handle for GK outlet: @cafebondgk. Second brand handle @thecoffeebond lists Uday Park (Delhi), Noida Sector 51 and Surat. | S3: Two launches pending — pitch before menus are fixed. | T3: Instagram DM | U3: @coffeebond | V3: https://www.instagram.com/coffeebond/ | AC3: https://www.instagram.com/coffeebond/ | AD3: Wave 4: no CP or Karkardooma listing found; Time Out calls it an Australian import. | AE3: Imported origins: Vietnam; Brew: Flat white | AG3: 3 of 4 read: https://www.explurger.com/pd/jjbnu1aqc73y2ajf6 https://www.explurger.com/pd/n1dlk70912p3g7pks https://wanderlog.com/place/details/1079729/coffee-bond
A4: C042 | B4: B | C4: Upcoming / Coming soon | D4: Premium | E4: Boojee Cafe — One BKC | F4: Roaster-cafe (roasts in-house) | G4: West | H4: Maharashtra | I4: Mumbai | J4: One BKC, Bandra Kurla Complex | K4: Yes | L4: Not published | M4: Own roastery | P4: Green coffee or a limited guest micro-lot collaboration (they roast in-house). | Q4: Don't pitch roasted supply — offer green lots or a co-branded guest micro-lot. | R4: Time Out (Aug 2026) reported Boojee's 5th Mumbai outlet opening soon at One BKC; Boojee runs as neighbourhood cafe + creative roastery. | S4: Roasts own, but expanding fast — pitch a limited guest single-estate for the BKC launch menu. | T4: Walk-in / Google Maps listing | AC4: https://www.timeout.com/mumbai/news/boojee-cafe-is-opening-a-new-outlet-at-one-bkc-in-mumbai-082026 | AD4: Wave 4: BKC still 'coming soon' (Time Out, Aug 2026); would be Boojee's 5th outlet. | AE4: Roasters named in articles about it: Boojee Cafe & Roastery; Brew: Flat white, Cold brew; ₹2,000 for two; Signals: Coming soon | AG4: 3 of 3 read: https://www.timeout.com/mumbai/news/boojee-cafe-is-opening-a-new-outlet-at-one-bkc-in-mumbai-082026 https://curlytales.com/india/food/mumbaikars-boojee-cafe-is-coming-to-bkc-with-its-signature-brews-bites/ https://www.freepressjournal.in/lifestyle/from-bandra-to-sobo-boojee-cafe-brings-its-classic-brews-brunch-to-south-mumbai
A5: C073 | B5: B | C5: Upcoming / Coming soon | D5: Normal | E5: Cafe Serenity — Baner (relocating) | F5: Independent specialty cafe | G5: West | H5: Maharashtra | I5: Pune | J5: Baner | K5: Unknown | L5: Not published | M5: Not published — ask on first contact (look at the retail shelf / bag on the bar) | P5: Premium house espresso blend of Indian estates + one rotating single estate + cold-brew lot. | Q5: Pre-launch: send a 3-estate tasting kit and offer a menu-development session before the menu locks; 90-day launch exclusivity in their micro-market; fixed price for the first 6 months. | R5: Instagram: 'Serenity finds a new home in Baner — be back soon'. | S5: Relaunch = supplier reset moment. | T5: Instagram DM | U5: @cafeserenity_pune | V5: https://www.instagram.com/cafeserenity_pune/ | AC5: https://www.instagram.com/cafeserenity_pune/ | AD5: Wave 4: only a Kothrud (Mayur Colony) listing found; Baner move unconfirmed. | AG5: 1 of 1 read: https://www.explurger.com/pd/pkfm8zlni1mxtmjw0
A6: C012 | B6: A | C6: New (opened 2026) | D6: Premium | E6: BBRWN Cafe | F6: Independent specialty cafe | G6: West | H6: Maharashtra | I6: Mumbai | J6: TBC | K6: Unknown | L6: Not published | M6: Not published — ask on first contact (look at the retail shelf / bag on the bar) | P6: Rotating single-estate / micro-lot for the filter bar + a single-origin espresso option. | Q6: Just opened: offer a guest-lot month + free barista calibration; side-by-side cupping against their current beans; ask which roaster/estates they use and what they'd change. | R6: New specialty cafe from Drishti Gundecha where coffee and ceremonial matcha take centre stage (2026 Mumbai openings coverage). | S6: New, coffee-first concept — offer espresso + filter single-estate pair. | T6: Walk-in / Google Maps listing | AB6: Drishti Gundecha (founder, per press) | AC6: Mumbai 2026 new-openings roundups (search) | AD6: Location and opening date not confirmed Instagram not indexed by search yet — look up by name on Instagram Wave 4: not found in a web search beyond its source roundup — confirm it is open (Instagram / Google Maps) before outreach.
A7: C013 | B7: A | C7: New (opened 2026) | D7: Premium | E7: Coffee Capital | F7: Cafe chain / multi-outlet | G7: West | H7: Maharashtra | I7: Mumbai | J7: Chembur + Versova (34 covers) | K7: Unknown | L7: Single-origin Arabica from Karnataka, Tamil Nadu, Odisha and Nagaland + a rotating slot of INTERNATIONAL micro-lots; whiskey-barrel-aged coffee; 'Noble Nectar'. | M7: Not published — ask on first contact (look at the retail shelf / bag on the bar) | N7: ~₹1,000 for two; EazyDiner 4.8 (249) | O7: Imports fill the 'exotic' slot. | P7: Indian anaerobic / experimental lots to replace the international micro-lot slot; barrel-ageing lots. | Q7: Lead with a cupping of 2–3 Indian experimental lots against their current import; offer the rotating slot at a fixed monthly price. | R7: 34-cover specialty cafe format built around single-origin Indian Arabica (Restaurant India). Instagram 'specialty coffee, cozy vibes — Chembur' with ~46 followers / 30 posts when indexed: account is brand-new. | S7: Menu is origin-driven — natural buyer of multiple single estates. | T7: Instagram DM | U7: @coffeecapital__ | V7: https://www.instagram.com/coffeecapital__/ | AB7: Tuhin Ghosh (founder) | AC7: https://www.restaurantindia.in/news/restaurant-india-news-coffee-capital-launches-in-mumbai-with-34-cover-speciality-caf-format.n15399 | AE7: Processes / format: Micro-lot, Single origin; Brew: Cold brew; Prices: wo at Coffee Capital? The cost of two at Coffee Capital is ₹ 1000. You can save EXTRA; ₹ 1000 for two | AG7: 2 of 3 read: https://www.eazydiner.com/mumbai/coffee-capital-versova-western-suburbs-712657 https://www.restaurantindia.in/news/restaurant-india-news-coffee-capital-launches-in-mumbai-with-34-cover-speciality-caf-format.n15399
A8: C015 | B8: A | C8: New (opened 2026) | D8: Premium | E8: Esc. Coffee x Deli | F8: Independent specialty cafe | G8: West | H8: Maharashtra | I8: Mumbai | J8: Bandra | K8: Unknown | L8: Not published | M8: Not published — ask on first contact (look at the retail shelf / bag on the bar) | P8: Rotating single-estate / micro-lot for the filter bar + a single-origin espresso option. | Q8: Just opened: offer a guest-lot month + free barista calibration; side-by-side cupping against their current beans; ask which roaster/estates they use and what they'd change. | R8: Specialty coffee spot in March 2026 openings (Foodies of India). | T8: Walk-in / Google Maps listing | AC8: https://foodiesofindia.wordpress.com/2026/03/01/new-restaurants-in-mumbai-march-2026-round-up-25-new-openings/ | AE8: ₹1500 for two | AG8: 2 of 2 read: https://www.district.in/dining/mumbai/esc-coffee-x-deli-carter-road-bandra-west https://foodiesofindia.wordpress.com/2026/03/01/new-restaurants-in-mumbai-march-2026-round-up-25-new-openings/
A9: C016 | B9: A | C9: New (opened 2026) | D9: Premium | E9: Grahm Cafe | F9: Independent specialty cafe | G9: West | H9: Maharashtra | I9: Mumbai | J9: Bandra | K9: Unknown | L9: Not published | M9: Not published — ask on first contact (look at the retail shelf / bag on the bar) | P9: Rotating single-estate / micro-lot for the filter bar + a single-origin espresso option. | Q9: Just opened: offer a guest-lot month + free barista calibration; side-by-side cupping against their current beans; ask which roaster/estates they use and what they'd change. | R9: Neighbourhood cafe for specialty coffee, fresh bakes, brunch (Foodies of India, Aug 2026). | T9: Walk-in / Google Maps listing | AC9: https://foodiesofindia.wordpress.com/2026/08/04/new-restaurants-cafes-in-mumbai-august-2026/ | AD9: Wave 4: not found in a web search beyond its source roundup — confirm it is open (Instagram / Google Maps) before outreach. | AE9: Commodity brands: Nespresso | AG9: 1 of 1 read: https://foodiesofindia.wordpress.com/2026/08/04/new-restaurants-cafes-in-mumbai-august-2026/
A10: C017 | B10: A | C10: New (opened 2026) | D10: Premium | E10: JOKER | F10: Coffee + cocktail bar | G10: West | H10: Maharashtra | I10: Mumbai | J10: Turner Rd, Bandra W (opened 2 Aug 2026) | K10: Unknown | L10: Cafe by day, cocktail bar by night; Brandy Barrel Aged pour-over; signatures Joker Twist, Frost and Fortune. | M10: Not published — ask on first contact (look at the retail shelf / bag on the bar) | O10: Barrel-aged programme needs lots that suit ageing. | P10: Co-developed barrel series (rum / brandy / whisky) on Indian naturals + cocktail-grade espresso. | Q10: Pitch Aspect Hospitality's F&B team — group can roll it out to other venues. | R10: Aspect Hospitality's all-day coffee & cocktail bar, opened 2 Aug 2026. | T10: Website contact form | W10: https://aspecthospitality.in | AB10: Aspect Hospitality | AC10: https://www.restaurantindia.in/news/aspect-hospitality-expands-fb-portfolio-with-joker-in-bandra.n16905 | AE10: Brew: Pour over | AG10: 3 of 4 read: https://aspecthospitality.in https://www.aspecthospitality.in/our-story https://www.restaurantindia.in/news/aspect-hospitality-expands-fb-portfolio-with-joker-in-bandra.n16905
A11: C019 | B11: A | C11: New (opened 2026) | D11: Premium | E11: Kink Speciality Coffee | F11: Cafe chain / multi-outlet | G11: West | H11: Maharashtra | I11: Mumbai | J11: Bandra (+ other outlets) | K11: Unknown | L11: Not published | M11: Not published — ask on first contact (look at the retail shelf / bag on the bar) | P11: Rotating single-estate / micro-lot for the filter bar + a single-origin espresso option. | Q11: Just opened: offer a guest-lot month + free barista calibration; side-by-side cupping against their current beans; ask which roaster/estates they use and what they'd change. | R11: Instagram: speciality coffee, Bandra among outlets. Foodies of India Jan 2026: bold, modern coffee spot, strong brews. | S11: Specialty indie. | T11: Instagram DM | U11: @kink.coffee | V11: https://www.instagram.com/kink.coffee/ | AC11: https://foodiesofindia.wordpress.com/2026/01/15/january-2026-30-new-restaurants-cafes-in-mumbai-you-need-to-check-out/ | AD11: Wave 4: not found in a web search beyond its source roundup — confirm it is open (Instagram / Google Maps) before outreach. | AG11: 0 of 1 read:
A12: C020 | B12: A | C12: New (opened 2026) | D12: Premium | E12: KĀPIBAR | F12: Independent specialty cafe | G12: West | H12: Maharashtra | I12: Mumbai | J12: Bandra | K12: Unknown | L12: Regional Indian coffee traditions (details not published). | M12: Not published — ask on first contact (look at the retail shelf / bag on the bar) | P12: Regional single estates (Coorg, Chikmagalur, Nilgiris, Araku, Northeast) — a 'map of India' flight. | Q12: Perfect story fit — lead with origin storytelling. | R12: South Indian-inspired cafe celebrating regional coffee traditions (Foodies of India, Aug 2026). | T12: Walk-in / Google Maps listing | AC12: https://foodiesofindia.wordpress.com/2026/08/04/new-restaurants-cafes-in-mumbai-august-2026/ | AD12: Wave 4: not found in a web search beyond its source roundup — confirm it is open (Instagram / Google Maps) before outreach. | AE12: Commodity brands: Nespresso | AG12: 1 of 1 read: https://foodiesofindia.wordpress.com/2026/08/04/new-restaurants-cafes-in-mumbai-august-2026/
A13: C021 | B13: A | C13: New (opened 2026) | D13: Premium | E13: MUVN Coffee | F13: Independent specialty cafe | G13: West | H13: Maharashtra | I13: Mumbai | J13: Andheri | K13: Unknown | L13: Not published | M13: Not published — ask on first contact (look at the retail shelf / bag on the bar) | P13: Rotating single-estate / micro-lot for the filter bar + a single-origin espresso option. | Q13: Just opened: offer a guest-lot month + free barista calibration; side-by-side cupping against their current beans; ask which roaster/estates they use and what they'd change. | R13: Listed under 'New Cafes in Andheri' (Foodies of India, Apr 2026). | T13: Walk-in / Google Maps listing | AC13: https://foodiesofindia.wordpress.com/2026/04/02/20-new-restaurants-in-mumbai-to-check-out-april-2026/ | AD13: Wave 4: not found in a web search beyond its source roundup — confirm it is open (Instagram / Google Maps) before outreach. | AG13: 1 of 1 read: https://foodiesofindia.wordpress.com/2026/04/02/20-new-restaurants-in-mumbai-to-check-out-april-2026/
A14: C022 | B14: A | C14: New (opened 2026) | D14: Premium | E14: Stand By Coffee — Juhu | F14: Cafe chain / multi-outlet | G14: West | H14: Maharashtra | I14: Mumbai | J14: Juhu (3rd outlet after Worli and Bandra) | K14: No (roasting partners) | L14: Pour-overs, espresso, matcha; first outlet with ube drinks. Seven Chikmagalur coffees from outside roasting partners. | M14: Works with outside roasting partners (unnamed) | N14: ₹600–1,700 for two | O14: Single-region roster (Chikmagalur only). | P14: Non-Chikmagalur estates (Northeast, Araku, Nilgiris, Odisha, Coorg) to diversify the 7-coffee wall. | Q14: Group pitch for all three outlets: offer a non-Karnataka estate as a guest pour-over across Worli, Bandra and Juhu. | R14: Mumbai-born cafe brand opened 3rd outlet in Juhu; menu has espresso, pour-over, matcha and ube drinks. Instagram bio: 7:30am–1am, phone numbers listed in bio, on Zomato/Swiggy. | S14: Growing indie brand with pour-over on menu — pitch rotating single-estate filter offering. | T14: Instagram DM | U14: @standbycoffee__ | V14: https://www.instagram.com/standbycoffee__/ | AB14: Aditya Wanwari (Toast Inc) | AC14: https://indianretailer.com/news/stand-coffee-expands-mumbai-footprint-new-juhu-outlet | AE14: Indian origins/estates: Chikmagalur; Brew: Pour over, Espresso tonic | AG14: 2 of 3 read: https://indianretailer.com/news/stand-coffee-expands-mumbai-footprint-new-juhu-outlet https://www.restaurantindia.in/news/stand-by-coffee-unveils-in-mumbai.n21574
A15: C023 | B15: A | C15: New (opened 2026) | D15: Premium | E15: Thought Coffee — Bandra flagship | F15: Cafe chain / multi-outlet | G15: West | H15: Maharashtra | I15: Mumbai | J15: Bandra | K15: Yes — 'single-estate AA, roasted in-house' (Restaurant India) | L15: Single-estate AA Arabica roasted in-house; rum- and wine-barrel-aged coffees; imported Colombian Castillo special; QSR under 5 minutes. | M15: Own roastery (single-estate AA, roasted in-house) | O15: Imports Colombian Castillo for its special; a QSR brand scaling across Mumbai needs volume + consistency. | P15: Green coffee (single-estate AA + an Indian replacement for the Castillo) for their roaster. | Q15: They roast: pitch green lots and an exclusive barrel-ageing lot as they densify across Mumbai. | R15: Mumbai-born quick-service specialty brand opening its Bandra flagship (Oct 2026 roundups); menu lists single-origin AA Arabica and barrel-aged coffees. Wave 4: Restaurant India (Sep 2026) says the beans are roasted in-house. | S15: Young brand building a menu of 'special' coffees — barrel-aged / experimental-process lots fit. | T15: Walk-in / Google Maps listing | AB15: Kush Kachhara, Kshitij Patil, Jhanvi Shah (founders) | AC15: https://www.restaurantindia.in/news/thought-coffee-opens-bandra-flagship-as-mumbai-quick-service-coffee-market-expands.n17296 | AD15: Instagram not indexed by search yet — look up by name on Instagram | AE15: Imported origins: Colombia; Processes / format: Single origin, Single estate | AG15: 2 of 3 read: https://www.restaurantindia.in/news/thought-coffee-opens-bandra-flagship-as-mumbai-quick-service-coffee-market-expands.n17296 https://www.passionateinmarketing.com/one-less-thought-thought-coffee-opens-in-bandra-with-quality-coffee/
A16: C024 | B16: A | C16: New (opened 2026) | D16: Premium | E16: Tsubaki Artisanal Coffee | F16: Independent specialty cafe | G16: West | H16: Maharashtra | I16: Mumbai | J16: Kandivali | K16: Unknown | L16: Not published | M16: Not published — ask on first contact (look at the retail shelf / bag on the bar) | P16: Suburban specialty with little competition — exclusive estates. | Q16: Just opened: offer a guest-lot month + free barista calibration; side-by-side cupping against their current beans; ask which roaster/estates they use and what they'd change. | R16: New artisanal coffee spot (Foodies of India, Jun 2026). | T16: Walk-in / Google Maps listing | AC16: https://foodiesofindia.wordpress.com/2026/06/01/june-2026-new-restaurants-in-mumbai-you-need-to-visit/ | AD16: Wave 4: not found in a web search beyond its source roundup — confirm it is open (Instagram / Google Maps) before outreach. | AG16: 1 of 1 read: https://foodiesofindia.wordpress.com/2026/06/01/june-2026-new-restaurants-in-mumbai-you-need-to-visit/
A17: C068 | B17: A | C17: New (opened 2026) | D17: Premium | E17: Cafe Lento — Pune | F17: All-day / food-led cafe | G17: West | H17: Maharashtra | I17: Pune | J17: Koregaon Park | K17: Unknown | L17: Single estate: Salawara Estate (Karnataka); coffee is the signature; Pune adds cocktails (raw mango wine, Lento espresso martini). | M17: Salawara Estate (roaster not named) | O17: Single-estate dependency. | P17: Second estate for a rotating pour-over + an espresso-martini-ready blend. | Q17: Luna Hospitality (also The Second House, Goa) — one pitch covers Goa + Pune. | R17: Luna Hospitality's Goa cafe opened a 2,200 sq ft Pune outpost (Nod Jun 2026; Elle Decor Sep 2026); coffee + congee concept. | S17: Single-estate-minded team — pitch an estate exclusive for Pune. | T17: Instagram DM | U17: @cafelento.in | V17: https://www.instagram.com/cafelento.in/ | AB17: Dishant Pritamani (co-founder, Luna Hospitality) | AC17: https://yourstory.com/ys-life/the-second-house-goa-lento-cafe | AG17: 0 of 2 read:
A18: C069 | B18: A | C18: New (opened 2026) | D18: Premium | E18: Momoka | F18: Independent specialty cafe | G18: West | H18: Maharashtra | I18: Pune | J18: Prabhat Rd, Pune (opened 1 Aug 2026) | K18: Unknown | L18: Japanese kissaten: ceremonial Uji matcha, hojicha; coffee jelly latte, coconut-foam cold brew. | M18: Not published — ask on first contact (look at the retail shelf / bag on the bar) | N18: ~₹900 for two | O18: Coffee is secondary to matcha; no named roaster. | P18: A kissaten-style medium-dark blend + a cold brew lot. | Q18: Chef-founder Brainard Colaco — offer to co-design a hand-drip menu. | R18: Japanese kissaten-style flagship opened Aug 2026 with specialty beverages, desserts and yoshoku food. Instagram bio: 'India's first kissaten' — Japanese coffee & tea room; Prabhat Road marked 'now open' (Jul 2026). | S18: Kissaten culture = hand-drip / siphon — pitch light-roast single estates. | T18: Instagram DM | U18: @momoka.india | V18: https://www.instagram.com/momoka.india/ | AB18: Chef Brainard Colaco | AC18: https://www.restaurantindia.in/news/momoka-opens-japanese-kissaten-inspired-caf-on-punes-prabhat-road.n16884 | AE18: Brew: Cold brew | AG18: 3 of 3 read: https://www.restaurantindia.in/news/momoka-opens-japanese-kissaten-inspired-caf-on-punes-prabhat-road.n16884 https://indianretailer.com/franchisetv/archives/news/momoka-brings-japanese-kissaten-culture-pune-new-flagship-cafe https://www.passionateinmarketing.com/momoka-brings-the-spirit-of-a-japanese-kissaten-to-pune/
A19: C124 | B19: A | C19: New (opened 2026) | D19: Premium | E19: Indiroom (at Pincode Bungalow) | F19: Independent specialty cafe | G19: West | H19: Goa | I19: Assagao | K19: No | L19: Indian specialty coffee roasted by Caarabi. | M19: Caarabi Coffee (New Delhi) | O19: Single-roaster. | P19: Second roaster / Goa-exclusive estate. | Q19: Approach via Pincode by Kunal Kapur team. | R19: Opened Feb 2026; serves Indian specialty coffee roasted by Caarabi Coffee, New Delhi. | S19: Proven external-roaster buyer — pitch as second/rotating roaster. | T19: Walk-in / Google Maps listing | U19: (via @pincode_india) | AB19: Inside Pincode by chef Kunal Kapur (@pincode_india) | AC19: https://www.district.in/blog/speciality-coffee-cafes-goa | AE19: Roasters named in articles about it: Caarabi Coffee Roasters; Brew: Tasting flight / omakase, V60, Pour over, Cold brew | AG19: 1 of 2 read: https://www.baristamagazine.com/exploring-the-vibrant-specialty-coffee-culture-of-goa-india/
A20: C156 | B20: A | C20: New (opened 2026) | D20: Premium | E20: More Over Coffee | F20: Cafe chain / multi-outlet | G20: Central | H20: Chhattisgarh | I20: Raipur | J20: Civil Lines + Devendra Nagar (Raipur), Nehru Nagar (Bhilai), Vyapar Vihar (Bilaspur) | K20: Unknown | L20: 'No long menu' — six drinks at a specialty bar (est. 2024). | M20: Not published — ask on first contact (look at the retail shelf / bag on the bar) | P20: Rotating single-estate / micro-lot for the filter bar + a single-origin espresso option. | Q20: Just opened: offer a guest-lot month + free barista calibration; side-by-side cupping against their current beans; ask which roaster/estates they use and what they'd change. | R20: Instagram: 'Speciality Coffee & More' — relaunched in Civil Lines, Raipur. Instagram lists 4 outlets across Raipur, Bhilai and Bilaspur — Chhattisgarh's only specialty-labelled multi-outlet brand. | S20: Relaunch + pour-over menu — Raipur's lone specialty lead. | T20: Instagram DM | U20: @moreovercoffee_india | V20: https://www.instagram.com/moreovercoffee_india/ | AC20: https://www.instagram.com/moreovercoffee_india/ | AD20: Wave 4: the only web page found is a demo site (moc-demo.vercel.app) — not used as its website. | AG20: 0 of 1 read:
A21: C158 | B21: A | C21: New (opened 2026) | D21: Premium | E21: Carbon — Vaishali Nagar (3rd outpost) | F21: Cafe chain / multi-outlet | G21: North | H21: Rajasthan | I21: Jaipur | J21: Ashok Nagar, Tilak Nagar, Vaishali Nagar (Jaipur) | K21: Unknown | L21: 18–96-hour cold brews (berry, mint-lime, whiskey barrel), Black Carbon Latte, Jamun Coffee Tonic, coffee mixology. | M21: Not published — ask on first contact (look at the retail shelf / bag on the bar) | N21: ~₹900 for two; Whiskey Barrel Cold Brew ₹220 | O21: Cold-brew-heavy menu across 3 outlets. | P21: Cold-brew-optimised naturals in bulk + espresso blend; co-developed coffee tonic. | Q21: 3-outlet local brand — pitch volume pricing. | R21: Third outpost pairing specialty coffee with a design-forward space (2026 roundup). Instagram: craft coffee bar, cold-brew focus, 9am–midnight. | S21: Expanding local brand. | T21: Instagram DM | U21: @carbon.jaipur | V21: https://www.instagram.com/carbon.jaipur/ | AC21: https://www.restaurantindia.in/news/carbon-opens-third-caf-in-jaipur-with-new-vaishali-nagar-outlet.n16924 | AD21: Single source | AE21: Imported origins: Vietnam; Processes / format: Experimental lot; Brew: Cold brew, V60, Siphon; Prices: Whiskey Cold Brew, INR 220 | Vanilla Strawberry Iced Latte, INR 220; ₹ 900 for two | AG21: 5 of 5 read: https://www.eazydiner.com/jaipur/carbon-ashok-nagar-jaipur-690551/reviews https://www.restaurantindia.in/news/carbon-opens-third-caf-in-jaipur-with-new-vaishali-nagar-outlet.n16924 https://curlytales.com/india/food/whiskey-barrel-cold-brew-to-au-chocolate-carbon-brings-a-new-cafe-culture-in-jaipur/ https://indianretailer.com/news/carbon-jaipur-expands-second-outlet-jaipur-cafe-market
A22: C159 | B22: A | C22: New (opened 2026) | D22: Premium | E22: Jacob's Brew House — Jaipur | F22: Cafe chain / multi-outlet | G22: North | H22: Rajasthan | I22: Jaipur | J22: JLN Marg, Malviya Nagar | K22: Likely in-house ('controlled roasting') | L22: Pour-over and espresso with tasting cards (origin, farm, producer, process, roast); signatures The Jacobs Sensation, Cloud 101. | M22: Not published — ask on first contact (look at the retail shelf / bag on the bar) | N22: ~₹1,500 for two | O22: Sophisticated, card-driven menu that needs a steady supply of traceable lots. | P22: Competition-grade lots with full farm data (green or roasted); co-branded tasting cards. | Q22: Speak to the coffee lead directly: send farm-level lot sheets — their tasting-card format rewards traceable single estates. | R22: Opened Mar 2026; design-led all-day cafe; specialty programme led by UAE Barista Champion Sonam Dorje Sherpa. | S22: Champion-led programme = appetite for competition-grade lots. | T22: Walk-in / Google Maps listing | AB22: Sonam Dorje Sherpa (UAE Barista Champion) leads the coffee programme | AC22: https://thenodmag.com/content/jacobs-brew-house-jaipur-cafe-coffee-house-review | AD22: Instagram unconfirmed (@jacobs_brew may be a different shop) | AE22: Imported origins: Vietnam; Brew: Cold brew, Pour over; Signals: Now open | AG22: 4 of 4 read: https://thenodmag.com/content/jacobs-brew-house-jaipur-cafe-coffee-house-review https://www.restaurantindia.in/news/restaurant-india-news-jacob-s-brew-house-brings-specialty-coffee-focus-to-jaipur.n15791 https://www.restaurantindia.in/news/restaurant-india-news-jacob-s-brew-house-opens-in-jaipur-introducing-a-design-led-specialty-coffee.n15452 https://oteats.outlooktraveller.com/amp/story/reviews/the-pesto-gnocchi-at-jacobs-is-all-you-need-to-make-sundays-saucy
A23: C160 | B23: A | C23: New (opened 2026) | D23: Premium | E23: Traut Coffee House | F23: Independent specialty cafe | G23: North | H23: Rajasthan | I23: Jaipur | J23: A-2, Ajmer Rd, Vidhyut Nagar | K23: Unknown | L23: Signature Pistachio Crème Latte; espresso-led. | M23: Not published — ask on first contact (look at the retail shelf / bag on the bar) | N23: ~₹800 for two | O23: No published filter / single-origin line. | P23: Espresso blend that holds up in milk + one single-estate filter to add depth. | Q23: Weeks-old, founder-run — walk-in tasting with founders Aalia Agarwal & Ujjwal Bijarnia. | R23: Outlook Traveller (26 Sep 2026): Jaipur's newest coffee hotspot, inventive coffee + broad food menu. Weekend queues reported; open till 11pm. | S23: Opened weeks ago — supplier relationships still forming. | T23: Walk-in / Google Maps listing | AA23: https://www.eazydiner.com/jaipur/traut-coffee-house-vidhyut-nagar-jaipur-719695 | AB23: Aalia Agarwal & Ujjwal Bijarnia (founders) | AC23: https://www.outlooktraveller.com/ot-pours/traut-coffee-house-opens-doors-as-jaipurs-newest-coffee-hotspot | AD23: Instagram not indexed by search yet — look up by name on Instagram | AE23: Imported origins: Java; Prices: aut Coffee House? The cost of two at Traut Coffee House is ₹ 800. You can save EXTRA; ₹ 800 for two | AG23: 2 of 2 read: https://www.eazydiner.com/jaipur/traut-coffee-house-vidhyut-nagar-jaipur-719695 https://www.outlooktraveller.com/ot-pours/traut-coffee-house-opens-doors-as-jaipurs-newest-coffee-hotspot
A24: C177 | B24: A | C24: New (opened 2026) | D24: Premium | E24: Common Time — Khan Market | F24: Cafe chain / multi-outlet | G24: North | H24: Delhi | I24: New Delhi | J24: Khan Market (Khan Kissaten) + Lodhi Colony + Basant Lok | K24: Unknown | L24: Rotating single-origin pour-overs; iced brown-butter latte, Earl Grey flat white, Competition Latte; no syrups. | M24: Not published — ask on first contact (look at the retail shelf / bag on the bar) | P24: Hand-drip single estates + kissaten blend. | Q24: Group deal with Bhatia Hospitality: Common Time (3 outlets) + Sidewalk (5 outlets) — pitch a rotating single-origin for Common Time and a house blend for Sidewalk. | R24: Time Out review 4/5. Lab Mag (Sep 2026): hidden cafe drawing on Japanese kissaten culture — design, music, coffee. | S24: Blend + single estate. | T24: Walk-in / Google Maps listing | AB24: Jaivardhan & Sagar Bhatia (Bhatia Hospitality Group) | AC24: https://www.thelabmagofficial.com/new-restaurants-cafes-and-bars-to-try-across-india-this-september/ | AE24: Processes / format: Single origin; Brew: Pour over, Cold brew, Flat white | AG24: 3 of 4 read: https://www.timeout.com/delhi/restaurants/common-time https://www.restaurantindia.in/news/restaurant-india-news-common-time-opens-second-delhi-caf-in-basant-lok-targets-premium-neighbourhood.n15317 https://indianretailer.com/news/common-time-opens-second-delhi-cafe-basant-lok-market
A25: C178 | B25: A | C25: New (opened 2026) | D25: Premium | E25: Cortasso Coffee and Bakehouse | F25: Bakery / patisserie cafe | G25: North | H25: Delhi | I25: New Delhi | J25: Sunder Nursery, Nizamuddin | K25: Unknown | L25: Rum-barrel-aged roast coffee, winter spice latte; opened 2025. | M25: Not published — ask on first contact (look at the retail shelf / bag on the bar) | P25: Rotating single-estate / micro-lot for the filter bar + a single-origin espresso option. | Q25: Just opened: offer a guest-lot month + free barista calibration; side-by-side cupping against their current beans; ask which roaster/estates they use and what they'd change. | R25: Named in The Nod's 'new wave' of south Delhi coffee (May 2026). | T25: Walk-in / Google Maps listing | AC25: https://thenodmag.com/content/the-drop-hauz-khas-delhi-indian-specialty-coffee-roastery-review | AE25: Processes / format: Guest roaster / rotating | AG25: 2 of 4 read: https://thenodmag.com/content/the-drop-hauz-khas-delhi-indian-specialty-coffee-roastery-review https://urbanaut.app/spot/delhi-coffee-crawl-7
A26: C179 | B26: A | C26: New (opened 2026) | D26: Premium | E26: In Good Co. | F26: Independent specialty cafe | G26: North | H26: Delhi | I26: New Delhi | J26: GK-2 (first outlet) | K26: Unknown | L26: 'Progressive Indianness': Americano beside filter coffee; signatures The Indulgent, The Romantic, The Optimist, The Conversationalist; hojicha mocha. | M26: Not published — ask on first contact (look at the retail shelf / bag on the bar) | N26: ~₹800 for two; Swiggy 4.2 | O26: One-origin roster (Chikkamagaluru AA) — no rotating filter or second region. | P26: Second estate for a rotating filter / seasonal special; Indian-origin storytelling to match its 'modern Indian' positioning. | Q26: Corporate-backed (Aditya Birla dining) — pitch a supply partnership for future outlets; Instagram DM + LinkedIn to the dining arm. | R26: Cafe-meets-cultural-hub built around coffee, food and community (The Nod, Jun 2026). Instagram: 'India's good coffee in good company' — modern Indian cafe, specialty coffee & comfort food; account sits under Aditya Birla dining (~5.2k followers). Corporate-backed: likely to add outlets. | S26: Corporate-backed concept with expansion potential — pitch a supply partnership, not a single bag. | T26: Instagram DM | U26: @ingoodcoindia | V26: https://www.instagram.com/ingoodcoindia/ | AC26: https://thenodmag.com/content/where-to-eat-this-june-in-delhi-ncr | AE26: Indian origins/estates: Chikmagalur; Imported origins: Vietnam; Processes / format: Single estate; Brew: Cold brew, Tasting flight / omakase; ₹800 for two | AG26: 3 of 5 read: https://thenodmag.com/content/where-to-eat-this-june-in-delhi-ncr https://curlytales.com/delhis-in-good-co-pampered-me-with-upma-balls-tahini-coffee-in-a-baby-blue-setting/ https://www.outlooktraveller.com/ot-pours/the-sulaimani-iced-tea-at-in-good-co-is-enough-reason-to-plan-a-visit
A27: C180 | B27: A | C27: New (opened 2026) | D27: Premium | E27: The Drop | F27: Coffee + cocktail bar | G27: North | H27: Delhi | I27: New Delhi | J27: G-8, Ground Floor, Hauz Khas Market (35 seats) | K27: No (Subko collaboration) | L27: House blend developed with Subko from Tamil Nadu estates (Orchardale, Bison Valley, Moganad); agave-barrel-aged (Maya Pistola) hot and iced pour-overs; new menu monthly. | M27: Developed with Subko (Mumbai) | N27: ₹1,000–1,800 for two (Swiggy / EazyDiner / OT) | O27: All-Tamil Nadu, single-partner line-up; no Northeast, Karnataka, Odisha or Araku coffees; rotation needs new lots every month. | P27: A guest 'drop' month of non-TN estates (Northeast / Odisha / Karnataka micro-lot or co-ferment), co-branded limited release. | Q27: Pitch Passcode Hospitality (also runs Saz, Jamun, PCO) — one deal can travel across the group. Lead with a 3-lot cupping flight. | R27: Passcode Hospitality's coffee-and-cocktail bar (May 2026); rotates its craft coffee menu monthly. | S27: Monthly rotation needs new lots — pitch a guest month featuring your estates. | T27: Website contact form | W27: https://passcodehospitality.com/drop | AB27: Passcode Hospitality | AC27: https://www.outlooktraveller.com/ot-pours/drop-in-at-the-drop-and-find-your-jaws-dropped | AD27: Instagram not indexed by search yet — look up by name on Instagram | AE27: Roasters named in articles about it: Subko Coffee Roasters; Indian origins/estates: Tamil Nadu; Imported origins: Colombia; Processes / format: Guest roaster / rotating, Single origin, House blend; Varietals: Robusta; Brew: Pour over | AF27: +91 98109 61802 | AG27: 5 of 6 read: https://passcodehospitality.com/drop https://passcodehospitality.com/about-us https://passcodehospitality.com/brands/drop/menu/ https://www.outlooktraveller.com/ot-pours/drop-in-at-the-drop-and-find-your-jaws-dropped
A28: C181 | B28: A | C28: New (opened 2026) | D28: Premium | E28: Therefore | F28: Coffee + cocktail bar | G28: North | H28: Delhi | I28: New Delhi | J28: Meherchand Market, Lodhi Colony | K28: Unknown | L28: Not published | M28: Not published — ask on first contact (look at the retail shelf / bag on the bar) | P28: Rotating single-estate / micro-lot for the filter bar + a single-origin espresso option. | Q28: Just opened: offer a guest-lot month + free barista calibration; side-by-side cupping against their current beans; ask which roaster/estates they use and what they'd change. | R28: All-day cafe turning cocktail bar; specialty coffee on menu (Outlook Traveller, 21 Oct 2026). | S28: Days-old opening — fastest-moving lead in Delhi. | T28: Walk-in / Google Maps listing | AC28: https://www.outlooktraveller.com/ot-pours | AD28: Only one press mention (OT Pours, Oct 2026) — confirm name/handle Wave 4: not found in a web search beyond its source roundup — confirm it is open (Instagram / Google Maps) before outreach. | AG28: 0 of 1 read:
A29: C202 | B29: A | C29: New (opened 2026) | D29: Premium | E29: Altogether Experimental (ATE) — Omakase | F29: Independent specialty cafe | G29: North | H29: Haryana | I29: Gurugram | J29: Sector 59, Gurugram | K29: Unknown | L29: Six-seat coffee omakase ('Textures': ethereal, slippery, syrupy, transient); Peru Geisha, clarified coffee, whiskey-barrel-aged course. | M29: Caarabi Coffee (sister company; format pioneered by Caarabi) | N29: Ticketed via District | O29: Uses an imported Peru Geisha for the headline course. | P29: An Indian rare-lot course (e.g. a Geisha/SL795 micro-lot) to replace the import. | Q29: Hard to displace Caarabi as house roaster — pitch a single omakase course / limited edition rather than supply. | R29: May 2026: four-course coffee + dessert omakase, iced pour-overs to dessert-like brews; bookings on District. Instagram ~24k followers; sister accounts @ate_patisserie, @ate_mini — 4+ outlets. Wave 4: Restaurant India says the omakase format comes from Caarabi Coffee, ATE's sister company. | S29: Omakase = curated rare lots — pitch micro-lots & experimental processes. | T29: Instagram DM | U29: @ate_altogetherexperimental | V29: https://www.instagram.com/ate_altogetherexperimental/ | AB29: Chef Anukriti Anand (founder; Instagram @chefanukritianand) | AC29: https://thenodmag.com/content/new-restaurants-bars-menus-delhi-may-2026 | AE29: Imported origins: Colombia, Costa Rica; Processes / format: Experimental lot; Varietals: Geisha / Gesha; Brew: Tasting flight / omakase, Affogato, Cold brew, Cortado; Commodity brands: Starbucks; Prices: Coffee • ₹1200 for two | Coffee • ₹2500 for two | ₹2500 for two • Coffee • Continental; ₹1200 for two | AG29: 6 of 7 read: https://thenodmag.com/content/new-restaurants-bars-menus-delhi-may-2026 https://www.restaurantindia.in/news/restaurant-india-news-ate-omakase-introduces-omakase-style-coffee-format-in-gurugram.n16015 https://www.indianretailer.com/franchisetv/archives/news/ate-omakase-introduces-curated-coffee-format-gurugram https://www.esquireindia.co.in/amp/story/food-and-drinks/where-to-drink/ate-omakase-coffee-in-gurgaon
A30: C203 | B30: A | C30: New (opened 2026) | D30: Premium | E30: Oro | F30: Independent specialty cafe | G30: North | H30: Haryana | I30: Gurugram | K30: Unknown | L30: Beans from North East India, Goa and Tamil Nadu; pour-over or classic; tiramisu latte, chocolate-berry cold brew. | M30: Not published — ask on first contact (look at the retail shelf / bag on the bar) | O30: No Karnataka / Coorg / Araku / Odisha coffees on the published list. | P30: An exclusive estate for the flagship plus supply for the planned NCR outlets. | Q30: Founder-led (Tisha Aggarwal) — founder outreach with a tasting kit; position as expansion partner. | R30: Flagship opened Aug/Sep 2026 by Tisha Aggarwal; plans NCR expansion. Curly Tales Oct 2026: 'new specialty coffee and all-day cafe in Gurgaon… design-led space'. | S30: Already multi-origin buyer — add your estate; future NCR outlets. | T30: Walk-in / Google Maps listing | AB30: Tisha Aggarwal (founder) | AC30: https://www.restaurantindia.in/news/oro-opens-flagship-specialty-coffee-caf-in-gurugram.n17284 | AD30: Instagram not indexed by search yet — look up by name on Instagram | AE30: Indian origins/estates: Tamil Nadu; Brew: Pour over, Cold brew | AG30: 2 of 2 read: https://www.restaurantindia.in/news/oro-opens-flagship-specialty-coffee-caf-in-gurugram.n17284 https://indianretailer.com/franchisetv/archives/news/specialty-coffee-brand-oro-opens-flagship-cafe-gurugram
A31: C213 | B31: A | C31: New (opened 2026) | D31: Premium | E31: Lumie — Fine Bakes & Speciality Coffee | F31: Bakery / patisserie cafe | G31: North | H31: Uttar Pradesh | I31: Lucknow | K31: Unknown | L31: Not published | M31: Not published — ask on first contact (look at the retail shelf / bag on the bar) | P31: Rotating single-estate / micro-lot for the filter bar + a single-origin espresso option. | Q31: Just opened: offer a guest-lot month + free barista calibration; side-by-side cupping against their current beans; ask which roaster/estates they use and what they'd change. | R31: Newer spot: croissants, desserts, specialty coffee (Knocksense). | T31: Walk-in / Google Maps listing | AC31: https://www.knocksense.com/lucknow/5-new-coffee-spots-in-lucknow-worth-adding-to-your-caf%C3%A9-hopping-list | AD31: Wave 4: not found in a web search beyond its source roundup — confirm it is open (Instagram / Google Maps) before outreach. | AG31: 0 of 1 read:
A32: C214 | B32: A | C32: New (opened 2026) | D32: Premium | E32: One PourCent | F32: Independent specialty cafe | G32: North | H32: Uttar Pradesh | I32: Lucknow | J32: Satya Tower, Vibhuti Khand, Gomti Nagar | K32: Unknown | L32: Known for cold coffee; reviews mixed on espresso. | M32: Not published — ask on first contact (look at the retail shelf / bag on the bar) | P32: Rotating single-estate / micro-lot for the filter bar + a single-origin espresso option. | Q32: Just opened: offer a guest-lot month + free barista calibration; side-by-side cupping against their current beans; ask which roaster/estates they use and what they'd change. | R32: Just opened (Jan 2026): coffee 'tested, tasted and trusted' (Knocksense). | T32: Walk-in / Google Maps listing | AC32: https://www.knocksense.com/lucknow/5-new-coffee-spots-in-lucknow-worth-adding-to-your-caf%C3%A9-hopping-list | AE32: ₹ 1200 for two; Signals: Coming soon | AG32: 3 of 4 read: https://www.eazydiner.com/lucknow/one-pourcent-gomti-nagar-lucknow-712033 https://www.knocksense.com/lucknow/5-new-coffee-spots-in-lucknow-worth-adding-to-your-caf%C3%A9-hopping-list https://www.knocksense.com/lucknow/5-new-coffee-spots-in-lucknow-worth-adding-to-your-café-hopping-list
A33: C250 | B33: A | C33: New (opened 2026) | D33: Premium | E33: Flameback Cafe & Kitchen | F33: All-day / food-led cafe | G33: East | H33: West Bengal | I33: Kolkata | J33: Purna Das Rd (25 seats) + new Tilak Rd outpost near Lake Mall (1,000 sq ft) | K33: Unknown | L33: Ethiopian Guji-grade and Colombian brews; specialty teas (second-flush Darjeeling, Risheehat Muscatel). | M33: Not published — ask on first contact (look at the retail shelf / bag on the bar) | O33: Coffee roster is 100% imported. | P33: Indian single estates — Northeast / Darjeeling-region coffee fits a Kolkata tea-and-coffee story. | Q33: Second outlet just opened — pitch an Indian estate for the Tilak Road menu. | R33: Original 500 sq ft cafe opened 2025; t2 'New cafe alert' on 1,000 sq ft Tilak Road extension. | S33: Expanding + imports beans — pitch Indian single estates. | T33: Walk-in / Google Maps listing | AB33: Shriti Pattanayak (owner) | AC33: https://t2online.in/goodlife/food-beverage/flameback-cafe---kitchen-is-where-global-flavours-pair-up-with-world-coffee--t2-checked-it-out/2001719 | AD33: Instagram not indexed by search yet — look up by name on Instagram | AE33: Imported origins: Ethiopia, Guji, Colombia; ₹800 for two | AG33: 2 of 2 read: https://t2online.in/goodlife/food-beverage/flameback-cafe---kitchen-is-where-global-flavours-pair-up-with-world-coffee--t2-checked-it-out/2001719 https://t2online.in/goodlife/food-beverage/new-cafe-alert--why-flameback-s-cozy-tilak-road-outpost-is-the-ultimate-hangout-spot-for-your-squad/2006388
A34: C007 | B34: A | C34: New (opened 2026) | D34: Normal | E34: Brevé (Running Late by Brevé) | F34: Independent specialty cafe | G34: West | H34: Maharashtra | I34: Mumbai | J34: Brevé 2.0, Shop G-2 Mount Apartment, St John Baptist Rd, Bandra W | K34: Unknown | L34: Espresso-led specialty menu alongside build-your-own breakfast boards; 36 seats; runs Mumbai's first cafe-led run club ('Running Late'). | M34: Not published — ask on first contact (look at the retail shelf / bag on the bar) | N34: ~₹1,000 for two | P34: Co-branded run-club blend, post-run cold brew, retail bags for the community. | Q34: Pitch a 'post-run' cold brew + a rotating single estate; offer to sponsor a run-club morning with a tasting of 3 Indian estates. | R34: 36-seat flagship built around 'Mumbai's first cafe-led run club'; Brevé Bakery (Bandra W) and 'Basque by breve' also hiring baristas — expanding. | T34: Walk-in / Google Maps listing | AB34: Usman & Farhaz Bhadelia (founders) | AC34: https://www.restaurantindia.in/news/restaurant-india-news-brev-opens-new-flagship-caf-in-bandra-expands-community-focused-coffee-concept.n16397 | AE34: Brew: Cold brew; ₹1000 for two | AG34: 3 of 3 read: https://www.restaurantindia.in/news/restaurant-india-news-brev-opens-new-flagship-caf-in-bandra-expands-community-focused-coffee-concept.n16397 https://www.freepressjournal.in/lifestyle/build-your-own-breakfast-board-at-mumbais-newest-caf-run-club-brev-20-that-doesnt-compromise-on-protein-calories https://curlytales.com/bandras-cafe-breve-is-where-your-gym-goals-and-cake-cravings-finally-shake-hands/
A35: C008 | B35: A | C35: New (opened 2026) | D35: Normal | E35: Cocoa & Katli | F35: Bakery / patisserie cafe | G35: West | H35: Maharashtra | I35: Mumbai | J35: Malad (1,050 sq ft) | K35: Unknown | L35: Specialty coffee paired with 'mindful' low-sugar desserts; coffee details not published. | M35: Not published — ask on first contact (look at the retail shelf / bag on the bar) | P35: Premium house espresso blend of Indian estates + one rotating single estate + cold-brew lot. | Q35: Just opened: offer a guest-lot month + free barista calibration; side-by-side cupping against their current beans; ask which roaster/estates they use and what they'd change. | R35: Launched 21 Oct 2026 by Harsh Kedia & Arihant Jain; specialty coffee programme alongside desserts and all-day menu. | S35: Brand-new — still fixing suppliers; pitch a house espresso blend of Indian estates. | T35: Instagram DM | U35: @cocoaandkatli | V35: https://www.instagram.com/cocoaandkatli/ | AB35: Harsh Kedia (chef) & Arihant Jain | AC35: https://aninews.in/news/business/harsh-kedia-and-arihant-jain-launch-cocoa-amp-katli-a-caf233-that-redefines-mindful-indulgence-for-the-conscious-mumbaikar20261021121947/ | AD35: Instagram not indexed by search yet — look up by name on Instagram | AE35: Imported origins: Vietnam | AG35: 2 of 3 read: https://theprint.in/ani-press-releases/harsh-kedia-and-arihant-jain-launch-cocoa-katli-a-cafe-that-redefines-mindful-indulgence-for-the-conscious-mumbaikar/3077520/ https://curlytales.com/india/food/coffee-desserts-mindful-indulgence-harsh-kedia-aka-a-diabetic-chef-opens-new-cafe-in-malad/
A36: C009 | B36: A | C36: New (opened 2026) | D36: Normal | E36: Javaphile | F36: Cafe chain / multi-outlet | G36: West | H36: Maharashtra | I36: Mumbai | J36: Worli flagship (Jan 2026) + Pali Hill, Bandra; sister venue Shelter (Versova) | K36: Unknown | L36: Espresso drinks + flavoured cold brews (citrus, elderflower, sweet lime, cucumber-cream) + manual brews (Chemex, AeroPress, pour-over). | M36: Not published — ask on first contact (look at the retail shelf / bag on the bar) | O36: Roaster not named; flavoured cold brews suit a dedicated cold-brew lot. | P36: Premium house espresso blend of Indian estates + one rotating single estate + cold-brew lot. | Q36: Group pitch across Javaphile Worli, Pali Hill and Shelter: one cold-brew lot + one manual-brew single estate. | R36: Comfort-first cafe focused on great coffee (Foodies of India, Jan 2026). | T36: Walk-in / Google Maps listing | AC36: https://www.restaurantindia.in/news/restaurant-india-news-javaphile-caf-opens-in-worli-mumbai.n14931 | AG36: 3 of 4 read: https://www.restaurantindia.in/news/restaurant-india-news-javaphile-caf-opens-in-worli-mumbai.n14931 https://www.cosmopolitan.in/life/features/story/this-worli-cafe-is-all-about-comfort-caffeine-and-slow-sips-1338113-2026-01-29 https://www.indianretailer.com/news/javaphile-cafe-arrives-worli-deepens-footprint-mumbai
A37: C010 | B37: A | C37: New (opened 2026) | D37: Normal | E37: Pouring Veranda | F37: Independent specialty cafe | G37: West | H37: Maharashtra | I37: Mumbai | J37: Andheri | K37: Unknown | L37: Not published | M37: Not published — ask on first contact (look at the retail shelf / bag on the bar) | P37: Premium house espresso blend of Indian estates + one rotating single estate + cold-brew lot. | Q37: Just opened: offer a guest-lot month + free barista calibration; side-by-side cupping against their current beans; ask which roaster/estates they use and what they'd change. | R37: Listed under 'New Cafes in Andheri' (Foodies of India, Apr 2026). | T37: Walk-in / Google Maps listing | AC37: https://foodiesofindia.wordpress.com/2026/04/02/20-new-restaurants-in-mumbai-to-check-out-april-2026/ | AD37: Wave 4: not found in a web search beyond its source roundup — confirm it is open (Instagram / Google Maps) before outreach. | AG37: 1 of 2 read: https://foodiesofindia.wordpress.com/2026/04/02/20-new-restaurants-in-mumbai-to-check-out-april-2026/
A38: C011 | B38: A | C38: New (opened 2026) | D38: Normal | E38: Rola | F38: All-day / food-led cafe | G38: West | H38: Maharashtra | I38: Mumbai | J38: Pali Hill, Bandra (opened 17 Aug 2026; 70 seats) | K38: Unknown | L38: Flat white, Spanish latte, coffee tonic, mochas; outdoor coffee cart at the entrance. | M38: Not published — ask on first contact (look at the retail shelf / bag on the bar) | N38: ~₹2,000 for two | O38: No filter or single-origin line. | P38: Single-estate tonic / filter line + espresso blend for the cart. | Q38: Offer a cart-friendly espresso blend + one single estate for tonic drinks; propose a cart 'estate of the month'. | R38: All-day diner opened 17 Aug 2026; 70 covers; specialty coffee programme + outdoor coffee cart. | T38: Walk-in / Google Maps listing | AB38: Puneet Anand (Anandvan Resort) | AC38: https://indianretailer.com/news/rola-opens-new-all-day-diner-bandra | AE38: Brew: Flat white, Affogato | AG38: 2 of 2 read: https://indianretailer.com/news/rola-opens-new-all-day-diner-bandra https://www.esquireindia.co.in/food-and-drinks/what-to-eat/from-rola-to-the-mahjong-club-9-new-restaurants-and-cafés-in-mumbai-to-try-this-september
A39: C157 | B39: A | C39: New (opened 2026) | D39: Normal | E39: The Usual | F39: Independent specialty cafe | G39: North | H39: Rajasthan | I39: Jaipur | K39: Unknown | L39: Craft coffee + fruit matchas; sea-salt caramel and burnt-butter lattes; cranberry espresso tonic. | M39: Not published — ask on first contact (look at the retail shelf / bag on the bar) | P39: Premium house espresso blend of Indian estates + one rotating single estate + cold-brew lot. | Q39: Just opened: offer a guest-lot month + free barista calibration; side-by-side cupping against their current beans; ask which roaster/estates they use and what they'd change. | R39: Featured in Outlook Traveller's 'Jaipur is entering its coffee smart era' (Aug 2026). | T39: Walk-in / Google Maps listing | AB39: Dhyaan Kaur (founder) | AC39: https://oteats.outlooktraveller.com/features/guides/jaipur-is-entering-its-coffee-smart-era-and-these-spots-prove-it | AD39: Details thin | AE39: Brew: Espresso tonic | AG39: 1 of 1 read: https://oteats.outlooktraveller.com/features/guides/jaipur-is-entering-its-coffee-smart-era-and-these-spots-prove-it
A40: C173 | B40: A | C40: New (opened 2026) | D40: Normal | E40: CUP | F40: Independent specialty cafe | G40: North | H40: Delhi | I40: New Delhi | J40: Coffee Under Palms — Oasis Bhawan LSC, Vasant Kunj | K40: Unknown | L40: Speciality Arabica; citrusy coffee-and-soda signature; menu still rolling out. | M40: Not published — ask on first contact (look at the retail shelf / bag on the bar) | N40: ~₹1,000 for two | P40: Premium house espresso blend of Indian estates + one rotating single estate + cold-brew lot. | Q40: Just opened: offer a guest-lot month + free barista calibration; side-by-side cupping against their current beans; ask which roaster/estates they use and what they'd change. | R40: New slow-paced cafe (Outlook Traveller Feb 2026 openings). | S40: New — blend + filter. | T40: Walk-in / Google Maps listing | AC40: https://www.oteats.outlooktraveller.com/features/guides/delhis-newest-openings-that-you-must-look-out-for-this-february | AD40: Instagram not indexed by search yet — look up by name on Instagram | AG40: 0 of 1 read:
A41: C175 | B41: A | C41: New (opened 2026) | D41: Normal | E41: Lizzu | F41: Coffee + cocktail bar | G41: North | H41: Delhi | I41: New Delhi | J41: No. 18, Lodhi Colony Market (9 am–1 am) | K41: Unknown | L41: Espresso programme + wines on nitrogen + cocktails; Sicilian/Levantine food. | M41: Not published — ask on first contact (look at the retail shelf / bag on the bar) | P41: Premium house espresso blend of Indian estates + one rotating single estate + cold-brew lot. | Q41: Just opened: offer a guest-lot month + free barista calibration; side-by-side cupping against their current beans; ask which roaster/estates they use and what they'd change. | R41: All-day cafe + wine bar: specialty coffee, breads, wine, cocktails (Curly Tales Sep 2026; Lab Mag Oct 2026). | T41: Walk-in / Google Maps listing | AC41: https://www.thelabmagofficial.com/new-tables-for-october-the-delhi-ncr-restaurants-cafes-and-bars-to-try/ | AG41: 2 of 2 read: https://www.thelabmagofficial.com/new-tables-for-october-the-delhi-ncr-restaurants-cafes-and-bars-to-try/ https://www.restaurantindia.in/news/lizzu-opens-in-lodhi-colony-with-all-day-caf-and-wine-bar-format.n17228
A42: C176 | B42: A | C42: New (opened 2026) | D42: Normal | E42: Off Mrkt | F42: All-day / food-led cafe | G42: North | H42: Delhi | I42: New Delhi | J42: Green Park | K42: Unknown | L42: Not published | M42: Not published — ask on first contact (look at the retail shelf / bag on the bar) | P42: Premium house espresso blend of Indian estates + one rotating single estate + cold-brew lot. | Q42: Just opened: offer a guest-lot month + free barista calibration; side-by-side cupping against their current beans; ask which roaster/estates they use and what they'd change. | R42: All-day spot with specialty coffee and creative bakes (Lab Mag, 1 Sep 2026). | T42: Walk-in / Google Maps listing | AC42: https://www.thelabmagofficial.com/new-restaurants-cafes-and-bars-to-try-across-india-this-september/ | AD42: Wave 4: not found in a web search beyond its source roundup — confirm it is open (Instagram / Google Maps) before outreach. | AG42: 1 of 1 read: https://www.thelabmagofficial.com/new-restaurants-cafes-and-bars-to-try-across-india-this-september/
A43: C200 | B43: A | C43: New (opened 2026) | D43: Normal | E43: Kokoy | F43: All-day / food-led cafe | G43: North | H43: Haryana | I43: Gurugram | J43: Plot 703, Sector 23 (opp. Ansal Plaza), Gurugram | K43: Unknown | L43: Chikmagalur beans; espresso, Americano, doppio, French press with customisable roasts; Cran Cran Coffee, Coffee Tonic. | M43: Not published — ask on first contact (look at the retail shelf / bag on the bar) | O43: Single region (Chikmagalur). | P43: A second region (Nilgiris / Araku / Northeast) for the French press. | Q43: Just opened: offer a guest-lot month + free barista calibration; side-by-side cupping against their current beans; ask which roaster/estates they use and what they'd change. | R43: Premium all-day cafe with specialty coffee, opened early Jan 2026. | T43: Walk-in / Google Maps listing | AC43: https://www.restaurantindia.in/news/restaurant-india-news-kokoy-launches-caf-in-gurugram-enters-premium-all-day-dining-segment.n14880 | AE43: Indian origins/estates: Chikmagalur; Brew: French press, Affogato, Flat white | AG43: 2 of 2 read: https://www.restaurantindia.in/news/restaurant-india-news-kokoy-launches-caf-in-gurugram-enters-premium-all-day-dining-segment.n14880 https://www.realshepower.in/new-coffee-cafes-delhi-ncr-2026/
A44: C201 | B44: A | C44: New (opened 2026) | D44: Normal | E44: Odd Culture | F44: Independent specialty cafe | G44: North | H44: Haryana | I44: Gurugram | J44: Unit 7, Emaar Capital Tower 2, Sector 26, Gurugram | K44: Unknown | L44: Kalita manual brews and cold brew on rotation; drinks on tap; miso coffee; fermentation-led kitchen. | M44: Not published — ask on first contact (look at the retail shelf / bag on the bar) | N44: ~₹2,000 for two; Time Out 5/5 | P44: Fermentation-process lots (anaerobic, co-ferment) that match the kitchen's ethos. | Q44: Just opened: offer a guest-lot month + free barista calibration; side-by-side cupping against their current beans; ask which roaster/estates they use and what they'd change. | R44: The Lab Mag 'New tables for October' (5 Oct 2026): new cafe, 8am–10pm. | S44: Weeks old — still choosing suppliers. | T44: Walk-in / Google Maps listing | AC44: https://www.thelabmagofficial.com/new-tables-for-october-the-delhi-ncr-restaurants-cafes-and-bars-to-try/ | AD44: Instagram not indexed by search yet — look up by name on Instagram | AE44: Brew: Kalita, Cold brew; ₹2,000 for two | AG44: 2 of 2 read: https://www.thelabmagofficial.com/new-tables-for-october-the-delhi-ncr-restaurants-cafes-and-bars-to-try/ https://www.timeout.com/delhi/restaurants/odd-culture
A45: C212 | B45: A | C45: New (opened 2026) | D45: Normal | E45: Brekka | F45: Independent specialty cafe | G45: North | H45: Uttar Pradesh | I45: Lucknow | J45: Gomti Nagar | K45: Unknown | L45: Not published | M45: Not published — ask on first contact (look at the retail shelf / bag on the bar) | P45: Premium house espresso blend of Indian estates + one rotating single estate + cold-brew lot. | Q45: Just opened: offer a guest-lot month + free barista calibration; side-by-side cupping against their current beans; ask which roaster/estates they use and what they'd change. | R45: New coffee bar with early-bird signature drinks + bakes (Knocksense). | T45: Walk-in / Google Maps listing | AC45: https://www.knocksense.com/lucknow/5-new-coffee-spots-in-lucknow-worth-adding-to-your-caf%C3%A9-hopping-list | AD45: Wave 4: not found in a web search beyond its source roundup — confirm it is open (Instagram / Google Maps) before outreach. | AG45: 0 of 1 read:
A46: C234 | B46: A | C46: New (opened 2026) | D46: Normal | E46: Batter Bar — CP67 Mohali | F46: Bakery / patisserie cafe | G46: North | H46: Punjab | I46: Mohali | J46: CP67 Mohali + Sector 7 Chandigarh | K46: Unknown | L46: Not published | M46: Not published — ask on first contact (look at the retail shelf / bag on the bar) | P46: Pastry-pairing single estates; espresso blend for 2 outlets. | Q46: Just opened: offer a guest-lot month + free barista calibration; side-by-side cupping against their current beans; ask which roaster/estates they use and what they'd change. | R46: French pastry + specialty coffee; new Mohali outlet (17 May 2026). | T46: Walk-in / Google Maps listing | AB46: Chef Abhinav Sundra (ex-Pierre Hermé) | AC46: https://realtynmore.com/batter-bar-coffee-cafe-at-cp67-mohali/ | AE46: Indian origins/estates: Punjab Real Estate; ₹800 for 2; Signals: Hiring | AG46: 3 of 3 read: https://realtynmore.com/batter-bar-coffee-cafe-at-cp67-mohali/ https://babushahi.com/trends.php?id=221174 https://shoutlo.com/restaurants/batter-bar-sector-7-chandigarh
A47: C266 | B47: A | C47: New (opened 2026) | D47: Normal | E47: BrewHaus | F47: Independent specialty cafe | G47: East | H47: Jharkhand | I47: Ranchi | K47: Unknown | L47: Not published | M47: Not published — ask on first contact (look at the retail shelf / bag on the bar) | P47: Premium house espresso blend of Indian estates + one rotating single estate + cold-brew lot. | Q47: Just opened: offer a guest-lot month + free barista calibration; side-by-side cupping against their current beans; ask which roaster/estates they use and what they'd change. | R47: Instagram bio: 'NOW OPEN!' — caffeine & coziness. | T47: Instagram DM | U47: @brewhaus.ranchi | V47: https://www.instagram.com/brewhaus.ranchi/ | AC47: https://www.instagram.com/brewhaus.ranchi/
A48: C026 | B48: B | C48: New (opened 2026) | D48: Normal | E48: Cafe Quattro — Babulnath | F48: Cafe chain / multi-outlet | G48: West | H48: Maharashtra | I48: Mumbai | J48: Babulnath (inside a theatre) + Juhu | K48: Unknown | L48: Specialty coffees, cold brews, Vietnamese coffee, coffee mocktails; all-veg. | M48: Not published — ask on first contact (look at the retail shelf / bag on the bar) | P48: Premium house espresso blend of Indian estates + one rotating single estate + cold-brew lot. | Q48: Just opened: offer a guest-lot month + free barista calibration; side-by-side cupping against their current beans; ask which roaster/estates they use and what they'd change. | R48: Second Mumbai cafe; vegetarian dining + specialty coffee + quick service. | S48: Food-led; pitch a dependable house blend. | T48: Walk-in / Google Maps listing | AC48: https://www.indianretailer.com/news/cafe-quattro-opens-second-mumbai-cafe-mumbai | AE48: Imported origins: Vietnam; Brew: Cold brew; ₹ 1200 for two | AG48: 3 of 3 read: https://www.eazydiner.com/mumbai/cafe-quattro-juhu-western-suburbs-707486 https://www.indianretailer.com/news/cafe-quattro-opens-second-mumbai-cafe-mumbai https://www.restaurantindia.in/news/caf-quattro-opens-second-outlet-in-babulnath-south-mumbai.n16988
A49: C027 | B49: B | C49: New (opened 2026) | D49: Normal | E49: DRNK Apartment | F49: Independent specialty cafe | G49: West | H49: Maharashtra | I49: Mumbai | J49: Andheri | K49: Unknown | L49: Matcha-led dessert coffees (s'mores latte); Time Out 4/5; Andheri outpost of Bandra's DRNK. | M49: Not published — ask on first contact (look at the retail shelf / bag on the bar) | P49: Premium house espresso blend of Indian estates + one rotating single estate + cold-brew lot. | Q49: Just opened: offer a guest-lot month + free barista calibration; side-by-side cupping against their current beans; ask which roaster/estates they use and what they'd change. | R49: Third-place cafe and matcha spot in Andheri (Man's World India restaurant update). | S49: Matcha-led; pitch espresso + filter to round out coffee side. | T49: Walk-in / Google Maps listing | AC49: https://www.mansworldindia.com/lifestyle/mw-restaurant-update-every-place-you-need-to-check-out-in-mumbai-right-now | AD49: Opening date not confirmed | AG49: 1 of 3 read: https://oteats.outlooktraveller.com/features/guides/the-coolest-new-openings-in-mumbai-you-need-to-be-on-the-lookout-for
A50: C028 | B50: B | C50: New (opened 2026) | D50: Normal | E50: Grounded | F50: Independent specialty cafe | G50: West | H50: Maharashtra | I50: Mumbai | J50: Khar | K50: Unknown | L50: Not published | M50: Not published — ask on first contact (look at the retail shelf / bag on the bar) | P50: Premium house espresso blend of Indian estates + one rotating single estate + cold-brew lot. | Q50: Just opened: offer a guest-lot month + free barista calibration; side-by-side cupping against their current beans; ask which roaster/estates they use and what they'd change. | R50: Community-driven cafe, good coffee + wholesome food (Jan 2026). | T50: Walk-in / Google Maps listing | AC50: https://foodiesofindia.wordpress.com/2026/01/15/january-2026-30-new-restaurants-cafes-in-mumbai-you-need-to-check-out/ | AE50: Signals: Now open | AG50: 2 of 3 read: https://foodiesofindia.wordpress.com/2026/01/15/january-2026-30-new-restaurants-cafes-in-mumbai-you-need-to-check-out/ https://www.indianretailer.com/restaurant/article/bandra-gets-a-new-enchanting-caf-grounded.14232
A51: C030 | B51: B | C51: New (opened 2026) | D51: Normal | E51: Linking House | F51: All-day / food-led cafe | G51: West | H51: Maharashtra | I51: Mumbai | J51: Linking Rd, Santacruz W (4,000 sq ft, 120 seats) | K51: Unknown | L51: Not published | M51: Not published — ask on first contact (look at the retail shelf / bag on the bar) | P51: Premium house espresso blend of Indian estates + one rotating single estate + cold-brew lot. | Q51: Just opened: offer a guest-lot month + free barista calibration; side-by-side cupping against their current beans; ask which roaster/estates they use and what they'd change. | R51: All-day: coffee & bakery by day, dinner & cocktails later (Esquire, Sep 2026). | T51: Walk-in / Google Maps listing | AB51: Riya Goon & Vivek Chandaliya | AC51: https://www.esquireindia.co.in/food-and-drinks/what-to-eat/from-rola-to-the-mahjong-club-9-new-restaurants-and-caf%C3%A9s-in-mumbai-to-try-this-september | AE51: Brew: Cold brew, Affogato | AG51: 2 of 2 read: https://www.esquireindia.co.in/food-and-drinks/what-to-eat/from-rola-to-the-mahjong-club-9-new-restaurants-and-caf%C3%A9s-in-mumbai-to-try-this-september https://www.restaurantindia.in/news/linking-house-opens-on-linking-road-with-120-seats-and-day-to-night-dining.n17078
A52: C031 | B52: B | C52: New (opened 2026) | D52: Normal | E52: Lygon St | F52: Independent specialty cafe | G52: West | H52: Maharashtra | I52: Mumbai | J52: Andheri | K52: Unknown | L52: Not published | M52: Not published — ask on first contact (look at the retail shelf / bag on the bar) | P52: Premium house espresso blend of Indian estates + one rotating single estate + cold-brew lot. | Q52: Just opened: offer a guest-lot month + free barista calibration; side-by-side cupping against their current beans; ask which roaster/estates they use and what they'd change. | R52: Feb 2026 opening (Foodies of India); name references Melbourne's cafe street. | T52: Walk-in / Google Maps listing | AC52: https://foodiesofindia.wordpress.com/2026/02/01/february-2026-new-restaurants-in-mumbai-you-need-to-try/ | AD52: Coffee programme not described Wave 4: not found in a web search beyond its source roundup — confirm it is open (Instagram / Google Maps) before outreach. | AG52: 1 of 1 read: https://foodiesofindia.wordpress.com/2026/02/01/february-2026-new-restaurants-in-mumbai-you-need-to-try/
A53: C035 | B53: B | C53: New (opened 2026) | D53: Normal | E53: NOT FAR | F53: Bakery / patisserie cafe | G53: West | H53: Maharashtra | I53: Mumbai | J53: Bandra | K53: No | L53: Coffee programme sourced from Corridor Seven, picked to match the cookies and cupcakes. | M53: Corridor Seven Coffee Roasters (Nagpur) | O53: Single roaster. | P53: Second roaster / seasonal guest bean. | Q53: Compare cup vs Corridor Seven at a tasting. | R53: Speciality cookies, cupcakes and coffee (Curly Tales, Jul 2026). | T53: Walk-in / Google Maps listing | AC53: https://www.restaurantindia.in/news/notfar-opens-in-bandra-with-specialty-cookies-cupcakes-and-coffee.n16686 | AG53: 0 of 1 read:
A54: C036 | B54: B | C54: New (opened 2026) | D54: Normal | E54: Namah Bengaluru Coffee House | F54: Independent specialty cafe | G54: West | H54: Maharashtra | I54: Mumbai | J54: Four Bungalows, Andheri W (7am–11:30pm) | K54: Unknown | L54: Darshini-style South Indian tiffin + filter coffee. | M54: Not published — ask on first contact (look at the retail shelf / bag on the bar) | N54: ~₹400 for two | P54: A filter-coffee blend (peaberry/robusta with optional chicory) — not single origin. | Q54: Pitch a filter-coffee decoction blend with consistent volume pricing. | R54: New coffee house (Foodies of India, Jun 2026). | T54: Instagram DM | U54: @namah.mumbai | V54: https://www.instagram.com/namah.mumbai/ | AB54: Arvind & Pallavi Shetty | AC54: https://foodiesofindia.wordpress.com/2026/06/01/june-2026-new-restaurants-in-mumbai-you-need-to-visit/ | AE54: Brew: South Indian filter; Signals: Coming soon, Now open | AG54: 3 of 4 read: https://foodiesofindia.wordpress.com/2026/06/01/june-2026-new-restaurants-in-mumbai-you-need-to-visit/ https://www.freepressjournal.in/lifestyle/food-review-we-tried-mumbais-viral-new-south-indian-spot-namah-is-it-worth-the-hype https://www.freepressjournal.in/lifestyle/narayan-rane-shreyas-talpade-others-join-star-studded-launch-of-new-south-indian-joint-in-mumbai
A55: C037 | B55: B | C55: New (opened 2026) | D55: Normal | E55: Pardon Our French | F55: Bakery / patisserie cafe | G55: West | H55: Maharashtra | I55: Mumbai | J55: Ballard Estate, Fort | K55: Unknown | L55: Parisian coffee shop (22 seats): rosemary & salted-honey cold brew, salted drinks. | M55: Not published — ask on first contact (look at the retail shelf / bag on the bar) | P55: Premium house espresso blend of Indian estates + one rotating single estate + cold-brew lot. | Q55: Approach via the consultant (Geetu Mohnani) who curated the menu — she can specify beans for other clients too. | R55: New pastry-led cafe from chef Pooja Dhingra. | S55: Patisserie pairing coffee. | T55: Walk-in / Google Maps listing | AB55: Pooja Dhingra; beverage programme by coffee consultant Geetu Mohnani | AC55: https://www.thestylelist.in/post/new-restaurants-cafes-bars-india | AE55: Indian origins/estates: Ballard Estate, Mumbai’s Ballard Estate; Brew: Cold brew; Signals: Now open | AG55: 2 of 4 read: https://thenodmag.com/content/pardon-our-french-pooja-dhingra-cafe-ballard-estate-mumbai-review https://curlytales.com/pardon-our-french-pooja-dhingra-has-a-new-cafe-in-mumbai-hint-its-not-in-bandra
A56: C038 | B56: B | C56: New (opened 2026) | D56: Normal | E56: Project Hum | F56: All-day / food-led cafe | G56: West | H56: Maharashtra | I56: Mumbai | J56: Bandra + Versova (kaviar:collaborative design) | K56: Unknown | L56: Curated specialty programme with Subko; traceable sourcing; grab-and-go window in Versova. | M56: Subko | P56: Premium house espresso blend of Indian estates + one rotating single estate + cold-brew lot. | Q56: Position as a guest single estate alongside Subko, not a replacement. | R56: In Foodies of India's Sep–Oct 2026 openings. Wave 4: Grazia/Elle Decor coverage names Subko as the coffee partner. | T56: Walk-in / Google Maps listing | AB56: Jatin Talreja (co-founder) | AC56: https://foodiesofindia.wordpress.com/tag/new-restaurants-in-mumbai/ | AD56: Coffee programme not described | AG56: 3 of 5 read: https://www.harpersbazaar.in/travel-food/story/14-new-restaurants-across-india-that-should-be-on-your-dining-list-2268 https://elledecor.in/cafe-project-hum-mumbai-by-kaviar-collaborative/ https://www.localsamosa.com/food-and-drinks/coffee-shops-in-mumbai-10068806
A57: C039 | B57: B | C57: New (opened 2026) | D57: Normal | E57: ROST | F57: Independent specialty cafe | G57: West | H57: Maharashtra | I57: Mumbai | J57: Mahesh Building, Khar W | K57: Unknown | L57: Not published | M57: Not published — ask on first contact (look at the retail shelf / bag on the bar) | P57: Premium house espresso blend of Indian estates + one rotating single estate + cold-brew lot. | Q57: Just opened: offer a guest-lot month + free barista calibration; side-by-side cupping against their current beans; ask which roaster/estates they use and what they'd change. | R57: French toast + coffee bar (Esquire, Sep 2026). | T57: Walk-in / Google Maps listing | AB57: Param Arora (co-founder) | AC57: https://www.esquireindia.co.in/food-and-drinks/what-to-eat/from-rola-to-the-mahjong-club-9-new-restaurants-and-caf%C3%A9s-in-mumbai-to-try-this-september | AE57: Indian origins/estates: Karnataka; Brew: V60, Cold brew, Affogato | AG57: 1 of 3 read: https://www.timeout.com/mumbai/restaurants/rost
A58: C040 | B58: B | C58: New (opened 2026) | D58: Normal | E58: San's in the Bay | F58: All-day / food-led cafe | G58: West | H58: Maharashtra | I58: Mumbai | J58: Kala Ghoda | K58: Unknown | L58: Not published | M58: Not published — ask on first contact (look at the retail shelf / bag on the bar) | P58: Premium house espresso blend of Indian estates + one rotating single estate + cold-brew lot. | Q58: Just opened: offer a guest-lot month + free barista calibration; side-by-side cupping against their current beans; ask which roaster/estates they use and what they'd change. | R58: Contemporary cafe serving specialty brews (2026 India openings roundup). | S58: Pitch house espresso + one rotating single estate. | T58: Walk-in / Google Maps listing | AC58: https://www.thestylelist.in/post/new-restaurants-cafes-bars-india | AD58: Single source Wave 4: not found in a web search beyond its source roundup — confirm it is open (Instagram / Google Maps) before outreach. | AG58: 0 of 1 read:
A59: C041 | B59: B | C59: New (opened 2026) | D59: Normal | E59: Vanilla Miel — Lower Parel | F59: Bakery / patisserie cafe | G59: West | H59: Maharashtra | I59: Mumbai | J59: Lodha Signet, Lower Parel (also Pali Village) | K59: Unknown | L59: Micro-roasted, low-acidity MEDIUM-DARK roast from high-altitude Chikmagalur estates; honey-cinnamon, crème-brûlée and tiramisu lattes, iced Vietnamese, vanilla-bean shakerato; orange-basil and spiced-guava cold brews; 'VM House Phin'; ceremonial matcha. | M59: Not published (Chikmagalur estates, medium-dark) | O59: One medium-dark espresso profile; no light roast or pour-over. | P59: A light/medium single estate for a filter or pour-over slot, plus a seasonal lot for dessert pairing. | Q59: Dessert-led brand: pitch a coffee-and-dessert pairing tasting at Lodha Signet and a co-branded seasonal lot. | R59: Patisserie-cafe brand's second cafe (Oct 2026). | S59: Patisserie pairing coffee. | T59: Walk-in / Google Maps listing | AB59: Isha & Mansi Shetty (founders) | AC59: https://www.restaurantindia.in/news/vanilla-miel-opens-second-mumbai-caf-at-lodha-signet-lower-parel.n17346 | AE59: Indian origins/estates: Chikmagalur; Imported origins: Vietnam; Processes / format: Experimental lot, Single origin; Brew: Cold brew, Cortado, Tasting flight / omakase; ₹2,000 for two; Signals: Wholesale / cafe partners | AG59: 4 of 4 read: https://curlytales.com/india/food/new-mumbai-restaurants-in-october-youll-want-to-tell-your-friends-about/ https://www.restaurantindia.in/news/vanilla-miel-opens-second-mumbai-caf-at-lodha-signet-lower-parel.n17346 https://luxebook.in/?p=82147 https://finelychopped.net/?p=75976
A60: C101 | B60: B | C60: New (opened 2026) | D60: Normal | E60: Crush Coffee | F60: Cafe chain / multi-outlet | G60: West | H60: Gujarat | I60: Rajkot / Surat | J60: DMD Pacific, Vesu Canal Rd, Surat | K60: Unknown | L60: Not published | M60: Not published — ask on first contact (look at the retail shelf / bag on the bar) | P60: Premium house espresso blend of Indian estates + one rotating single estate + cold-brew lot. | Q60: Just opened: offer a guest-lot month + free barista calibration; side-by-side cupping against their current beans; ask which roaster/estates they use and what they'd change. | R60: Brand site says ESTD 2026 with stores in Rajkot and Vesu. | S60: New multi-city brand — house blend. | T60: Website contact form | W60: https://crushcoffee.vercel.app/ | AC60: https://crushcoffee.vercel.app/ | AD60: Brand website only Wave 4: no Rajkot outlet found. | AE60: Processes / format: House blend | AF60: thecrushcafe07@gmail.com · +91 83206 12851 | AG60: 1 of 2 read: https://crushcoffee.vercel.app/
A61: C127 | B61: B | C61: New (opened 2026) | D61: Normal | E61: AAMI Café & Bistro | F61: All-day / food-led cafe | G61: West | H61: Goa | I61: Candolim | K61: Unknown | L61: Not published | M61: Not published — ask on first contact (look at the retail shelf / bag on the bar) | P61: Premium house espresso blend of Indian estates + one rotating single estate + cold-brew lot. | Q61: Just opened: offer a guest-lot month + free barista calibration; side-by-side cupping against their current beans; ask which roaster/estates they use and what they'd change. | R61: New all-day cafe; espresso spritz and house cold coffee. | T61: Walk-in / Google Maps listing | AC61: https://www.restaurantindia.in/news/restaurant-india-news-aami-caf-bistro-opens-its-doors-in-candolim-goa.n16290 | AG61: 1 of 1 read: https://www.restaurantindia.in/news/restaurant-india-news-aami-caf-bistro-opens-its-doors-in-candolim-goa.n16290
A62: C132 | B62: B | C62: New (opened 2026) | D62: Normal | E62: Affo — Santa Inez | F62: Independent specialty cafe | G62: West | H62: Goa | I62: Panjim | J62: Santa Inez | K62: Unknown | L62: Not published | M62: Not published — ask on first contact (look at the retail shelf / bag on the bar) | P62: Premium house espresso blend of Indian estates + one rotating single estate + cold-brew lot. | Q62: Just opened: offer a guest-lot month + free barista calibration; side-by-side cupping against their current beans; ask which roaster/estates they use and what they'd change. | R62: Gelato-and-coffee spot that moved to Santa Inez in 2026. | T62: Walk-in / Google Maps listing | AC62: https://travellerscoop.com/must-try-new-restaurants-in-goa-openings/ | AD62: Wave 4: not found in a web search beyond its source roundup — confirm it is open (Instagram / Google Maps) before outreach. | AG62: 1 of 1 read: https://travellerscoop.com/must-try-new-restaurants-in-goa-openings/
A63: C162 | B63: B | C63: New (opened 2026) | D63: Normal | E63: Cafe Nola — Jaipur | F63: All-day / food-led cafe | G63: North | H63: Rajasthan | I63: Jaipur | J63: Jawahar Lal Nehru Marg | K63: Unknown | L63: Organic Indian beans incl. Araku Valley in signature coffee sauces; Jaipur's first cold-foam programme. | M63: Not published — ask on first contact (look at the retail shelf / bag on the bar) | O63: No Karnataka, Northeast or Odisha coffees. | P63: Seasonal guest estate; organic-certified lots if available. | Q63: Brand is multi-city (entered Jaipur Mar 2026) — pitch central procurement. | R63: Mar 2026 entry; food-led cafe with coffee/bakery programme, cold-foam coffee menu. | S63: Blend + cold brew. | T63: Walk-in / Google Maps listing | AB63: Sanjeet Walia (coffee programme) | AC63: https://oteats.outlooktraveller.com/features/guides/jaipur-is-entering-its-coffee-smart-era-and-these-spots-prove-it | AG63: 0 of 4 read:
A64: C182 | B64: B | C64: New (opened 2026) | D64: Normal | E64: Cafe Sandoz | F64: Cafe chain / multi-outlet | G64: North | H64: Delhi | I64: New Delhi | J64: Rajouri Garden Ring Rd flagship + Connaught Place (N-7) | K64: Unknown | L64: 'Artisanal coffees use beans sourced from Italy.' | M64: Not published — ask on first contact (look at the retail shelf / bag on the bar) | O64: Imported Italian beans. | P64: An Indian espresso blend matched to an Italian profile (medium-dark, chocolatey, robusta-backed). | Q64: Import-replacement pitch: cupping vs their Italian beans on cost and freshness. | R64: New cafe with artisanal coffee, comfort food, desserts, cocktails (Aug 2026). | S64: Blend. | T64: Walk-in / Google Maps listing | AC64: https://www.thelabmagofficial.com/best-new-restaurants-cafes-bars-in-india-to-visit-in-august-2026/ | AG64: 3 of 4 read: https://www.thelabmagofficial.com/best-new-restaurants-cafes-bars-in-india-to-visit-in-august-2026/ https://indianretailer.com/franchisetv/archives/news/cafe-sandoz-strengthens-delhi-footprint-new-lifestyle-cafe-rajouri-garden https://www.restaurantindia.in/news/cafe-sandoz-launches-new-outlet-at-rajouri-garden-ring-road-new-delhi.n16734
A65: C184 | B65: B | C65: New (opened 2026) | D65: Normal | E65: FES Cafe & Desserts | F65: Cafe chain / multi-outlet | G65: North | H65: Delhi | I65: New Delhi | J65: Meherchand Market; cookie flagship at Lodhi Art District; Galleria Market (Gurugram) | K65: Unknown | L65: Dessert-first cafe chain; coffee secondary; 'Coffee Raves'; 'ethically sourced coffee' at an event. | M65: Not published — ask on first contact (look at the retail shelf / bag on the bar) | P65: Premium house espresso blend of Indian estates + one rotating single estate + cold-brew lot. | Q65: Funded, expanding and hiring coffee talent: pitch a house espresso + one single estate at chain pricing before a supplier is locked in. | R65: Cookie-focused flagship with shaken coffees (Jun 2026). Wave 4b: raised ~$1M pre-Series A (12 Flags) for Delhi NCR expansion and hired a former Blue Tokai executive (World Coffee Portal). | T65: Walk-in / Google Maps listing | AB65: Vidur Mayor (founder) | AC65: https://www.worldcoffeeportal.com/news/indias-fes-cafe-appoints-former-blue-tokai-executive-following-1m-fundraise/ | AG65: 0 of 3 read:
A66: C186 | B66: B | C66: New (opened 2026) | D66: Normal | E66: T's Tiramisu | F66: Bakery / patisserie cafe | G66: North | H66: Delhi | I66: New Delhi | J66: Panchsheel Park | K66: Unknown | L66: Not published | M66: Not published — ask on first contact (look at the retail shelf / bag on the bar) | P66: Premium house espresso blend of Indian estates + one rotating single estate + cold-brew lot. | Q66: Just opened: offer a guest-lot month + free barista calibration; side-by-side cupping against their current beans; ask which roaster/estates they use and what they'd change. | R66: Small cafe pairing tiramisu with filter coffee (The Lab Mag, Oct 2026). | S66: Filter-coffee single estate. | T66: Walk-in / Google Maps listing | AC66: https://www.thelabmagofficial.com/new-tables-for-october-the-delhi-ncr-restaurants-cafes-and-bars-to-try/ | AD66: Wave 4: not found in a web search beyond its source roundup — confirm it is open (Instagram / Google Maps) before outreach. | AE66: Brew: South Indian filter | AG66: 1 of 1 read: https://www.thelabmagofficial.com/new-tables-for-october-the-delhi-ncr-restaurants-cafes-and-bars-to-try/
A67: C204 | B67: B | C67: New (opened 2026) | D67: Normal | E67: Ammy's Coffee — Galleria Market | F67: Cafe chain / multi-outlet | G67: North | H67: Haryana | I67: Gurugram | J67: Punjabi Bagh, SDA, Galleria (Aug 2025), GK | K67: Unknown | L67: Not published | M67: Not published — ask on first contact (look at the retail shelf / bag on the bar) | P67: Premium house espresso blend of Indian estates + one rotating single estate + cold-brew lot. | Q67: Just opened: offer a guest-lot month + free barista calibration; side-by-side cupping against their current beans; ask which roaster/estates they use and what they'd change. | R67: New outlet listed in LBB #NewInTown (Oct 2026). | S67: Growing brand — blend supply. | T67: Walk-in / Google Maps listing | AB67: Amar Preet Singh (co-founder) | AC67: https://lbb.in/delhi/best-restaurants-cafes-delhi/ | AE67: Brew: Cold brew | AG67: 2 of 2 read: https://lbb.in/delhi/best-restaurants-cafes-delhi/ https://www.restaurantindia.in/news/restaurant-india-news-ammy-s-coffee-expands-to-galleria-gurgaon-gk-new-delhi.n13541
A68: C205 | B68: B | C68: New (opened 2026) | D68: Normal | E68: ButterHands cafe | F68: Cafe chain / multi-outlet | G68: North | H68: Haryana | I68: Gurugram | J68: Select Citywalk, Saket (flagship) + Galleria Market (Sep 2026) + DLF Summit Plaza (mid-Sep 2026), Gurugram; began at 32nd Avenue | K68: Unknown | L68: NY-style stuffed cookies + coffee; 'ButterBrew' = South Indian filter-kaapi cold brew. | M68: Not published — ask on first contact (look at the retail shelf / bag on the bar) | P68: A single-estate cold-brew lot (or a filter-kaapi-style blend) for ButterBrew. | Q68: Fast-growing 3-outlet dessert chain: pitch the cold-brew lot. | R68: Cookie-and-coffee cafe (The Lab Mag, Oct 2026). | S68: Blend. | T68: Walk-in / Google Maps listing | AB68: Melt House founders | AC68: https://indianretailer.com/news/butterhands-makes-delhi-ncr-debut-flagship-store-saket | AE68: Brew: Cold brew, South Indian filter | AG68: 4 of 4 read: https://www.thelabmagofficial.com/new-tables-for-october-the-delhi-ncr-restaurants-cafes-and-bars-to-try/ https://www.passionateinmarketing.com/?p=760546 https://indianretailer.com/news/butterhands-makes-delhi-ncr-debut-flagship-store-saket https://www.restaurantindia.in/news/restaurant-india-news-butterhands-debuts-at-select-citywalk-as-melt-house-founders-expand-dessert.n14869
A69: C217 | B69: B | C69: New (opened 2026) | D69: Normal | E69: Coffee Terminal 2 | F69: Independent specialty cafe | G69: North | H69: Uttar Pradesh | I69: Lucknow | J69: 2nd floor above Axis Bank, Vijay Khand, Gomti Nagar | K69: Unknown | L69: Not published | M69: Not published — ask on first contact (look at the retail shelf / bag on the bar) | N69: ~₹1,000 for two; EazyDiner 4.7 (187) | P69: Premium house espresso blend of Indian estates + one rotating single estate + cold-brew lot. | Q69: Just opened: offer a guest-lot month + free barista calibration; side-by-side cupping against their current beans; ask which roaster/estates they use and what they'd change. | R69: New coffee spot, 11:30am–11pm (Knocksense). | T69: Walk-in / Google Maps listing | AC69: https://www.knocksense.com/lucknow/5-new-coffee-spots-in-lucknow-worth-adding-to-your-caf%C3%A9-hopping-list | AE69: Signals: Coming soon | AG69: 2 of 3 read: https://www.knocksense.com/lucknow/5-new-coffee-spots-in-lucknow-worth-adding-to-your-caf%C3%A9-hopping-list https://www.knocksense.com/lucknow/5-new-coffee-spots-in-lucknow-worth-adding-to-your-café-hopping-list
A70: C227 | B70: B | C70: New (opened 2026) | D70: Normal | E70: Kohi — The Cafe | F70: Independent specialty cafe | G70: North | H70: Punjab | I70: Amritsar (verify) | J70: Ranjit Avenue (EazyDiner) | K70: Unknown | L70: Not published | M70: Not published — ask on first contact (look at the retail shelf / bag on the bar) | P70: Premium house espresso blend of Indian estates + one rotating single estate + cold-brew lot. | Q70: Just opened: offer a guest-lot month + free barista calibration; side-by-side cupping against their current beans; ask which roaster/estates they use and what they'd change. | R70: 'Newest hidden gem (2026)', European-style interiors. | T70: Walk-in / Google Maps listing | AC70: https://zipbiz.in/hidden-cafes-chandigarh-mohali/ | AD70: Single listing Wave 4: the only listing found is in Amritsar, not Mohali. | AE70: Brew: Flat white; Prices: Coffee Cottage Kansal ⭐4.9 ₹400-600 Coffee, Pets Flat White 099886 13030 | The Hedgehog Sector 7C ⭐4.3 ₹200-1000 Books, Breakfast Cold Coffee 0172 473 0478 | Kamaa Café Sector 7C ⭐4.6 ₹600-1800 Bar, Late Night Tandoori Platter 098557 77080; ₹ 1000 for two | AG70: 2 of 2 read: https://www.eazydiner.com/amritsar/kohi-the-cafe-ranjit-avenue-amritsar-696155 https://zipbiz.in/hidden-cafes-chandigarh-mohali/
A71: C056 | B71: C | C71: New (opened 2026) | D71: Premium | E71: Angry Toast | F71: Roaster-cafe (roasts in-house) | G71: West | H71: Maharashtra | I71: Mumbai | J71: Waterfield Rd, Bandra W (450 sq ft; opened 16 Jul 2026) | K71: Yes — in-house micro-roastery | L71: On-site micro-roastery; hot and cold coffee, cold brew, matcha, taro latte; 3-inch sandwiches sold in pairs. | M71: Own roastery (micro-roastery) | P71: Green coffee / guest lots for its micro-roastery. | Q71: They roast: pitch green lots to the coffee lead. | R71: Sandwich shop + micro-roastery, opened 16 Jul 2026; coffee led by a WBC semi-finalist. | T71: Walk-in / Google Maps listing | AB71: Blabber Hospitality; Suhas Dwarakanath (coffee lead, WBC semi-finalist) | AC71: https://www.timeout.com/mumbai/news/angry-toast-bandras-new-sandwich-shop-has-its-own-coffee-roastery-071626 | AE71: Indian origins/estates: Coorg / Kodagu, Wayanad; Imported origins: Vietnam; Brew: Cold brew; Signals: Coming soon | AG71: 2 of 2 read: https://www.timeout.com/mumbai/news/angry-toast-bandras-new-sandwich-shop-has-its-own-coffee-roastery-071626 https://homegrown.co.in/homegrown-explore/angry-toast-opens-in-bandra-with-3-inch-sandwiches-an-in-house-coffee-roastery
A72: C047 | B72: C | C72: New (opened 2026) | D72: Normal | E72: AlienKind | F72: Cafe chain / multi-outlet | G72: West | H72: Maharashtra | I72: Mumbai | J72: Andheri | K72: Unknown | L72: Bengaluru UFO-burger QSR (5 BLR + 4 DEL); coffee drinks such as The Cloudy. | M72: Not published — ask on first contact (look at the retail shelf / bag on the bar) | P72: Premium house espresso blend of Indian estates + one rotating single estate + cold-brew lot. | Q72: Just opened: offer a guest-lot month + free barista calibration; side-by-side cupping against their current beans; ask which roaster/estates they use and what they'd change. | R72: Immersive cafe (Aug 2026). | T72: Walk-in / Google Maps listing | AC72: https://foodiesofindia.wordpress.com/2026/08/04/new-restaurants-cafes-in-mumbai-august-2026/ | AE72: Commodity brands: Nespresso | AG72: 3 of 3 read: https://foodiesofindia.wordpress.com/2026/08/04/new-restaurants-cafes-in-mumbai-august-2026/ https://www.restaurantindia.in/news/alienkind-opens-its-biggest-outlet-in-mumbais-oshiwara.n16757 https://indianretailer.com/news/alienkind-expands-retail-presence-first-mumbai-outlet
A73: C048 | B73: C | C73: New (opened 2026) | D73: Normal | E73: Belsta Coffee | F73: Independent specialty cafe | G73: West | H73: Maharashtra | I73: Mumbai | J73: Scooter (Activa) coffee stall, Union Park / Carter Rd, Bandra (from 7:30 pm) | K73: Unknown | L73: Espresso, Vietnamese shakerato, mochas, lattes from a scooter; vegan milk. | M73: Not published — ask on first contact (look at the retail shelf / bag on the bar) | N73: Espresso ₹67, cappuccino ₹97, max ₹137 | O73: Very low price point — a premium single estate would not fit the margin. | P73: Premium house espresso blend of Indian estates + one rotating single estate + cold-brew lot. | Q73: Just opened: offer a guest-lot month + free barista calibration; side-by-side cupping against their current beans; ask which roaster/estates they use and what they'd change. | R73: Coffee-focused opening (Foodies of India, Feb 2026). | T73: Walk-in / Google Maps listing | AB73: Suraj Kumar | AC73: https://foodiesofindia.wordpress.com/2026/02/01/february-2026-new-restaurants-in-mumbai-you-need-to-try/ | AD73: Wave 4: a coffee cart, not a cafe — kept as a low-volume Normal lead. | AE73: Prices: Serving Cappuccinos Starting At ₹67, Mumbai’s Cutest Coffee Spot Runs On An Activa! | London For The 1st Time Suraj is serving espresso for just ₹67 and cappuccino that | r just ₹67 and cappuccino that will blow your mind for just ₹97. His limited coffee | AG73: 2 of 2 read: https://foodiesofindia.wordpress.com/2026/02/01/february-2026-new-restaurants-in-mumbai-you-need-to-try/ https://curlytales.com/india/food/serving-cappuccinos-starting-at-mumbais-cutest-coffee-spot-runs-on-an-activa/
A74: C051 | B74: C | C74: New (opened 2026) | D74: Normal | E74: Fold Bakehouse | F74: Bakery / patisserie cafe | G74: West | H74: Maharashtra | I74: Mumbai | J74: Bandra | K74: Unknown | L74: Not published | M74: Not published — ask on first contact (look at the retail shelf / bag on the bar) | P74: Premium house espresso blend of Indian estates + one rotating single estate + cold-brew lot. | Q74: Just opened: offer a guest-lot month + free barista calibration; side-by-side cupping against their current beans; ask which roaster/estates they use and what they'd change. | R74: Jul 2026 opening. | T74: Walk-in / Google Maps listing | AC74: https://foodiesofindia.wordpress.com/2026/07/01/new-restaurants-in-mumbai-july-2026-roundup/ | AD74: Wave 4: not found in a web search beyond its source roundup — confirm it is open (Instagram / Google Maps) before outreach. | AG74: 1 of 1 read: https://foodiesofindia.wordpress.com/2026/07/01/new-restaurants-in-mumbai-july-2026-roundup/
A75: C052 | B75: C | C75: New (opened 2026) | D75: Normal | E75: GOAT Brew | F75: Coffee + cocktail bar | G75: West | H75: Maharashtra | I75: Mumbai | J75: New Link Rd, Oshiwara | K75: Unknown | L75: Not published | M75: Not published — ask on first contact (look at the retail shelf / bag on the bar) | N75: ₹2,000–2,500 for two | P75: Premium house espresso blend of Indian estates + one rotating single estate + cold-brew lot. | Q75: Just opened: offer a guest-lot month + free barista calibration; side-by-side cupping against their current beans; ask which roaster/estates they use and what they'd change. | R75: Listed in Free Press Journal's Sep 2026 new Mumbai openings as a cafe-bar. Foodies of India Aug 2026: speciality cafe for artisanal coffee. | S75: Coffee cocktails — espresso blend + cold brew bulk. | T75: Walk-in / Google Maps listing | AB75: Lizaa Malik & Saurabh Pathak | AC75: https://foodiesofindia.wordpress.com/2026/08/04/new-restaurants-cafes-in-mumbai-august-2026/ | AD75: Coffee programme details not confirmed | AE75: ₹2500 for two | AG75: 3 of 4 read: https://www.district.in/dining/mumbai/goat-brew-oshiwara https://www.restaurantindia.in/news/goat-brew-launches-new-caf-restaurant-and-bar-in-mumbai.n16812 https://indianretailer.com/news/goat-brew-opens-new-cafe-and-bar-mumbai
A76: C055 | B76: C | C76: New (opened 2026) | D76: Normal | E76: The Blondie House | F76: Bakery / patisserie cafe | G76: West | H76: Maharashtra | I76: Mumbai | J76: Versova (Sep 2026; Blondie + Janu under one roof) | K76: Unknown | L76: Not published | M76: Not published — ask on first contact (look at the retail shelf / bag on the bar) | P76: Premium house espresso blend of Indian estates + one rotating single estate + cold-brew lot. | Q76: Pitch with Blondie (same group). | R76: Multi-level community space combining Blondie's cafe/bakery with Janu's menu (Oct 2026). | S76: Bakery-cafe; house blend. | T76: Walk-in / Google Maps listing | AC76: https://curlytales.com/india/food/new-mumbai-restaurants-in-october-youll-want-to-tell-your-friends-about/ | AE76: Brew: Tasting flight / omakase, South Indian filter; ₹2,000 for two | AG76: 4 of 4 read: https://curlytales.com/india/food/new-mumbai-restaurants-in-october-youll-want-to-tell-your-friends-about/ https://www.restaurantindia.in/news/bastian-hospitality-opens-the-blondie-house-in-versova.n17320 https://indianretailer.com/news/blondie-house-opens-new-community-cafe-versova https://t2online.in/goodlife/food-beverage/blondie-and-janu-find-a-new-home-in-versova--mumbai/2008352
A77: C063 | B77: C | C77: New (opened 2026) | D77: Normal | E77: The Coffee Project — Nagpur (4th outlet) | F77: Cafe chain / multi-outlet | G77: West | H77: Maharashtra | I77: Nagpur | K77: Unknown | L77: Not published | M77: Not published — ask on first contact (look at the retail shelf / bag on the bar) | P77: Premium house espresso blend of Indian estates + one rotating single estate + cold-brew lot. | Q77: Just opened: offer a guest-lot month + free barista calibration; side-by-side cupping against their current beans; ask which roaster/estates they use and what they'd change. | R77: Opened 4th Nagpur outlet on 15 Aug 2026 and hiring baristas (LinkedIn). | S77: Growing regional chain — blend supply. | T77: Walk-in / Google Maps listing | AC77: https://in.linkedin.com/jobs/cafe-jobs-pune | AD77: LinkedIn post via search summary Wave 4b: not found; 'The Coffee Project' is a Philippine chain. Nagpur alternatives: The Brew Crew (Bajaj Nagar), All That's Coffee (Sadar). | AG77: 0 of 1 read:
A78: C081 | B78: C | C78: New (opened 2026) | D78: Normal | E78: Christopher's Cafe & Bakehouse | F78: Bakery / patisserie cafe | G78: West | H78: Maharashtra | I78: Pune | J78: Goodwill Enclave 4, opp. Suman Business Park, Kalyani Nagar | K78: Unknown | L78: Victorian-themed all-day restaurant and bakehouse; coffee not a focus. | M78: Not published — ask on first contact (look at the retail shelf / bag on the bar) | N78: ~₹1,000 for two | P78: Premium house espresso blend of Indian estates + one rotating single estate + cold-brew lot. | Q78: Just opened: offer a guest-lot month + free barista calibration; side-by-side cupping against their current beans; ask which roaster/estates they use and what they'd change. | R78: Victorian-style all-day cafe (Curly Tales). | T78: Walk-in / Google Maps listing | AC78: https://curlytales.com/india/food/victorian-themed-cafe-to-k-drama-like-eatery-new-restaurants-to-try-in-pune-this-february/ | AG78: 1 of 1 read: https://curlytales.com/india/food/victorian-themed-cafe-to-k-drama-like-eatery-new-restaurants-to-try-in-pune-this-february/
A79: C083 | B79: C | C79: New (opened 2026) | D79: Normal | E79: Handmade Cafe | F79: Independent specialty cafe | G79: West | H79: Maharashtra | I79: Pune | J79: Merchant's Bungalow, 3C South Ave, Kalyani Nagar (10 am–7 pm) | K79: Unknown | L79: 'Community living room' cafe; pet-friendly; coffee menu not published. | M79: Not published — ask on first contact (look at the retail shelf / bag on the bar) | P79: Premium house espresso blend of Indian estates + one rotating single estate + cold-brew lot. | Q79: Just opened: offer a guest-lot month + free barista calibration; side-by-side cupping against their current beans; ask which roaster/estates they use and what they'd change. | R79: Pet-friendly cafe (Curly Tales). | T79: Walk-in / Google Maps listing | AB79: Three friends (founders) | AC79: https://curlytales.com/india/food/victorian-themed-cafe-to-k-drama-like-eatery-new-restaurants-to-try-in-pune-this-february/ | AG79: 1 of 2 read: https://curlytales.com/india/food/victorian-themed-cafe-to-k-drama-like-eatery-new-restaurants-to-try-in-pune-this-february/
A80: C094 | B80: C | C80: New (opened 2026) | D80: Normal | E80: Cafe Deli — Novotel Ahmedabad | F80: Hotel / resort cafe | G80: West | H80: Gujarat | I80: Ahmedabad | J80: S.G. Highway | K80: Unknown | L80: 'Café Deli-Tel': espressos, cappuccinos, cold brews (Sunrise Cold Brew), 'artisanal blends' from Coffee Co; 7 am–2 am. | M80: The Coffee Co (launch report) | N80: ~₹1,500 for two | P80: Premium house espresso blend of Indian estates + one rotating single estate + cold-brew lot. | Q80: Accor hotel cafe already on The Coffee Co (as is Novotel Goa's The Little Place) — only worth it through Accor F&B procurement. | R80: Casual specialty coffee + bakes (Knocksense new openings). | T80: Walk-in / Google Maps listing | AC80: https://www.knocksense.com/ahmedabad/9-new-restaurants-in-ahmedabad-bringing-fresh-flavours-to-the-table | AE80: Indian origins/estates: Baba Budangiri; Brew: Cold brew; ₹ 1500 for two | AG80: 1 of 3 read: https://www.eazydiner.com/ahmedabad/cafe-deli-tel-novotel-ahmedabad-697631
A81: C095 | B81: C | C81: New (opened 2026) | D81: Normal | E81: Insitu (Unsettle cafe) | F81: All-day / food-led cafe | G81: West | H81: Gujarat | I81: Ahmedabad | J81: Near RK Farm, off Sindhu Bhavan Marg, Thaltej | K81: Unknown | L81: Restaurant with a rooftop, the Unsettle cafe and a coffee + mocktail section. | M81: Not published — ask on first contact (look at the retail shelf / bag on the bar) | N81: ₹1,900 for two (Unsettle ~₹1,100); 4.6 (310) | P81: Premium house espresso blend of Indian estates + one rotating single estate + cold-brew lot. | Q81: Just opened: offer a guest-lot month + free barista calibration; side-by-side cupping against their current beans; ask which roaster/estates they use and what they'd change. | R81: Feb 2026 restaurant with cafe section 'Unsettle' and coffee/mocktail bar. | S81: Blend. | T81: Walk-in / Google Maps listing | AC81: https://curlytales.com/india/food/enjoy-different-vibes-under-one-roof-at-ahmedabads-new-cafe-insitu/ | AE81: ₹ 1900 for two | AG81: 3 of 3 read: https://www.eazydiner.com/ahmedabad/insitu-restaurant-thaltej-west-ahmedabad-712698 https://curlytales.com/india/food/enjoy-different-vibes-under-one-roof-at-ahmedabads-new-cafe-insitu/ https://www.eazydiner.com/ahmedabad/unsettle-thaltej-west-ahmedabad-712923
A82: C134 | B82: C | C82: New (opened 2026) | D82: Normal | E82: Cháfé Braz | F82: Independent specialty cafe | G82: West | H82: Goa | I82: Panjim | K82: Unknown | L82: Goan-Portuguese bites on a CIPA heritage balcony with jazz; coffee is secondary. | M82: Not published — ask on first contact (look at the retail shelf / bag on the bar) | P82: Premium house espresso blend of Indian estates + one rotating single estate + cold-brew lot. | Q82: Just opened: offer a guest-lot month + free barista calibration; side-by-side cupping against their current beans; ask which roaster/estates they use and what they'd change. | R82: New 2026 cafe on the balcony of a 200-year-old Goan home overlooking the Mandovi. | T82: Walk-in / Google Maps listing | AC82: https://travellerscoop.com/must-try-new-restaurants-in-goa-openings/ | AD82: Wave 4: coffee not a focus in any coverage — downgraded to C. | AG82: 3 of 3 read: https://travellerscoop.com/must-try-new-restaurants-in-goa-openings/ https://thenodmag.com/content/goa-new-restaurants-bars-food-menus-july-2026 https://wanderlog.com/place/details/5383434
A83: C194 | B83: C | C83: New (opened 2026) | D83: Normal | E83: Public Supply | F83: All-day / food-led cafe | G83: North | H83: Delhi | I83: New Delhi | J83: Hauz Khas | K83: Unknown | L83: Wellness cafe — juices, açai; coffee minor. | M83: Not published — ask on first contact (look at the retail shelf / bag on the bar) | P83: Premium house espresso blend of Indian estates + one rotating single estate + cold-brew lot. | Q83: Just opened: offer a guest-lot month + free barista calibration; side-by-side cupping against their current beans; ask which roaster/estates they use and what they'd change. | R83: Wellness-focused cafe by chefs Megha Kohli & Noah Louis Barnes (The Nod, Jul 2026). | S83: Chef-led — clean single estates. | T83: Walk-in / Google Maps listing | AB83: Megha Kohli & Noah Louis Barnes (ex-Pendulo, ex-Cortasso) | AC83: https://thenodmag.com/content/delhi-ncr-new-restaurants-bars-food-menus-july-2026 | AE83: ₹1,500 for two | AG83: 2 of 4 read: https://thenodmag.com/content/delhi-ncr-new-restaurants-bars-food-menus-july-2026 https://www.timeout.com/delhi/restaurants/public-supply
A84: C195 | B84: C | C84: New (opened 2026) | D84: Normal | E84: Second Born | F84: Coffee + cocktail bar | G84: North | H84: Delhi | I84: New Delhi | J84: GK-II (rooftop above Staple) | K84: Unknown | L84: Rooftop bar (5 pm–1 am); coffee & cascara signatures. | M84: Not published — ask on first contact (look at the retail shelf / bag on the bar) | P84: Premium house espresso blend of Indian estates + one rotating single estate + cold-brew lot. | Q84: Just opened: offer a guest-lot month + free barista calibration; side-by-side cupping against their current beans; ask which roaster/estates they use and what they'd change. | R84: Rooftop 'living room' serving coffees and cocktails (The Nod, Feb 2026). | T84: Walk-in / Google Maps listing | AC84: https://thenodmag.com/content/new-restaurants-bars-openings-february-2026-mumbai-delhi-bengaluru-goa | AE84: Brew: Cascara; Signals: Coming soon | AG84: 2 of 3 read: https://thenodmag.com/content/new-restaurants-bars-openings-february-2026-mumbai-delhi-bengaluru-goa https://thenodmag.com/content/second-born-delhi-restaurant-rooftop-cocktail-bar-review
A85: C208 | B85: C | C85: New (opened 2026) | D85: Normal | E85: Lume and Lime | F85: All-day / food-led cafe | G85: North | H85: Haryana | I85: Gurugram | J85: M3M SCO Market, Sector 113, Gurugram (3,800 sq ft bistro) | K85: Unknown | L85: Not published | M85: Not published — ask on first contact (look at the retail shelf / bag on the bar) | P85: Premium house espresso blend of Indian estates + one rotating single estate + cold-brew lot. | Q85: Just opened: offer a guest-lot month + free barista calibration; side-by-side cupping against their current beans; ask which roaster/estates they use and what they'd change. | R85: European-Mediterranean cafe, 9am–11pm (Lab Mag, Oct 2026). | T85: Walk-in / Google Maps listing | AC85: https://www.thelabmagofficial.com/new-tables-for-october-the-delhi-ncr-restaurants-cafes-and-bars-to-try/ | AD85: Wave 4: coverage describes a bistro with no coffee programme. | AG85: 1 of 2 read: https://www.thelabmagofficial.com/new-tables-for-october-the-delhi-ncr-restaurants-cafes-and-bars-to-try/
A86: C260 | B86: C | C86: New (opened 2026) | D86: Normal | E86: Whizz Coffee (by Craft Coffee Box) | F86: Cafe chain / multi-outlet | G86: East | H86: West Bengal | I86: Kolkata | J86: Jatindas Road | K86: Group roasts own | L86: Not published | M86: Own roastery (Craft Coffee group) | P86: Premium house espresso blend of Indian estates + one rotating single estate + cold-brew lot. | Q86: Just opened: offer a guest-lot month + free barista calibration; side-by-side cupping against their current beans; ask which roaster/estates they use and what they'd change. | R86: Budget Gen-Z artisanal coffee hub (t2, Oct 2026). | T86: Walk-in / Google Maps listing | AC86: https://t2online.in/goodlife/food-beverage/whizz-coffee-from-craft-coffee-box-is-brewing-a-new-sip-culture-where-artisanal-cups-meet-affordable-prices/2008421 | AG86: 1 of 1 read: https://t2online.in/goodlife/food-beverage/whizz-coffee-from-craft-coffee-box-is-brewing-a-new-sip-culture-where-artisanal-cups-meet-affordable-prices/2008421
A87: C270 | B87: C | C87: New (opened 2026) | D87: Normal | E87: Cafe 138 | F87: Independent specialty cafe | G87: Northeast | H87: Assam | I87: Guwahati | K87: Unknown | L87: Not published | M87: Not published — ask on first contact (look at the retail shelf / bag on the bar) | P87: Premium house espresso blend of Indian estates + one rotating single estate + cold-brew lot. | Q87: Just opened: offer a guest-lot month + free barista calibration; side-by-side cupping against their current beans; ask which roaster/estates they use and what they'd change. | R87: Instagram bio: 'A new Cafe in Guwahati!'. | S87: New — blend. | T87: Instagram DM | U87: @cafe138_ | V87: https://www.instagram.com/cafe138_/ | AC87: https://www.instagram.com/cafe138_/ | AD87: Coffee programme unknown Wave 4: not found in a web search beyond its source roundup — confirm it is open (Instagram / Google Maps) before outreach. | AG87: 0 of 1 read:
A88: C014 | B88: A | C88: New (late 2025) | D88: Premium | E88: Doppio Coffee — Colaba | F88: Independent specialty cafe | G88: West | H88: Maharashtra | I88: Mumbai | J88: Colaba | K88: Unknown | L88: Not published | M88: Not published — ask on first contact (look at the retail shelf / bag on the bar) | P88: Rotating single-estate / micro-lot for the filter bar + a single-origin espresso option. | Q88: Just opened: offer a guest-lot month + free barista calibration; side-by-side cupping against their current beans; ask which roaster/estates they use and what they'd change. | R88: New outpost for specialty coffee fans (Foodies of India, Nov 2025). | T88: Walk-in / Google Maps listing | AC88: https://foodiesofindia.wordpress.com/2025/11/03/25-new-restaurants-cafes-in-mumbai-you-need-to-try-this-november-2025/ | AE88: Processes / format: Single origin; Brew: Pour over | AG88: 2 of 3 read: https://foodiesofindia.wordpress.com/2025/11/03/25-new-restaurants-cafes-in-mumbai-you-need-to-try-this-november-2025/ https://www.restaurantindia.in/article/Have-a-fun-dining-experience-with-Doppio.7025
A89: C025 | B89: A | C89: New (late 2025) | D89: Premium | E89: Tuskin Coffee | F89: Independent specialty cafe | G89: West | H89: Maharashtra | I89: Mumbai | J89: Bandra | K89: Unknown | L89: Not published | M89: Not published — ask on first contact (look at the retail shelf / bag on the bar) | P89: Rotating single-estate / micro-lot for the filter bar + a single-origin espresso option. | Q89: Just opened: offer a guest-lot month + free barista calibration; side-by-side cupping against their current beans; ask which roaster/estates they use and what they'd change. | R89: Specialty coffee spot (Foodies of India, Oct 2025). | T89: Walk-in / Google Maps listing | AC89: https://foodiesofindia.wordpress.com/2025/10/01/25-new-restaurants-cafes-to-check-out-in-mumbai-this-october-2025/ | AD89: Wave 4: not found in a web search beyond its source roundup — confirm it is open (Instagram / Google Maps) before outreach. | AG89: 1 of 1 read: https://foodiesofindia.wordpress.com/2025/10/01/25-new-restaurants-cafes-to-check-out-in-mumbai-this-october-2025/
A90: C049 | B90: C | C90: New (late 2025) | D90: Normal | E90: Cafe Chikory | F90: All-day / food-led cafe | G90: West | H90: Maharashtra | I90: Mumbai | J90: 43 Raja Bahadur Compound, Tamarind Lane, Fort | K90: Unknown | L90: Not published | M90: Not published — ask on first contact (look at the retail shelf / bag on the bar) | N90: ~₹350 for two | P90: Premium house espresso blend of Indian estates + one rotating single estate + cold-brew lot. | Q90: Just opened: offer a guest-lot month + free barista calibration; side-by-side cupping against their current beans; ask which roaster/estates they use and what they'd change. | R90: For brunch and specialty coffee lovers (Oct 2025). | T90: Walk-in / Google Maps listing | AC90: https://foodiesofindia.wordpress.com/2025/10/01/25-new-restaurants-cafes-to-check-out-in-mumbai-this-october-2025/ | AE90: Brew: South Indian filter, Affogato; ₹350 for two | AF90: +91 77189 91865 | AG90: 2 of 2 read: https://www.district.in/dining/mumbai/cafe-chikory-fort https://foodiesofindia.wordpress.com/2025/10/01/25-new-restaurants-cafes-to-check-out-in-mumbai-this-october-2025/
A91: C096 | B91: C | C91: New (late 2025) | D91: Normal | E91: KOMO by Kaffa | F91: Roaster-cafe (roasts in-house) | G91: West | H91: Gujarat | I91: Ahmedabad | J91: Rajpath Rangoli Road, behind Rajpath Club | K91: Yes (Kaffa Coffee Roasters) | L91: Not published | M91: Own roastery | P91: Green coffee or a limited guest micro-lot collaboration (they roast in-house). | Q91: Don't pitch roasted supply — offer green lots or a co-branded guest micro-lot. | R91: 'Gujarat's biggest cafe', opened 10 Nov 2025 by Kaffa Coffee Roasters' owner. Wave 4: opened 10 Nov 2025 by Anand Heena Thakkar, owner of Kaffa Coffee Roasters. | S91: Roaster-owned; guest-lot / collab only. | T91: Walk-in / Google Maps listing | AC91: https://curlytales.com/india/food/cafe-hoppers-rejoice-gujarats-biggest-cafe-komo-by-kaffa-opens-in-ahmedabad/ | AE91: Roasters named in articles about it: Kaffa Coffee Roasters | AG91: 1 of 1 read: https://curlytales.com/india/food/cafe-hoppers-rejoice-gujarats-biggest-cafe-komo-by-kaffa-opens-in-ahmedabad/

Sheet All Cafes (Premium+Normal)
A1: ID | B1: Priority | C1: Status | D1: Tier | E1: Name | F1: Type | G1: Region | H1: State | I1: City | J1: Area / address | K1: Roasts in-house? | L1: Current coffee roster | M1: Supplier / roaster | N1: Price signals | O1: Gap in their roster | P1: What we can offer | Q1: Approach strategy | R1: Evidence (why this tier) | S1: Pitch angle | T1: Best first contact | U1: Instagram | V1: Instagram URL | W1: Website | X1: Email | Y1: Phone | Z1: LinkedIn | AA1: Listing (Zomato / EazyDiner / Reddit) | AB1: Key people (public) | AC1: Source | AD1: Verify / notes | AE1: Web check: roster evidence (auto — verify) | AF1: Contacts on its own pages | AG1: Pages read (web check)
A2: C001 | B2: B | C2: Established | D2: Normal | E2: Linzz Cafe | F2: Independent specialty cafe | G2: West | H2: Maharashtra | I2: Chhatrapati Sambhajinagar (Aurangabad) | K2: Unknown | L2: Not published | M2: Not published — ask on first contact (look at the retail shelf / bag on the bar) | P2: Premium house espresso blend of Indian estates + one rotating single estate + cold-brew lot. | Q2: Established: position as a second roaster / rotating single estate; walk-in cupping with the head barista. | R2: Instagram bio: 'Artisanal coffee | Authentic global bites'. | S2: Only artisanal-coffee cafe found in city. | T2: Instagram DM | U2: @linzz.csn | V2: https://www.instagram.com/linzz.csn/ | AC2: https://www.instagram.com/linzz.csn/
A3: C002 | B3: C | C3: Established | D3: Normal | E3: EssPressOh Cafe | F3: Independent specialty cafe | G3: West | H3: Maharashtra | I3: Chhatrapati Sambhajinagar (Aurangabad) | J3: API Rd, MIDC Chilkalthana (listed as 'Ess Press Oh') | K3: Unknown | L3: Not published | M3: Not published — ask on first contact (look at the retail shelf / bag on the bar) | N3: 4.1 (148) | P3: Premium house espresso blend of Indian estates + one rotating single estate + cold-brew lot. | Q3: Established: position as a second roaster / rotating single estate; walk-in cupping with the head barista. | R3: Espresso + waffles cafe. | S3: Blend. | T3: Website contact form | W3: http://www.esspressoh.com/ | AC3: http://esspressoh.com/about-us/ | AF3: Esspressohindia@gmail.com · +91 80553 33333 | AG3: 3 of 4 read: http://www.esspressoh.com/ https://esspressoh.com/about-us/ https://esspressoh.com/menu/
A4: C003 | B4: C | C4: Established | D4: Normal | E4: NoMeatNaan | F4: Bakery / patisserie cafe | G4: West | H4: Maharashtra | I4: Chhatrapati Sambhajinagar (Aurangabad) | J4: CIDCO + Connaught | K4: Unknown | L4: Not published | M4: Not published — ask on first contact (look at the retail shelf / bag on the bar) | P4: Premium house espresso blend of Indian estates + one rotating single estate + cold-brew lot. | Q4: Established: position as a second roaster / rotating single estate; walk-in cupping with the head barista. | R4: Bakery and coffee shop (Instagram). | T4: Instagram DM | U4: @nomeatnaan_bakery | V4: https://www.instagram.com/nomeatnaan_bakery/ | AC4: https://www.instagram.com/nomeatnaan_bakery/ | AD4: Wave 4: not found in a web search beyond its source roundup — confirm it is open (Instagram / Google Maps) before outreach.
A5: C004 | B5: C | C5: Established | D5: Normal | E5: Coffee Sanskruti | F5: Independent specialty cafe | G5: West | H5: Maharashtra | I5: Kolhapur | J5: S2 Royal Classic, Rajarampuri 3rd Lane, near Jain Temple | K5: Unknown | L5: Small coffee bar: hot and cold coffees; 4.4 (97); closed Mondays. | M5: Not published — ask on first contact (look at the retail shelf / bag on the bar) | P5: Premium house espresso blend of Indian estates + one rotating single estate + cold-brew lot. | Q5: Established: position as a second roaster / rotating single estate; walk-in cupping with the head barista. | R5: Self-described premium coffee cafe. | S5: Blend. | T5: Call / WhatsApp | W5: https://www.coffeesanskruti.com/ | Y5: +91 96737 35453 (Yappe) | AC5: https://www.coffeesanskruti.com/ | AE5: Brew: Cold brew; Commodity brands: Starbucks | AF5: coffeesanskruti@gmail.com · +91 96737 35453 | AG5: 2 of 2 read: https://www.coffeesanskruti.com/ https://yappe.in/maharashtra/kolhapur/coffee-sanskruti/225223
A6: C005 | B6: C | C6: Established | D6: Normal | E6: Grain de Cafe | F6: Independent specialty cafe | G6: West | H6: Maharashtra | I6: Kolhapur | J6: NCC Bhavan Rd, opp. Shivaji University, Vidya Nagar | K6: Unknown | L6: Cafe-restaurant used for parties; 4.2 (740); food reviews mixed. | M6: Not published — ask on first contact (look at the retail shelf / bag on the bar) | P6: Premium house espresso blend of Indian estates + one rotating single estate + cold-brew lot. | Q6: Established: position as a second roaster / rotating single estate; walk-in cupping with the head barista. | R6: Coffee cafe (Instagram). | T6: Instagram DM | U6: @graindecafe_kolhapur | V6: https://www.instagram.com/graindecafe_kolhapur/ | Y6: +91 95957 09599 (Yappe) | AC6: https://www.instagram.com/graindecafe_kolhapur/ | AG6: 0 of 1 read:
A7: C006 | B7: C | C7: Established | D7: Normal | E7: The Treaat Coffee | F7: Independent specialty cafe | G7: West | H7: Maharashtra | I7: Kolhapur | J7: Shop 8, Shahaji Law College Complex, Rajarampuri Main Rd | K7: Unknown | L7: Shakes, smoothies, hazelnut mocha; 4.4 (54). | M7: Not published — ask on first contact (look at the retail shelf / bag on the bar) | P7: Premium house espresso blend of Indian estates + one rotating single estate + cold-brew lot. | Q7: Established: position as a second roaster / rotating single estate; walk-in cupping with the head barista. | R7: Coffee, smoothies, shakes (Instagram). | T7: Instagram DM | U7: @the.treaat.coffee_kolhapur | V7: https://www.instagram.com/the.treaat.coffee_kolhapur/ | Y7: +91 96042 57000 (Yappe) | AC7: https://www.instagram.com/the.treaat.coffee_kolhapur/ | AG7: 1 of 1 read: https://yappe.in/maharashtra/kolhapur/the-treaat-coffee-in-kolhapur/657955
A8: C007 | B8: A | C8: New (opened 2026) | D8: Normal | E8: Brevé (Running Late by Brevé) | F8: Independent specialty cafe | G8: West | H8: Maharashtra | I8: Mumbai | J8: Brevé 2.0, Shop G-2 Mount Apartment, St John Baptist Rd, Bandra W | K8: Unknown | L8: Espresso-led specialty menu alongside build-your-own breakfast boards; 36 seats; runs Mumbai's first cafe-led run club ('Running Late'). | M8: Not published — ask on first contact (look at the retail shelf / bag on the bar) | N8: ~₹1,000 for two | P8: Co-branded run-club blend, post-run cold brew, retail bags for the community. | Q8: Pitch a 'post-run' cold brew + a rotating single estate; offer to sponsor a run-club morning with a tasting of 3 Indian estates. | R8: 36-seat flagship built around 'Mumbai's first cafe-led run club'; Brevé Bakery (Bandra W) and 'Basque by breve' also hiring baristas — expanding. | T8: Walk-in / Google Maps listing | AB8: Usman & Farhaz Bhadelia (founders) | AC8: https://www.restaurantindia.in/news/restaurant-india-news-brev-opens-new-flagship-caf-in-bandra-expands-community-focused-coffee-concept.n16397 | AE8: Brew: Cold brew; ₹1000 for two | AG8: 3 of 3 read: https://www.restaurantindia.in/news/restaurant-india-news-brev-opens-new-flagship-caf-in-bandra-expands-community-focused-coffee-concept.n16397 https://www.freepressjournal.in/lifestyle/build-your-own-breakfast-board-at-mumbais-newest-caf-run-club-brev-20-that-doesnt-compromise-on-protein-calories https://curlytales.com/bandras-cafe-breve-is-where-your-gym-goals-and-cake-cravings-finally-shake-hands/
A9: C008 | B9: A | C9: New (opened 2026) | D9: Normal | E9: Cocoa & Katli | F9: Bakery / patisserie cafe | G9: West | H9: Maharashtra | I9: Mumbai | J9: Malad (1,050 sq ft) | K9: Unknown | L9: Specialty coffee paired with 'mindful' low-sugar desserts; coffee details not published. | M9: Not published — ask on first contact (look at the retail shelf / bag on the bar) | P9: Premium house espresso blend of Indian estates + one rotating single estate + cold-brew lot. | Q9: Just opened: offer a guest-lot month + free barista calibration; side-by-side cupping against their current beans; ask which roaster/estates they use and what they'd change. | R9: Launched 21 Oct 2026 by Harsh Kedia & Arihant Jain; specialty coffee programme alongside desserts and all-day menu. | S9: Brand-new — still fixing suppliers; pitch a house espresso blend of Indian estates. | T9: Instagram DM | U9: @cocoaandkatli | V9: https://www.instagram.com/cocoaandkatli/ | AB9: Harsh Kedia (chef) & Arihant Jain | AC9: https://aninews.in/news/business/harsh-kedia-and-arihant-jain-launch-cocoa-amp-katli-a-caf233-that-redefines-mindful-indulgence-for-the-conscious-mumbaikar20261021121947/ | AD9: Instagram not indexed by search yet — look up by name on Instagram | AE9: Imported origins: Vietnam | AG9: 2 of 3 read: https://theprint.in/ani-press-releases/harsh-kedia-and-arihant-jain-launch-cocoa-katli-a-cafe-that-redefines-mindful-indulgence-for-the-conscious-mumbaikar/3077520/ https://curlytales.com/india/food/coffee-desserts-mindful-indulgence-harsh-kedia-aka-a-diabetic-chef-opens-new-cafe-in-malad/
A10: C009 | B10: A | C10: New (opened 2026) | D10: Normal | E10: Javaphile | F10: Cafe chain / multi-outlet | G10: West | H10: Maharashtra | I10: Mumbai | J10: Worli flagship (Jan 2026) + Pali Hill, Bandra; sister venue Shelter (Versova) | K10: Unknown | L10: Espresso drinks + flavoured cold brews (citrus, elderflower, sweet lime, cucumber-cream) + manual brews (Chemex, AeroPress, pour-over). | M10: Not published — ask on first contact (look at the retail shelf / bag on the bar) | O10: Roaster not named; flavoured cold brews suit a dedicated cold-brew lot. | P10: Premium house espresso blend of Indian estates + one rotating single estate + cold-brew lot. | Q10: Group pitch across Javaphile Worli, Pali Hill and Shelter: one cold-brew lot + one manual-brew single estate. | R10: Comfort-first cafe focused on great coffee (Foodies of India, Jan 2026). | T10: Walk-in / Google Maps listing | AC10: https://www.restaurantindia.in/news/restaurant-india-news-javaphile-caf-opens-in-worli-mumbai.n14931 | AG10: 3 of 4 read: https://www.restaurantindia.in/news/restaurant-india-news-javaphile-caf-opens-in-worli-mumbai.n14931 https://www.cosmopolitan.in/life/features/story/this-worli-cafe-is-all-about-comfort-caffeine-and-slow-sips-1338113-2026-01-29 https://www.indianretailer.com/news/javaphile-cafe-arrives-worli-deepens-footprint-mumbai
A11: C010 | B11: A | C11: New (opened 2026) | D11: Normal | E11: Pouring Veranda | F11: Independent specialty cafe | G11: West | H11: Maharashtra | I11: Mumbai | J11: Andheri | K11: Unknown | L11: Not published | M11: Not published — ask on first contact (look at the retail shelf / bag on the bar) | P11: Premium house espresso blend of Indian estates + one rotating single estate + cold-brew lot. | Q11: Just opened: offer a guest-lot month + free barista calibration; side-by-side cupping against their current beans; ask which roaster/estates they use and what they'd change. | R11: Listed under 'New Cafes in Andheri' (Foodies of India, Apr 2026). | T11: Walk-in / Google Maps listing | AC11: https://foodiesofindia.wordpress.com/2026/04/02/20-new-restaurants-in-mumbai-to-check-out-april-2026/ | AD11: Wave 4: not found in a web search beyond its source roundup — confirm it is open (Instagram / Google Maps) before outreach. | AG11: 1 of 2 read: https://foodiesofindia.wordpress.com/2026/04/02/20-new-restaurants-in-mumbai-to-check-out-april-2026/
A12: C011 | B12: A | C12: New (opened 2026) | D12: Normal | E12: Rola | F12: All-day / food-led cafe | G12: West | H12: Maharashtra | I12: Mumbai | J12: Pali Hill, Bandra (opened 17 Aug 2026; 70 seats) | K12: Unknown | L12: Flat white, Spanish latte, coffee tonic, mochas; outdoor coffee cart at the entrance. | M12: Not published — ask on first contact (look at the retail shelf / bag on the bar) | N12: ~₹2,000 for two | O12: No filter or single-origin line. | P12: Single-estate tonic / filter line + espresso blend for the cart. | Q12: Offer a cart-friendly espresso blend + one single estate for tonic drinks; propose a cart 'estate of the month'. | R12: All-day diner opened 17 Aug 2026; 70 covers; specialty coffee programme + outdoor coffee cart. | T12: Walk-in / Google Maps listing | AB12: Puneet Anand (Anandvan Resort) | AC12: https://indianretailer.com/news/rola-opens-new-all-day-diner-bandra | AE12: Brew: Flat white, Affogato | AG12: 2 of 2 read: https://indianretailer.com/news/rola-opens-new-all-day-diner-bandra https://www.esquireindia.co.in/food-and-drinks/what-to-eat/from-rola-to-the-mahjong-club-9-new-restaurants-and-cafés-in-mumbai-to-try-this-september
A13: C012 | B13: A | C13: New (opened 2026) | D13: Premium | E13: BBRWN Cafe | F13: Independent specialty cafe | G13: West | H13: Maharashtra | I13: Mumbai | J13: TBC | K13: Unknown | L13: Not published | M13: Not published — ask on first contact (look at the retail shelf / bag on the bar) | P13: Rotating single-estate / micro-lot for the filter bar + a single-origin espresso option. | Q13: Just opened: offer a guest-lot month + free barista calibration; side-by-side cupping against their current beans; ask which roaster/estates they use and what they'd change. | R13: New specialty cafe from Drishti Gundecha where coffee and ceremonial matcha take centre stage (2026 Mumbai openings coverage). | S13: New, coffee-first concept — offer espresso + filter single-estate pair. | T13: Walk-in / Google Maps listing | AB13: Drishti Gundecha (founder, per press) | AC13: Mumbai 2026 new-openings roundups (search) | AD13: Location and opening date not confirmed Instagram not indexed by search yet — look up by name on Instagram Wave 4: not found in a web search beyond its source roundup — confirm it is open (Instagram / Google Maps) before outreach.
A14: C013 | B14: A | C14: New (opened 2026) | D14: Premium | E14: Coffee Capital | F14: Cafe chain / multi-outlet | G14: West | H14: Maharashtra | I14: Mumbai | J14: Chembur + Versova (34 covers) | K14: Unknown | L14: Single-origin Arabica from Karnataka, Tamil Nadu, Odisha and Nagaland + a rotating slot of INTERNATIONAL micro-lots; whiskey-barrel-aged coffee; 'Noble Nectar'. | M14: Not published — ask on first contact (look at the retail shelf / bag on the bar) | N14: ~₹1,000 for two; EazyDiner 4.8 (249) | O14: Imports fill the 'exotic' slot. | P14: Indian anaerobic / experimental lots to replace the international micro-lot slot; barrel-ageing lots. | Q14: Lead with a cupping of 2–3 Indian experimental lots against their current import; offer the rotating slot at a fixed monthly price. | R14: 34-cover specialty cafe format built around single-origin Indian Arabica (Restaurant India). Instagram 'specialty coffee, cozy vibes — Chembur' with ~46 followers / 30 posts when indexed: account is brand-new. | S14: Menu is origin-driven — natural buyer of multiple single estates. | T14: Instagram DM | U14: @coffeecapital__ | V14: https://www.instagram.com/coffeecapital__/ | AB14: Tuhin Ghosh (founder) | AC14: https://www.restaurantindia.in/news/restaurant-india-news-coffee-capital-launches-in-mumbai-with-34-cover-speciality-caf-format.n15399 | AE14: Processes / format: Micro-lot, Single origin; Brew: Cold brew; Prices: wo at Coffee Capital? The cost of two at Coffee Capital is ₹ 1000. You can save EXTRA; ₹ 1000 for two | AG14: 2 of 3 read: https://www.eazydiner.com/mumbai/coffee-capital-versova-western-suburbs-712657 https://www.restaurantindia.in/news/restaurant-india-news-coffee-capital-launches-in-mumbai-with-34-cover-speciality-caf-format.n15399
A15: C014 | B15: A | C15: New (late 2025) | D15: Premium | E15: Doppio Coffee — Colaba | F15: Independent specialty cafe | G15: West | H15: Maharashtra | I15: Mumbai | J15: Colaba | K15: Unknown | L15: Not published | M15: Not published — ask on first contact (look at the retail shelf / bag on the bar) | P15: Rotating single-estate / micro-lot for the filter bar + a single-origin espresso option. | Q15: Just opened: offer a guest-lot month + free barista calibration; side-by-side cupping against their current beans; ask which roaster/estates they use and what they'd change. | R15: New outpost for specialty coffee fans (Foodies of India, Nov 2025). | T15: Walk-in / Google Maps listing | AC15: https://foodiesofindia.wordpress.com/2025/11/03/25-new-restaurants-cafes-in-mumbai-you-need-to-try-this-november-2025/ | AE15: Processes / format: Single origin; Brew: Pour over | AG15: 2 of 3 read: https://foodiesofindia.wordpress.com/2025/11/03/25-new-restaurants-cafes-in-mumbai-you-need-to-try-this-november-2025/ https://www.restaurantindia.in/article/Have-a-fun-dining-experience-with-Doppio.7025
A16: C015 | B16: A | C16: New (opened 2026) | D16: Premium | E16: Esc. Coffee x Deli | F16: Independent specialty cafe | G16: West | H16: Maharashtra | I16: Mumbai | J16: Bandra | K16: Unknown | L16: Not published | M16: Not published — ask on first contact (look at the retail shelf / bag on the bar) | P16: Rotating single-estate / micro-lot for the filter bar + a single-origin espresso option. | Q16: Just opened: offer a guest-lot month + free barista calibration; side-by-side cupping against their current beans; ask which roaster/estates they use and what they'd change. | R16: Specialty coffee spot in March 2026 openings (Foodies of India). | T16: Walk-in / Google Maps listing | AC16: https://foodiesofindia.wordpress.com/2026/03/01/new-restaurants-in-mumbai-march-2026-round-up-25-new-openings/ | AE16: ₹1500 for two | AG16: 2 of 2 read: https://www.district.in/dining/mumbai/esc-coffee-x-deli-carter-road-bandra-west https://foodiesofindia.wordpress.com/2026/03/01/new-restaurants-in-mumbai-march-2026-round-up-25-new-openings/
A17: C016 | B17: A | C17: New (opened 2026) | D17: Premium | E17: Grahm Cafe | F17: Independent specialty cafe | G17: West | H17: Maharashtra | I17: Mumbai | J17: Bandra | K17: Unknown | L17: Not published | M17: Not published — ask on first contact (look at the retail shelf / bag on the bar) | P17: Rotating single-estate / micro-lot for the filter bar + a single-origin espresso option. | Q17: Just opened: offer a guest-lot month + free barista calibration; side-by-side cupping against their current beans; ask which roaster/estates they use and what they'd change. | R17: Neighbourhood cafe for specialty coffee, fresh bakes, brunch (Foodies of India, Aug 2026). | T17: Walk-in / Google Maps listing | AC17: https://foodiesofindia.wordpress.com/2026/08/04/new-restaurants-cafes-in-mumbai-august-2026/ | AD17: Wave 4: not found in a web search beyond its source roundup — confirm it is open (Instagram / Google Maps) before outreach. | AE17: Commodity brands: Nespresso | AG17: 1 of 1 read: https://foodiesofindia.wordpress.com/2026/08/04/new-restaurants-cafes-in-mumbai-august-2026/
A18: C017 | B18: A | C18: New (opened 2026) | D18: Premium | E18: JOKER | F18: Coffee + cocktail bar | G18: West | H18: Maharashtra | I18: Mumbai | J18: Turner Rd, Bandra W (opened 2 Aug 2026) | K18: Unknown | L18: Cafe by day, cocktail bar by night; Brandy Barrel Aged pour-over; signatures Joker Twist, Frost and Fortune. | M18: Not published — ask on first contact (look at the retail shelf / bag on the bar) | O18: Barrel-aged programme needs lots that suit ageing. | P18: Co-developed barrel series (rum / brandy / whisky) on Indian naturals + cocktail-grade espresso. | Q18: Pitch Aspect Hospitality's F&B team — group can roll it out to other venues. | R18: Aspect Hospitality's all-day coffee & cocktail bar, opened 2 Aug 2026. | T18: Website contact form | W18: https://aspecthospitality.in | AB18: Aspect Hospitality | AC18: https://www.restaurantindia.in/news/aspect-hospitality-expands-fb-portfolio-with-joker-in-bandra.n16905 | AE18: Brew: Pour over | AG18: 3 of 4 read: https://aspecthospitality.in https://www.aspecthospitality.in/our-story https://www.restaurantindia.in/news/aspect-hospitality-expands-fb-portfolio-with-joker-in-bandra.n16905
A19: C018 | B19: A | C19: Established | D19: Premium | E19: Kalopsia Artisan Coffee | F19: Independent specialty cafe | G19: West | H19: Maharashtra | I19: Mumbai | J19: Bandra | K19: Unknown | L19: Cold brew, Turkish and Vietnamese coffee; Mahlkönig K30 grinder. | M19: Not published — ask on first contact (look at the retail shelf / bag on the bar) | P19: Rotating single-estate / micro-lot for the filter bar + a single-origin espresso option. | Q19: Established: position as a second roaster / rotating single estate; walk-in cupping with the head barista. | R19: Tiny owner-run Bandra counter with direct-trade practices pouring Indian single-origin micro-lots (Mumbai specialty guides 2026). | S19: Ideal: buys micro-lots from outside roasters — lead with your rarest single estate. | T19: Walk-in / Google Maps listing | AC19: https://www.localspecialtycoffee.com/cities/specialty-coffee-mumbai/single-origin | AD19: Instagram not indexed by search yet — look up by name on Instagram | AE19: Indian origins/estates: Araku, Pulney / Kodaikanal; Imported origins: Vietnam, Indonesia; Processes / format: Single origin, Micro-lot; Brew: Cold brew, Pour over, Siphon, Tasting flight / omakase | AG19: 2 of 2 read: https://www.localspecialtycoffee.com/cities/specialty-coffee-mumbai/single-origin https://kaapimachines.com/for-coffee-lovers-in-mumbai
A20: C019 | B20: A | C20: New (opened 2026) | D20: Premium | E20: Kink Speciality Coffee | F20: Cafe chain / multi-outlet | G20: West | H20: Maharashtra | I20: Mumbai | J20: Bandra (+ other outlets) | K20: Unknown | L20: Not published | M20: Not published — ask on first contact (look at the retail shelf / bag on the bar) | P20: Rotating single-estate / micro-lot for the filter bar + a single-origin espresso option. | Q20: Just opened: offer a guest-lot month + free barista calibration; side-by-side cupping against their current beans; ask which roaster/estates they use and what they'd change. | R20: Instagram: speciality coffee, Bandra among outlets. Foodies of India Jan 2026: bold, modern coffee spot, strong brews. | S20: Specialty indie. | T20: Instagram DM | U20: @kink.coffee | V20: https://www.instagram.com/kink.coffee/ | AC20: https://foodiesofindia.wordpress.com/2026/01/15/january-2026-30-new-restaurants-cafes-in-mumbai-you-need-to-check-out/ | AD20: Wave 4: not found in a web search beyond its source roundup — confirm it is open (Instagram / Google Maps) before outreach. | AG20: 0 of 1 read:
A21: C020 | B21: A | C21: New (opened 2026) | D21: Premium | E21: KĀPIBAR | F21: Independent specialty cafe | G21: West | H21: Maharashtra | I21: Mumbai | J21: Bandra | K21: Unknown | L21: Regional Indian coffee traditions (details not published). | M21: Not published — ask on first contact (look at the retail shelf / bag on the bar) | P21: Regional single estates (Coorg, Chikmagalur, Nilgiris, Araku, Northeast) — a 'map of India' flight. | Q21: Perfect story fit — lead with origin storytelling. | R21: South Indian-inspired cafe celebrating regional coffee traditions (Foodies of India, Aug 2026). | T21: Walk-in / Google Maps listing | AC21: https://foodiesofindia.wordpress.com/2026/08/04/new-restaurants-cafes-in-mumbai-august-2026/ | AD21: Wave 4: not found in a web search beyond its source roundup — confirm it is open (Instagram / Google Maps) before outreach. | AE21: Commodity brands: Nespresso | AG21: 1 of 1 read: https://foodiesofindia.wordpress.com/2026/08/04/new-restaurants-cafes-in-mumbai-august-2026/
A22: C021 | B22: A | C22: New (opened 2026) | D22: Premium | E22: MUVN Coffee | F22: Independent specialty cafe | G22: West | H22: Maharashtra | I22: Mumbai | J22: Andheri | K22: Unknown | L22: Not published | M22: Not published — ask on first contact (look at the retail shelf / bag on the bar) | P22: Rotating single-estate / micro-lot for the filter bar + a single-origin espresso option. | Q22: Just opened: offer a guest-lot month + free barista calibration; side-by-side cupping against their current beans; ask which roaster/estates they use and what they'd change. | R22: Listed under 'New Cafes in Andheri' (Foodies of India, Apr 2026). | T22: Walk-in / Google Maps listing | AC22: https://foodiesofindia.wordpress.com/2026/04/02/20-new-restaurants-in-mumbai-to-check-out-april-2026/ | AD22: Wave 4: not found in a web search beyond its source roundup — confirm it is open (Instagram / Google Maps) before outreach. | AG22: 1 of 1 read: https://foodiesofindia.wordpress.com/2026/04/02/20-new-restaurants-in-mumbai-to-check-out-april-2026/
A23: C022 | B23: A | C23: New (opened 2026) | D23: Premium | E23: Stand By Coffee — Juhu | F23: Cafe chain / multi-outlet | G23: West | H23: Maharashtra | I23: Mumbai | J23: Juhu (3rd outlet after Worli and Bandra) | K23: No (roasting partners) | L23: Pour-overs, espresso, matcha; first outlet with ube drinks. Seven Chikmagalur coffees from outside roasting partners. | M23: Works with outside roasting partners (unnamed) | N23: ₹600–1,700 for two | O23: Single-region roster (Chikmagalur only). | P23: Non-Chikmagalur estates (Northeast, Araku, Nilgiris, Odisha, Coorg) to diversify the 7-coffee wall. | Q23: Group pitch for all three outlets: offer a non-Karnataka estate as a guest pour-over across Worli, Bandra and Juhu. | R23: Mumbai-born cafe brand opened 3rd outlet in Juhu; menu has espresso, pour-over, matcha and ube drinks. Instagram bio: 7:30am–1am, phone numbers listed in bio, on Zomato/Swiggy. | S23: Growing indie brand with pour-over on menu — pitch rotating single-estate filter offering. | T23: Instagram DM | U23: @standbycoffee__ | V23: https://www.instagram.com/standbycoffee__/ | AB23: Aditya Wanwari (Toast Inc) | AC23: https://indianretailer.com/news/stand-coffee-expands-mumbai-footprint-new-juhu-outlet | AE23: Indian origins/estates: Chikmagalur; Brew: Pour over, Espresso tonic | AG23: 2 of 3 read: https://indianretailer.com/news/stand-coffee-expands-mumbai-footprint-new-juhu-outlet https://www.restaurantindia.in/news/stand-by-coffee-unveils-in-mumbai.n21574
A24: C023 | B24: A | C24: New (opened 2026) | D24: Premium | E24: Thought Coffee — Bandra flagship | F24: Cafe chain / multi-outlet | G24: West | H24: Maharashtra | I24: Mumbai | J24: Bandra | K24: Yes — 'single-estate AA, roasted in-house' (Restaurant India) | L24: Single-estate AA Arabica roasted in-house; rum- and wine-barrel-aged coffees; imported Colombian Castillo special; QSR under 5 minutes. | M24: Own roastery (single-estate AA, roasted in-house) | O24: Imports Colombian Castillo for its special; a QSR brand scaling across Mumbai needs volume + consistency. | P24: Green coffee (single-estate AA + an Indian replacement for the Castillo) for their roaster. | Q24: They roast: pitch green lots and an exclusive barrel-ageing lot as they densify across Mumbai. | R24: Mumbai-born quick-service specialty brand opening its Bandra flagship (Oct 2026 roundups); menu lists single-origin AA Arabica and barrel-aged coffees. Wave 4: Restaurant India (Sep 2026) says the beans are roasted in-house. | S24: Young brand building a menu of 'special' coffees — barrel-aged / experimental-process lots fit. | T24: Walk-in / Google Maps listing | AB24: Kush Kachhara, Kshitij Patil, Jhanvi Shah (founders) | AC24: https://www.restaurantindia.in/news/thought-coffee-opens-bandra-flagship-as-mumbai-quick-service-coffee-market-expands.n17296 | AD24: Instagram not indexed by search yet — look up by name on Instagram | AE24: Imported origins: Colombia; Processes / format: Single origin, Single estate | AG24: 2 of 3 read: https://www.restaurantindia.in/news/thought-coffee-opens-bandra-flagship-as-mumbai-quick-service-coffee-market-expands.n17296 https://www.passionateinmarketing.com/one-less-thought-thought-coffee-opens-in-bandra-with-quality-coffee/
A25: C024 | B25: A | C25: New (opened 2026) | D25: Premium | E25: Tsubaki Artisanal Coffee | F25: Independent specialty cafe | G25: West | H25: Maharashtra | I25: Mumbai | J25: Kandivali | K25: Unknown | L25: Not published | M25: Not published — ask on first contact (look at the retail shelf / bag on the bar) | P25: Suburban specialty with little competition — exclusive estates. | Q25: Just opened: offer a guest-lot month + free barista calibration; side-by-side cupping against their current beans; ask which roaster/estates they use and what they'd change. | R25: New artisanal coffee spot (Foodies of India, Jun 2026). | T25: Walk-in / Google Maps listing | AC25: https://foodiesofindia.wordpress.com/2026/06/01/june-2026-new-restaurants-in-mumbai-you-need-to-visit/ | AD25: Wave 4: not found in a web search beyond its source roundup — confirm it is open (Instagram / Google Maps) before outreach. | AG25: 1 of 1 read: https://foodiesofindia.wordpress.com/2026/06/01/june-2026-new-restaurants-in-mumbai-you-need-to-visit/
A26: C025 | B26: A | C26: New (late 2025) | D26: Premium | E26: Tuskin Coffee | F26: Independent specialty cafe | G26: West | H26: Maharashtra | I26: Mumbai | J26: Bandra | K26: Unknown | L26: Not published | M26: Not published — ask on first contact (look at the retail shelf / bag on the bar) | P26: Rotating single-estate / micro-lot for the filter bar + a single-origin espresso option. | Q26: Just opened: offer a guest-lot month + free barista calibration; side-by-side cupping against their current beans; ask which roaster/estates they use and what they'd change. | R26: Specialty coffee spot (Foodies of India, Oct 2025). | T26: Walk-in / Google Maps listing | AC26: https://foodiesofindia.wordpress.com/2025/10/01/25-new-restaurants-cafes-to-check-out-in-mumbai-this-october-2025/ | AD26: Wave 4: not found in a web search beyond its source roundup — confirm it is open (Instagram / Google Maps) before outreach. | AG26: 1 of 1 read: https://foodiesofindia.wordpress.com/2025/10/01/25-new-restaurants-cafes-to-check-out-in-mumbai-this-october-2025/
A27: C026 | B27: B | C27: New (opened 2026) | D27: Normal | E27: Cafe Quattro — Babulnath | F27: Cafe chain / multi-outlet | G27: West | H27: Maharashtra | I27: Mumbai | J27: Babulnath (inside a theatre) + Juhu | K27: Unknown | L27: Specialty coffees, cold brews, Vietnamese coffee, coffee mocktails; all-veg. | M27: Not published — ask on first contact (look at the retail shelf / bag on the bar) | P27: Premium house espresso blend of Indian estates + one rotating single estate + cold-brew lot. | Q27: Just opened: offer a guest-lot month + free barista calibration; side-by-side cupping against their current beans; ask which roaster/estates they use and what they'd change. | R27: Second Mumbai cafe; vegetarian dining + specialty coffee + quick service. | S27: Food-led; pitch a dependable house blend. | T27: Walk-in / Google Maps listing | AC27: https://www.indianretailer.com/news/cafe-quattro-opens-second-mumbai-cafe-mumbai | AE27: Imported origins: Vietnam; Brew: Cold brew; ₹ 1200 for two | AG27: 3 of 3 read: https://www.eazydiner.com/mumbai/cafe-quattro-juhu-western-suburbs-707486 https://www.indianretailer.com/news/cafe-quattro-opens-second-mumbai-cafe-mumbai https://www.restaurantindia.in/news/caf-quattro-opens-second-outlet-in-babulnath-south-mumbai.n16988
A28: C027 | B28: B | C28: New (opened 2026) | D28: Normal | E28: DRNK Apartment | F28: Independent specialty cafe | G28: West | H28: Maharashtra | I28: Mumbai | J28: Andheri | K28: Unknown | L28: Matcha-led dessert coffees (s'mores latte); Time Out 4/5; Andheri outpost of Bandra's DRNK. | M28: Not published — ask on first contact (look at the retail shelf / bag on the bar) | P28: Premium house espresso blend of Indian estates + one rotating single estate + cold-brew lot. | Q28: Just opened: offer a guest-lot month + free barista calibration; side-by-side cupping against their current beans; ask which roaster/estates they use and what they'd change. | R28: Third-place cafe and matcha spot in Andheri (Man's World India restaurant update). | S28: Matcha-led; pitch espresso + filter to round out coffee side. | T28: Walk-in / Google Maps listing | AC28: https://www.mansworldindia.com/lifestyle/mw-restaurant-update-every-place-you-need-to-check-out-in-mumbai-right-now | AD28: Opening date not confirmed | AG28: 1 of 3 read: https://oteats.outlooktraveller.com/features/guides/the-coolest-new-openings-in-mumbai-you-need-to-be-on-the-lookout-for
A29: C028 | B29: B | C29: New (opened 2026) | D29: Normal | E29: Grounded | F29: Independent specialty cafe | G29: West | H29: Maharashtra | I29: Mumbai | J29: Khar | K29: Unknown | L29: Not published | M29: Not published — ask on first contact (look at the retail shelf / bag on the bar) | P29: Premium house espresso blend of Indian estates + one rotating single estate + cold-brew lot. | Q29: Just opened: offer a guest-lot month + free barista calibration; side-by-side cupping against their current beans; ask which roaster/estates they use and what they'd change. | R29: Community-driven cafe, good coffee + wholesome food (Jan 2026). | T29: Walk-in / Google Maps listing | AC29: https://foodiesofindia.wordpress.com/2026/01/15/january-2026-30-new-restaurants-cafes-in-mumbai-you-need-to-check-out/ | AE29: Signals: Now open | AG29: 2 of 3 read: https://foodiesofindia.wordpress.com/2026/01/15/january-2026-30-new-restaurants-cafes-in-mumbai-you-need-to-check-out/ https://www.indianretailer.com/restaurant/article/bandra-gets-a-new-enchanting-caf-grounded.14232
A30: C029 | B30: B | C30: Established | D30: Normal | E30: Kerb Coffee Co. | F30: Independent specialty cafe | G30: West | H30: Maharashtra | I30: Mumbai | J30: Khar West | K30: Unknown | L30: Not published | M30: Not published — ask on first contact (look at the retail shelf / bag on the bar) | P30: Premium house espresso blend of Indian estates + one rotating single estate + cold-brew lot. | Q30: Established: position as a second roaster / rotating single estate; walk-in cupping with the head barista. | R30: Hiring baristas in 2026 (Glassdoor listing). | S30: Indie in Khar specialty belt — sample drop. | T30: Walk-in / Google Maps listing | AC30: https://www.glassdoor.co.in/Job/mumbai-barista-jobs-SRCH_IL.0,6_IC2851180_KO7,14.htm | AD30: Tier/coffee programme not confirmed Wave 4: not found in a web search beyond its source roundup — confirm it is open (Instagram / Google Maps) before outreach. | AG30: 0 of 1 read:
A31: C030 | B31: B | C31: New (opened 2026) | D31: Normal | E31: Linking House | F31: All-day / food-led cafe | G31: West | H31: Maharashtra | I31: Mumbai | J31: Linking Rd, Santacruz W (4,000 sq ft, 120 seats) | K31: Unknown | L31: Not published | M31: Not published — ask on first contact (look at the retail shelf / bag on the bar) | P31: Premium house espresso blend of Indian estates + one rotating single estate + cold-brew lot. | Q31: Just opened: offer a guest-lot month + free barista calibration; side-by-side cupping against their current beans; ask which roaster/estates they use and what they'd change. | R31: All-day: coffee & bakery by day, dinner & cocktails later (Esquire, Sep 2026). | T31: Walk-in / Google Maps listing | AB31: Riya Goon & Vivek Chandaliya | AC31: https://www.esquireindia.co.in/food-and-drinks/what-to-eat/from-rola-to-the-mahjong-club-9-new-restaurants-and-caf%C3%A9s-in-mumbai-to-try-this-september | AE31: Brew: Cold brew, Affogato | AG31: 2 of 2 read: https://www.esquireindia.co.in/food-and-drinks/what-to-eat/from-rola-to-the-mahjong-club-9-new-restaurants-and-caf%C3%A9s-in-mumbai-to-try-this-september https://www.restaurantindia.in/news/linking-house-opens-on-linking-road-with-120-seats-and-day-to-night-dining.n17078
A32: C031 | B32: B | C32: New (opened 2026) | D32: Normal | E32: Lygon St | F32: Independent specialty cafe | G32: West | H32: Maharashtra | I32: Mumbai | J32: Andheri | K32: Unknown | L32: Not published | M32: Not published — ask on first contact (look at the retail shelf / bag on the bar) | P32: Premium house espresso blend of Indian estates + one rotating single estate + cold-brew lot. | Q32: Just opened: offer a guest-lot month + free barista calibration; side-by-side cupping against their current beans; ask which roaster/estates they use and what they'd change. | R32: Feb 2026 opening (Foodies of India); name references Melbourne's cafe street. | T32: Walk-in / Google Maps listing | AC32: https://foodiesofindia.wordpress.com/2026/02/01/february-2026-new-restaurants-in-mumbai-you-need-to-try/ | AD32: Coffee programme not described Wave 4: not found in a web search beyond its source roundup — confirm it is open (Instagram / Google Maps) before outreach. | AG32: 1 of 1 read: https://foodiesofindia.wordpress.com/2026/02/01/february-2026-new-restaurants-in-mumbai-you-need-to-try/
A33: C032 | B33: B | C33: Established | D33: Normal | E33: Mazi Mumbai | F33: Independent specialty cafe | G33: West | H33: Maharashtra | I33: Mumbai | J33: Mazi Coffee Bar & Kitchen — 27C Sujata Rajpipla CHS, Juhu Tara Rd, Santacruz W | K33: Unknown | L33: Beverage Union roasts for the bar: classics, special cold brews, Orange Brew, passion-fruit espresso tonic. | M33: Beverage Union coffee roasters | N33: EazyDiner 4.5 (222) | P33: Premium house espresso blend of Indian estates + one rotating single estate + cold-brew lot. | Q33: Position as a guest single estate beside Beverage Union for the specials menu. | R33: Instagram: artisanal community cafe, 8am–11pm. Wave 4: Free Press Journal review names Beverage Union as the roaster. | S33: Community cafe — blend + filter. | T33: Instagram DM | U33: @mazicoffee | V33: https://www.instagram.com/mazicoffee/ | AC33: https://www.instagram.com/mazicoffee/ | AG33: 0 of 4 read:
A34: C033 | B34: B | C34: Established | D34: Normal | E34: Mokai | F34: All-day / food-led cafe | G34: West | H34: Maharashtra | I34: Mumbai | J34: Moved to Pali Hill, Bandra (Mokai 2.0, Mar 2026) | K34: Unknown | L34: House blend from Chikmagalur; IMPORTED blends from Singapore, South America and Africa via Common Man Roasters; Kyoto cold brew; Southeast Asian 'Traveller's menu'. | M34: Common Man Roasters (Singapore) + a Chikmagalur house blend | N34: ₹1,400–1,500 for two | O34: Imported coffees carry the premium slot. | P34: Indian naturals/anaerobics as the 'traveller' origins; a Kyoto-drip lot. | Q34: Import-replacement pitch: landed cost and freshness vs Singapore imports; tie to their Asian menu with Northeast Indian lots. | R34: All-day brunch cafe known for matcha lineup; on Mumbai specialty lists. Wave 4: Time Out names Common Man Roasters (Singapore) as roasting partner. | S34: House espresso blend. | T34: Walk-in / Google Maps listing | AC34: https://www.district.in/blog/speciality-coffee-spots-mumbai | AE34: Indian origins/estates: Chikmagalur; Imported origins: Brazil, Burundi; Processes / format: House blend; Brew: South Indian filter, Moka pot, Cortado, Affogato; Foreign roasters: Common Man Roasters; Prices: Coffee • ₹600 for two | Coffee • ₹800 for two | Coffee • ₹1400 for two; ₹600 for two | AG34: 5 of 5 read: https://www.district.in/blog/speciality-coffee-spots-mumbai https://www.timeout.com/mumbai/restaurants/mokai https://www.timeout.com/mumbai/news/this-famous-cafe-is-shifting-from-bandra-to-bandra-031826 https://curlytales.com/ctexclusive-streets-of-japan-come-alive-at-bandra-in-the-form-of-new-coffeehouse-dining-spot-mokai
A35: C034 | B35: B | C35: Established | D35: Normal | E35: Mumbai Blondie | F35: Cafe chain / multi-outlet | G35: West | H35: Maharashtra | I35: Mumbai | J35: Blondie by Bastian Hospitality — Khar; sister cafes Janu (Juhu) and The Blondie House (Versova) | K35: Unknown | L35: Mumbai's first matcha bar + Slow Bar (V60, French press, AeroPress); Chikmagalur + Ethiopia and Costa Rica single origins. | M35: Not published — ask on first contact (look at the retail shelf / bag on the bar) | O35: Imported single origins on the slow bar. | P35: Premium house espresso blend of Indian estates + one rotating single estate + cold-brew lot. | Q35: Group deal with Bastian Hospitality (Blondie, Janu, Blondie House): Indian single origins for the slow bar across all three. | R35: Instagram: specialty coffee, cocktails, matcha & bakes, 9am–midnight. | S35: Coffee-cocktail programme. | T35: Instagram DM | U35: @mumbaiblondie | V35: https://www.instagram.com/mumbaiblondie/ | AC35: https://www.restaurantindia.in/news/bastian-hospitality-enters-coffee-space-with-blondie.n12554 | AG35: 0 of 2 read:
A36: C035 | B36: B | C36: New (opened 2026) | D36: Normal | E36: NOT FAR | F36: Bakery / patisserie cafe | G36: West | H36: Maharashtra | I36: Mumbai | J36: Bandra | K36: No | L36: Coffee programme sourced from Corridor Seven, picked to match the cookies and cupcakes. | M36: Corridor Seven Coffee Roasters (Nagpur) | O36: Single roaster. | P36: Second roaster / seasonal guest bean. | Q36: Compare cup vs Corridor Seven at a tasting. | R36: Speciality cookies, cupcakes and coffee (Curly Tales, Jul 2026). | T36: Walk-in / Google Maps listing | AC36: https://www.restaurantindia.in/news/notfar-opens-in-bandra-with-specialty-cookies-cupcakes-and-coffee.n16686 | AG36: 0 of 1 read:
A37: C036 | B37: B | C37: New (opened 2026) | D37: Normal | E37: Namah Bengaluru Coffee House | F37: Independent specialty cafe | G37: West | H37: Maharashtra | I37: Mumbai | J37: Four Bungalows, Andheri W (7am–11:30pm) | K37: Unknown | L37: Darshini-style South Indian tiffin + filter coffee. | M37: Not published — ask on first contact (look at the retail shelf / bag on the bar) | N37: ~₹400 for two | P37: A filter-coffee blend (peaberry/robusta with optional chicory) — not single origin. | Q37: Pitch a filter-coffee decoction blend with consistent volume pricing. | R37: New coffee house (Foodies of India, Jun 2026). | T37: Instagram DM | U37: @namah.mumbai | V37: https://www.instagram.com/namah.mumbai/ | AB37: Arvind & Pallavi Shetty | AC37: https://foodiesofindia.wordpress.com/2026/06/01/june-2026-new-restaurants-in-mumbai-you-need-to-visit/ | AE37: Brew: South Indian filter; Signals: Coming soon, Now open | AG37: 3 of 4 read: https://foodiesofindia.wordpress.com/2026/06/01/june-2026-new-restaurants-in-mumbai-you-need-to-visit/ https://www.freepressjournal.in/lifestyle/food-review-we-tried-mumbais-viral-new-south-indian-spot-namah-is-it-worth-the-hype https://www.freepressjournal.in/lifestyle/narayan-rane-shreyas-talpade-others-join-star-studded-launch-of-new-south-indian-joint-in-mumbai
A38: C037 | B38: B | C38: New (opened 2026) | D38: Normal | E38: Pardon Our French | F38: Bakery / patisserie cafe | G38: West | H38: Maharashtra | I38: Mumbai | J38: Ballard Estate, Fort | K38: Unknown | L38: Parisian coffee shop (22 seats): rosemary & salted-honey cold brew, salted drinks. | M38: Not published — ask on first contact (look at the retail shelf / bag on the bar) | P38: Premium house espresso blend of Indian estates + one rotating single estate + cold-brew lot. | Q38: Approach via the consultant (Geetu Mohnani) who curated the menu — she can specify beans for other clients too. | R38: New pastry-led cafe from chef Pooja Dhingra. | S38: Patisserie pairing coffee. | T38: Walk-in / Google Maps listing | AB38: Pooja Dhingra; beverage programme by coffee consultant Geetu Mohnani | AC38: https://www.thestylelist.in/post/new-restaurants-cafes-bars-india | AE38: Indian origins/estates: Ballard Estate, Mumbai’s Ballard Estate; Brew: Cold brew; Signals: Now open | AG38: 2 of 4 read: https://thenodmag.com/content/pardon-our-french-pooja-dhingra-cafe-ballard-estate-mumbai-review https://curlytales.com/pardon-our-french-pooja-dhingra-has-a-new-cafe-in-mumbai-hint-its-not-in-bandra
A39: C038 | B39: B | C39: New (opened 2026) | D39: Normal | E39: Project Hum | F39: All-day / food-led cafe | G39: West | H39: Maharashtra | I39: Mumbai | J39: Bandra + Versova (kaviar:collaborative design) | K39: Unknown | L39: Curated specialty programme with Subko; traceable sourcing; grab-and-go window in Versova. | M39: Subko | P39: Premium house espresso blend of Indian estates + one rotating single estate + cold-brew lot. | Q39: Position as a guest single estate alongside Subko, not a replacement. | R39: In Foodies of India's Sep–Oct 2026 openings. Wave 4: Grazia/Elle Decor coverage names Subko as the coffee partner. | T39: Walk-in / Google Maps listing | AB39: Jatin Talreja (co-founder) | AC39: https://foodiesofindia.wordpress.com/tag/new-restaurants-in-mumbai/ | AD39: Coffee programme not described | AG39: 3 of 5 read: https://www.harpersbazaar.in/travel-food/story/14-new-restaurants-across-india-that-should-be-on-your-dining-list-2268 https://elledecor.in/cafe-project-hum-mumbai-by-kaviar-collaborative/ https://www.localsamosa.com/food-and-drinks/coffee-shops-in-mumbai-10068806
A40: C039 | B40: B | C40: New (opened 2026) | D40: Normal | E40: ROST | F40: Independent specialty cafe | G40: West | H40: Maharashtra | I40: Mumbai | J40: Mahesh Building, Khar W | K40: Unknown | L40: Not published | M40: Not published — ask on first contact (look at the retail shelf / bag on the bar) | P40: Premium house espresso blend of Indian estates + one rotating single estate + cold-brew lot. | Q40: Just opened: offer a guest-lot month + free barista calibration; side-by-side cupping against their current beans; ask which roaster/estates they use and what they'd change. | R40: French toast + coffee bar (Esquire, Sep 2026). | T40: Walk-in / Google Maps listing | AB40: Param Arora (co-founder) | AC40: https://www.esquireindia.co.in/food-and-drinks/what-to-eat/from-rola-to-the-mahjong-club-9-new-restaurants-and-caf%C3%A9s-in-mumbai-to-try-this-september | AE40: Indian origins/estates: Karnataka; Brew: V60, Cold brew, Affogato | AG40: 1 of 3 read: https://www.timeout.com/mumbai/restaurants/rost
A41: C040 | B41: B | C41: New (opened 2026) | D41: Normal | E41: San's in the Bay | F41: All-day / food-led cafe | G41: West | H41: Maharashtra | I41: Mumbai | J41: Kala Ghoda | K41: Unknown | L41: Not published | M41: Not published — ask on first contact (look at the retail shelf / bag on the bar) | P41: Premium house espresso blend of Indian estates + one rotating single estate + cold-brew lot. | Q41: Just opened: offer a guest-lot month + free barista calibration; side-by-side cupping against their current beans; ask which roaster/estates they use and what they'd change. | R41: Contemporary cafe serving specialty brews (2026 India openings roundup). | S41: Pitch house espresso + one rotating single estate. | T41: Walk-in / Google Maps listing | AC41: https://www.thestylelist.in/post/new-restaurants-cafes-bars-india | AD41: Single source Wave 4: not found in a web search beyond its source roundup — confirm it is open (Instagram / Google Maps) before outreach. | AG41: 0 of 1 read:
A42: C041 | B42: B | C42: New (opened 2026) | D42: Normal | E42: Vanilla Miel — Lower Parel | F42: Bakery / patisserie cafe | G42: West | H42: Maharashtra | I42: Mumbai | J42: Lodha Signet, Lower Parel (also Pali Village) | K42: Unknown | L42: Micro-roasted, low-acidity MEDIUM-DARK roast from high-altitude Chikmagalur estates; honey-cinnamon, crème-brûlée and tiramisu lattes, iced Vietnamese, vanilla-bean shakerato; orange-basil and spiced-guava cold brews; 'VM House Phin'; ceremonial matcha. | M42: Not published (Chikmagalur estates, medium-dark) | O42: One medium-dark espresso profile; no light roast or pour-over. | P42: A light/medium single estate for a filter or pour-over slot, plus a seasonal lot for dessert pairing. | Q42: Dessert-led brand: pitch a coffee-and-dessert pairing tasting at Lodha Signet and a co-branded seasonal lot. | R42: Patisserie-cafe brand's second cafe (Oct 2026). | S42: Patisserie pairing coffee. | T42: Walk-in / Google Maps listing | AB42: Isha & Mansi Shetty (founders) | AC42: https://www.restaurantindia.in/news/vanilla-miel-opens-second-mumbai-caf-at-lodha-signet-lower-parel.n17346 | AE42: Indian origins/estates: Chikmagalur; Imported origins: Vietnam; Processes / format: Experimental lot, Single origin; Brew: Cold brew, Cortado, Tasting flight / omakase; ₹2,000 for two; Signals: Wholesale / cafe partners | AG42: 4 of 4 read: https://curlytales.com/india/food/new-mumbai-restaurants-in-october-youll-want-to-tell-your-friends-about/ https://www.restaurantindia.in/news/vanilla-miel-opens-second-mumbai-caf-at-lodha-signet-lower-parel.n17346 https://luxebook.in/?p=82147 https://finelychopped.net/?p=75976
A43: C042 | B43: B | C43: Upcoming / Coming soon | D43: Premium | E43: Boojee Cafe — One BKC | F43: Roaster-cafe (roasts in-house) | G43: West | H43: Maharashtra | I43: Mumbai | J43: One BKC, Bandra Kurla Complex | K43: Yes | L43: Not published | M43: Own roastery | P43: Green coffee or a limited guest micro-lot collaboration (they roast in-house). | Q43: Don't pitch roasted supply — offer green lots or a co-branded guest micro-lot. | R43: Time Out (Aug 2026) reported Boojee's 5th Mumbai outlet opening soon at One BKC; Boojee runs as neighbourhood cafe + creative roastery. | S43: Roasts own, but expanding fast — pitch a limited guest single-estate for the BKC launch menu. | T43: Walk-in / Google Maps listing | AC43: https://www.timeout.com/mumbai/news/boojee-cafe-is-opening-a-new-outlet-at-one-bkc-in-mumbai-082026 | AD43: Wave 4: BKC still 'coming soon' (Time Out, Aug 2026); would be Boojee's 5th outlet. | AE43: Roasters named in articles about it: Boojee Cafe & Roastery; Brew: Flat white, Cold brew; ₹2,000 for two; Signals: Coming soon | AG43: 3 of 3 read: https://www.timeout.com/mumbai/news/boojee-cafe-is-opening-a-new-outlet-at-one-bkc-in-mumbai-082026 https://curlytales.com/india/food/mumbaikars-boojee-cafe-is-coming-to-bkc-with-its-signature-brews-bites/ https://www.freepressjournal.in/lifestyle/from-bandra-to-sobo-boojee-cafe-brings-its-classic-brews-brunch-to-south-mumbai
A44: C043 | B44: B | C44: Established | D44: Premium | E44: RITUAL daily coffee | F44: Independent specialty cafe | G44: West | H44: Maharashtra | I44: Mumbai | J44: Pali Market, Pali Hill + outlet inside Dawntown sneaker store (Bandra) | K44: Unknown | L44: Locally sourced single-origin beans; matcha menu; Vietnamese cold brew. | M44: Not published — ask on first contact (look at the retail shelf / bag on the bar) | P44: Rotating single-estate / micro-lot for the filter bar + a single-origin espresso option. | Q44: Established: position as a second roaster / rotating single estate; walk-in cupping with the head barista. | R44: Listed on Mumbai Coffee Collective's curated specialty list. | S44: Specialty indie — sample drop. | T44: Call / WhatsApp | Y44: +91 90829 43228 (reservations) | AB44: Chef Rahul Ramnani & Meher Kohli (founders) | AC44: https://mumbaicoffeecollective.com/pages/specialty-coffee-mumbai | AD44: Location/format not confirmed | AG44: 1 of 5 read: https://wanderlog.com/place/details/9635733/ritual-daily-coffee
A45: C044 | B45: B | C45: Established | D45: Premium | E45: Shelter | F45: All-day / food-led cafe | G45: West | H45: Maharashtra | I45: Mumbai | J45: 28 JP Rd, Versova (3 floors) — Javaphile group | K45: Unknown | L45: Not published | M45: Not published — ask on first contact (look at the retail shelf / bag on the bar) | N45: ~₹1,200 for two; District 4.6 (1,051) | O45: Reviews call the coffee 'average' while the food is praised. | P45: Rotating single-estate / micro-lot for the filter bar + a single-origin espresso option. | Q45: Pitch with Javaphile (same group); lead with an upgrade of the house espresso. | R45: Instagram: neighbourhood cafe — food, speciality coffee, unhurried moments. | T45: Instagram DM | U45: @sheltercafe.mumbai | V45: https://www.instagram.com/sheltercafe.mumbai/ | Y45: +91 93214 70550 (LBB) | AC45: https://www.instagram.com/sheltercafe.mumbai/ | AE45: ₹1200 for two | AF45: +91 93214 70550 | AG45: 5 of 5 read: https://www.district.in/dining/mumbai/shelter-x-coffee-by-javaphile-versova https://hospibuz.com/shelter-by-javaphile-in-versova-unveils-a-new-chapter-in-community-dining https://curlytales.com/more-than-a-regular-cafe-this-3-storeyed-haunt-in-versova-has-a-library-cafe-rooftop-vibes-more https://www.knocksense.com/mumbai/bandras-javaphile-has-a-new-shelter-in-versova-it-is-the-talk-of-the-town
A46: C045 | B46: B | C46: Established | D46: Premium | E46: The Brew Cafe — Thakur Village | F46: Independent specialty cafe | G46: West | H46: Maharashtra | I46: Mumbai | J46: 1 Viceroy Court, Thakur Village, Kandivali E | K46: Unknown | L46: Not published | M46: Not published — ask on first contact (look at the retail shelf / bag on the bar) | N46: ~₹500 for two (pure veg) | P46: Rotating single-estate / micro-lot for the filter bar + a single-origin espresso option. | Q46: Established: position as a second roaster / rotating single estate; walk-in cupping with the head barista. | R46: Instagram: specialty coffee, freshly roasted beans, 9am–midnight. | T46: Instagram DM | U46: @thebrewcafemumbai | V46: https://www.instagram.com/thebrewcafemumbai/ | AC46: https://www.instagram.com/thebrewcafemumbai/ | AE46: ₹ 500 for two | AG46: 1 of 1 read: https://www.eazydiner.com/mumbai/the-brew-cafe-kandivali-east-western-suburbs-695614
A47: C046 | B47: B | C47: Established | D47: Premium | E47: bōkka coffee | F47: Cafe chain / multi-outlet | G47: West | H47: Maharashtra | I47: Mumbai | J47: 16th Rd, Pali Hill, Bandra | K47: Unknown | L47: India's first coffee-on-tap: ready-to-serve tap drinks, 18-hour cold drip, matcha on tap; spill-proof cans. | M47: Not published — ask on first contact (look at the retail shelf / bag on the bar) | P47: Batch-brew/cold-drip lots sized for tap systems; can-friendly cold brew concentrate. | Q47: Pitch a cold-drip lot with fixed specs for their tap system. | R47: Instagram: specialty coffee shop, 3 outlets, 8am–11pm. | S47: Fast-growing indie chain — rotating single estate. | T47: Instagram DM | U47: @bokkacoffeemumbai | V47: https://www.instagram.com/bokkacoffeemumbai/ | AB47: Karishma Dalal (Bombay Salad Co), Karan Gaba, barista Travis Braganza | AC47: https://www.instagram.com/bokkacoffeemumbai/ | AG47: 0 of 3 read:
A48: C047 | B48: C | C48: New (opened 2026) | D48: Normal | E48: AlienKind | F48: Cafe chain / multi-outlet | G48: West | H48: Maharashtra | I48: Mumbai | J48: Andheri | K48: Unknown | L48: Bengaluru UFO-burger QSR (5 BLR + 4 DEL); coffee drinks such as The Cloudy. | M48: Not published — ask on first contact (look at the retail shelf / bag on the bar) | P48: Premium house espresso blend of Indian estates + one rotating single estate + cold-brew lot. | Q48: Just opened: offer a guest-lot month + free barista calibration; side-by-side cupping against their current beans; ask which roaster/estates they use and what they'd change. | R48: Immersive cafe (Aug 2026). | T48: Walk-in / Google Maps listing | AC48: https://foodiesofindia.wordpress.com/2026/08/04/new-restaurants-cafes-in-mumbai-august-2026/ | AE48: Commodity brands: Nespresso | AG48: 3 of 3 read: https://foodiesofindia.wordpress.com/2026/08/04/new-restaurants-cafes-in-mumbai-august-2026/ https://www.restaurantindia.in/news/alienkind-opens-its-biggest-outlet-in-mumbais-oshiwara.n16757 https://indianretailer.com/news/alienkind-expands-retail-presence-first-mumbai-outlet
A49: C048 | B49: C | C49: New (opened 2026) | D49: Normal | E49: Belsta Coffee | F49: Independent specialty cafe | G49: West | H49: Maharashtra | I49: Mumbai | J49: Scooter (Activa) coffee stall, Union Park / Carter Rd, Bandra (from 7:30 pm) | K49: Unknown | L49: Espresso, Vietnamese shakerato, mochas, lattes from a scooter; vegan milk. | M49: Not published — ask on first contact (look at the retail shelf / bag on the bar) | N49: Espresso ₹67, cappuccino ₹97, max ₹137 | O49: Very low price point — a premium single estate would not fit the margin. | P49: Premium house espresso blend of Indian estates + one rotating single estate + cold-brew lot. | Q49: Just opened: offer a guest-lot month + free barista calibration; side-by-side cupping against their current beans; ask which roaster/estates they use and what they'd change. | R49: Coffee-focused opening (Foodies of India, Feb 2026). | T49: Walk-in / Google Maps listing | AB49: Suraj Kumar | AC49: https://foodiesofindia.wordpress.com/2026/02/01/february-2026-new-restaurants-in-mumbai-you-need-to-try/ | AD49: Wave 4: a coffee cart, not a cafe — kept as a low-volume Normal lead. | AE49: Prices: Serving Cappuccinos Starting At ₹67, Mumbai’s Cutest Coffee Spot Runs On An Activa! | London For The 1st Time Suraj is serving espresso for just ₹67 and cappuccino that | r just ₹67 and cappuccino that will blow your mind for just ₹97. His limited coffee | AG49: 2 of 2 read: https://foodiesofindia.wordpress.com/2026/02/01/february-2026-new-restaurants-in-mumbai-you-need-to-try/ https://curlytales.com/india/food/serving-cappuccinos-starting-at-mumbais-cutest-coffee-spot-runs-on-an-activa/
A50: C049 | B50: C | C50: New (late 2025) | D50: Normal | E50: Cafe Chikory | F50: All-day / food-led cafe | G50: West | H50: Maharashtra | I50: Mumbai | J50: 43 Raja Bahadur Compound, Tamarind Lane, Fort | K50: Unknown | L50: Not published | M50: Not published — ask on first contact (look at the retail shelf / bag on the bar) | N50: ~₹350 for two | P50: Premium house espresso blend of Indian estates + one rotating single estate + cold-brew lot. | Q50: Just opened: offer a guest-lot month + free barista calibration; side-by-side cupping against their current beans; ask which roaster/estates they use and what they'd change. | R50: For brunch and specialty coffee lovers (Oct 2025). | T50: Walk-in / Google Maps listing | AC50: https://foodiesofindia.wordpress.com/2025/10/01/25-new-restaurants-cafes-to-check-out-in-mumbai-this-october-2025/ | AE50: Brew: South Indian filter, Affogato; ₹350 for two | AF50: +91 77189 91865 | AG50: 2 of 2 read: https://www.district.in/dining/mumbai/cafe-chikory-fort https://foodiesofindia.wordpress.com/2025/10/01/25-new-restaurants-cafes-to-check-out-in-mumbai-this-october-2025/
A51: C050 | B51: C | C51: Established | D51: Normal | E51: Cafe Essence | F51: All-day / food-led cafe | G51: West | H51: Maharashtra | I51: Mumbai | J51: Devidayal Rd, Mulund W | K51: Unknown | L51: Not published | M51: Not published — ask on first contact (look at the retail shelf / bag on the bar) | P51: Premium house espresso blend of Indian estates + one rotating single estate + cold-brew lot. | Q51: Established: position as a second roaster / rotating single estate; walk-in cupping with the head barista. | R51: Pure-veg/Jain cafe with coffee, 8am–midnight. | T51: Instagram DM | U51: @cafeessence.mulund | V51: https://www.instagram.com/cafeessence.mulund/ | AC51: https://www.instagram.com/cafeessence.mulund/ | AD51: Wave 4b: only an 'Essence Cafe' listing found (location not stated) — confirm. Mulund already has Blue Tokai and Third Wave outlets. | AG51: 1 of 1 read: https://wanderlog.com/place/details/2904960/essence-cafe
A52: C051 | B52: C | C52: New (opened 2026) | D52: Normal | E52: Fold Bakehouse | F52: Bakery / patisserie cafe | G52: West | H52: Maharashtra | I52: Mumbai | J52: Bandra | K52: Unknown | L52: Not published | M52: Not published — ask on first contact (look at the retail shelf / bag on the bar) | P52: Premium house espresso blend of Indian estates + one rotating single estate + cold-brew lot. | Q52: Just opened: offer a guest-lot month + free barista calibration; side-by-side cupping against their current beans; ask which roaster/estates they use and what they'd change. | R52: Jul 2026 opening. | T52: Walk-in / Google Maps listing | AC52: https://foodiesofindia.wordpress.com/2026/07/01/new-restaurants-in-mumbai-july-2026-roundup/ | AD52: Wave 4: not found in a web search beyond its source roundup — confirm it is open (Instagram / Google Maps) before outreach. | AG52: 1 of 1 read: https://foodiesofindia.wordpress.com/2026/07/01/new-restaurants-in-mumbai-july-2026-roundup/
A53: C052 | B53: C | C53: New (opened 2026) | D53: Normal | E53: GOAT Brew | F53: Coffee + cocktail bar | G53: West | H53: Maharashtra | I53: Mumbai | J53: New Link Rd, Oshiwara | K53: Unknown | L53: Not published | M53: Not published — ask on first contact (look at the retail shelf / bag on the bar) | N53: ₹2,000–2,500 for two | P53: Premium house espresso blend of Indian estates + one rotating single estate + cold-brew lot. | Q53: Just opened: offer a guest-lot month + free barista calibration; side-by-side cupping against their current beans; ask which roaster/estates they use and what they'd change. | R53: Listed in Free Press Journal's Sep 2026 new Mumbai openings as a cafe-bar. Foodies of India Aug 2026: speciality cafe for artisanal coffee. | S53: Coffee cocktails — espresso blend + cold brew bulk. | T53: Walk-in / Google Maps listing | AB53: Lizaa Malik & Saurabh Pathak | AC53: https://foodiesofindia.wordpress.com/2026/08/04/new-restaurants-cafes-in-mumbai-august-2026/ | AD53: Coffee programme details not confirmed | AE53: ₹2500 for two | AG53: 3 of 4 read: https://www.district.in/dining/mumbai/goat-brew-oshiwara https://www.restaurantindia.in/news/goat-brew-launches-new-caf-restaurant-and-bar-in-mumbai.n16812 https://indianretailer.com/news/goat-brew-opens-new-cafe-and-bar-mumbai
A54: C053 | B54: C | C54: Established | D54: Normal | E54: Greenr | F54: Cafe chain / multi-outlet | G54: West | H54: Maharashtra | I54: Mumbai | J54: Goregaon (International Business Park, Oberoi Garden City — 12th outlet), Pali Hill (Bandra), Breach Candy; also NCR | K54: Unknown | L54: Plant-based menu with 'specialty coffee' (Goregaon); roaster not named. | M54: Not published — ask on first contact (look at the retail shelf / bag on the bar) | N54: ~₹2,500 for two (Bandra) | P54: Premium house espresso blend of Indian estates + one rotating single estate + cold-brew lot. | Q54: 12-outlet plant-based chain: central-procurement pitch — a house espresso plus an oat-milk-friendly single estate. | R54: 12th India outlet opened at a Mumbai commercial hub with specialty coffee offerings. | S54: Chain — central procurement pitch. | T54: Walk-in / Google Maps listing | AC54: https://www.restaurantindia.in/news/greenr-opens-12th-outlet-in-mumbai-s-goregaon-as-plant-based-chain-expands.n17065 | AD54: Coffee sourcing unknown | AE54: ₹500 for two | AG54: 4 of 4 read: https://indianretailer.com/news/ballard-pier-opens-mumbai-retail-and-dining https://www.restaurantindia.in/news/greenr-opens-12th-outlet-in-mumbai-s-goregaon-as-plant-based-chain-expands.n17065 https://www.knocksense.com/mumbai/bandras-greenr-cafe-beckons-foodies-in-mumbai-to-embrace-sustainable-fare-choices https://elledecor.in/new-greenr-cafe-mumbai-by-studio-hohma-and-stand-design/
A55: C054 | B55: C | C55: Established | D55: Normal | E55: Kala Ghoda Cafe | F55: All-day / food-led cafe | G55: West | H55: Maharashtra | I55: Mumbai | J55: Kala Ghoda | K55: Unknown | L55: Own blend of organic beans (origin not named); cafe + gallery + wine. | M55: Not published — ask on first contact (look at the retail shelf / bag on the bar) | P55: Premium house espresso blend of Indian estates + one rotating single estate + cold-brew lot. | Q55: Established: position as a second roaster / rotating single estate; walk-in cupping with the head barista. | R55: Long-running gallery-cafe, coffee + waffles. | S55: Heritage cafe; blend. | T55: Walk-in / Google Maps listing | AC55: https://theculturetrip.com/asia/india/articles/the-best-coffee-shops-in-mumbai | AG55: 1 of 2 read: https://fathomaway.com/kala-ghoda-cafe/
A56: C055 | B56: C | C56: New (opened 2026) | D56: Normal | E56: The Blondie House | F56: Bakery / patisserie cafe | G56: West | H56: Maharashtra | I56: Mumbai | J56: Versova (Sep 2026; Blondie + Janu under one roof) | K56: Unknown | L56: Not published | M56: Not published — ask on first contact (look at the retail shelf / bag on the bar) | P56: Premium house espresso blend of Indian estates + one rotating single estate + cold-brew lot. | Q56: Pitch with Blondie (same group). | R56: Multi-level community space combining Blondie's cafe/bakery with Janu's menu (Oct 2026). | S56: Bakery-cafe; house blend. | T56: Walk-in / Google Maps listing | AC56: https://curlytales.com/india/food/new-mumbai-restaurants-in-october-youll-want-to-tell-your-friends-about/ | AE56: Brew: Tasting flight / omakase, South Indian filter; ₹2,000 for two | AG56: 4 of 4 read: https://curlytales.com/india/food/new-mumbai-restaurants-in-october-youll-want-to-tell-your-friends-about/ https://www.restaurantindia.in/news/bastian-hospitality-opens-the-blondie-house-in-versova.n17320 https://indianretailer.com/news/blondie-house-opens-new-community-cafe-versova https://t2online.in/goodlife/food-beverage/blondie-and-janu-find-a-new-home-in-versova--mumbai/2008352
A57: C056 | B57: C | C57: New (opened 2026) | D57: Premium | E57: Angry Toast | F57: Roaster-cafe (roasts in-house) | G57: West | H57: Maharashtra | I57: Mumbai | J57: Waterfield Rd, Bandra W (450 sq ft; opened 16 Jul 2026) | K57: Yes — in-house micro-roastery | L57: On-site micro-roastery; hot and cold coffee, cold brew, matcha, taro latte; 3-inch sandwiches sold in pairs. | M57: Own roastery (micro-roastery) | P57: Green coffee / guest lots for its micro-roastery. | Q57: They roast: pitch green lots to the coffee lead. | R57: Sandwich shop + micro-roastery, opened 16 Jul 2026; coffee led by a WBC semi-finalist. | T57: Walk-in / Google Maps listing | AB57: Blabber Hospitality; Suhas Dwarakanath (coffee lead, WBC semi-finalist) | AC57: https://www.timeout.com/mumbai/news/angry-toast-bandras-new-sandwich-shop-has-its-own-coffee-roastery-071626 | AE57: Indian origins/estates: Coorg / Kodagu, Wayanad; Imported origins: Vietnam; Brew: Cold brew; Signals: Coming soon | AG57: 2 of 2 read: https://www.timeout.com/mumbai/news/angry-toast-bandras-new-sandwich-shop-has-its-own-coffee-roastery-071626 https://homegrown.co.in/homegrown-explore/angry-toast-opens-in-bandra-with-3-inch-sandwiches-an-in-house-coffee-roastery
A58: C057 | B58: B | C58: Established | D58: Normal | E58: Bouffage Cafe and Bistro | F58: All-day / food-led cafe | G58: West | H58: Maharashtra | I58: Nagpur | J58: Sanskrutik Sankul, Ambazari Rd, Shankar Nagar | K58: Unknown | L58: Not published | M58: Corridor Seven Coffee Roasters | O58: Pour-over quality flagged by reviewers. | P58: Better filter beans + barista calibration. | Q58: Established: position as a second roaster / rotating single estate; walk-in cupping with the head barista. | R58: Serves pour-over (reviews mixed on quality). | T58: Call / WhatsApp | Y58: 098237 77849 (Curly Tales) | AB58: Anshul & Dewansh Jaiswal | AC58: https://www.nagpurtoday.in/best-cafes-in-nagpur-2026-our-independent-ranking-based-on-reviews-coffee-quality-ambience-customer-experience/ | AE58: Roasters named in articles about it: Corridor Seven Coffee Roasters; Signals: Coming soon | AG58: 4 of 4 read: https://www.nagpurtoday.in/best-cafes-in-nagpur-2026-our-independent-ranking-based-on-reviews-coffee-quality-ambience-customer-experience/ https://curlytales.com/every-coffee-lover-must-head-to-bouffage-cafe-in-nagpur https://www.nagpurtoday.in/inside-the-grand-feast-a-conversation-with-anshul-and-dewansh-jaiswal-of-bouffage/ https://wanderlog.com/place/details/3061288/bouffage-cafe-and-bistro
A59: C058 | B59: B | C59: Established | D59: Normal | E59: Oro's India | F59: All-day / food-led cafe | G59: West | H59: Maharashtra | I59: Nagpur | J59: ORO's Wood-Fired Pizza & Speciality Coffee — Ved Bhumi Apt, Abhyankar Marg, Dhantoli | K59: Unknown | L59: Not published | M59: Not published — ask on first contact (look at the retail shelf / bag on the bar) | N59: ~₹1,500 for two (pure veg) | P59: Premium house espresso blend of Indian estates + one rotating single estate + cold-brew lot. | Q59: Established: position as a second roaster / rotating single estate; walk-in cupping with the head barista. | R59: Instagram: specialty coffee, pizza, pasta, bakes, 9am–midnight. | S59: Nagpur's specialty-labelled cafe. | T59: Instagram DM | U59: @oros_india | V59: https://www.instagram.com/oros_india/ | AC59: https://www.instagram.com/oros_india/ | AE59: Prices: o at ORO's: Gourmet Wood-Fired Pizza & Speciality Coffee is ₹ 1500. You can save EXTRA; ₹ 1500 for two | AG59: 1 of 1 read: https://www.eazydiner.com/nagpur/oros-gourmet-wood-fired-pizza-speciality-coffee-dhantoli-nagpur-713990
A60: C059 | B60: B | C60: Established | D60: Normal | E60: Retreat Cafe & Eatery | F60: All-day / food-led cafe | G60: West | H60: Maharashtra | I60: Nagpur | K60: Unknown | L60: Not published | M60: Not published — ask on first contact (look at the retail shelf / bag on the bar) | P60: Premium house espresso blend of Indian estates + one rotating single estate + cold-brew lot. | Q60: Established: position as a second roaster / rotating single estate; walk-in cupping with the head barista. | R60: 'Best emerging cafe' in Nagpur Today's 2026 ranking. | T60: Walk-in / Google Maps listing | AC60: https://www.nagpurtoday.in/best-cafes-in-nagpur-2026-our-independent-ranking-based-on-reviews-coffee-quality-ambience-customer-experience/ | AG60: 0 of 1 read:
A61: C060 | B61: B | C61: Established | D61: Normal | E61: Three Beans Coffee Roasters | F61: Cafe chain / multi-outlet | G61: West | H61: Maharashtra | I61: Nagpur | J61: Civil Lines (Sunnydale, Rajlaxmi Marg) + Coffee Bar, Gorepeth (Janki Apts, JB Thakkar Marg) + Dharampeth | K61: Unclear — trades as 'Coffee Roasters', but a company profile says it serves coffee from well-regarded Indian roasters | L61: Cold brews, matcha lattes, frappes; the Coffee Bar format adds cocktails; hosts home-brewing workshops (Insider, Jan 2024). | M61: Not published (outside Indian specialty roasters, per a company profile) | N61: ₹600 for two; EazyDiner 4.1 (~3K) | P61: Premium house espresso blend of Indian estates + one rotating single estate + cold-brew lot. | Q61: 3-outlet Nagpur group buying from outside roasters: pitch a guest single estate and co-host a brewing workshop. | R61: Solid coffee choice, 4.1 (rokazu). Wave 4b: est. 2017, 20+ staff (company profile). | S61: Blend. | T61: Walk-in / Google Maps listing | AC61: https://rokazu.com/coffee-shops-in-nagpur-india/ | AE61: Commodity brands: Starbucks; Prices: s Coffee Bar? The cost of two at Three Beans Coffee Bar is ₹ 600. You can save EXTRA; ₹ 600 for two | AG61: 2 of 4 read: https://www.eazydiner.com/nagpur/three-beans-coffee-bar-dharampeth-nagpur-700706 https://rokazu.com/coffee-shops-in-nagpur-india/
A62: C061 | B62: B | C62: Established | D62: Premium | E62: Brewin Cafe | F62: Bakery / patisserie cafe | G62: West | H62: Maharashtra | I62: Nagpur | K62: Unknown | L62: Not published | M62: Not published — ask on first contact (look at the retail shelf / bag on the bar) | P62: Rotating single-estate / micro-lot for the filter bar + a single-origin espresso option. | Q62: Established: position as a second roaster / rotating single estate; walk-in cupping with the head barista. | R62: Instagram: cafe | speciality coffee | bake house. | T62: Instagram DM | U62: @brewincafe_nagpur | V62: https://www.instagram.com/brewincafe_nagpur/ | AC62: https://www.instagram.com/brewincafe_nagpur/
A63: C062 | B63: B | C63: Established | D63: Premium | E63: Coffeeboo Specialty Coffee | F63: Independent specialty cafe | G63: West | H63: Maharashtra | I63: Nagpur | J63: VNIT Health Center, Adisun Sq, Bajaj Nagar (2nd outlet) | K63: Unknown | L63: Not published | M63: Not published — ask on first contact (look at the retail shelf / bag on the bar) | P63: Rotating single-estate / micro-lot for the filter bar + a single-origin espresso option. | Q63: Established: position as a second roaster / rotating single estate; walk-in cupping with the head barista. | R63: Instagram: 'the original specialty coffee shop in Nagpur'; has a LinkedIn company page. | T63: Instagram DM | U63: @coffeebooco | V63: https://www.instagram.com/coffeebooco/ | Y63: +91 92850 77010 (Yappe) | Z63: https://www.linkedin.com/company/coffeeboo-specialty-coffee | AC63: https://www.instagram.com/coffeebooco/ | AD63: Wave 4: listed as 'coffee roasters' — ask whether they roast. | AE63: Brew: Cold brew | AG63: 2 of 3 read: https://www.linkedin.com/company/coffeeboo-specialty-coffee https://yappe.in/maharashtra/nagpur/coffeeboo/232089
A64: C063 | B64: C | C64: New (opened 2026) | D64: Normal | E64: The Coffee Project — Nagpur (4th outlet) | F64: Cafe chain / multi-outlet | G64: West | H64: Maharashtra | I64: Nagpur | K64: Unknown | L64: Not published | M64: Not published — ask on first contact (look at the retail shelf / bag on the bar) | P64: Premium house espresso blend of Indian estates + one rotating single estate + cold-brew lot. | Q64: Just opened: offer a guest-lot month + free barista calibration; side-by-side cupping against their current beans; ask which roaster/estates they use and what they'd change. | R64: Opened 4th Nagpur outlet on 15 Aug 2026 and hiring baristas (LinkedIn). | S64: Growing regional chain — blend supply. | T64: Walk-in / Google Maps listing | AC64: https://in.linkedin.com/jobs/cafe-jobs-pune | AD64: LinkedIn post via search summary Wave 4b: not found; 'The Coffee Project' is a Philippine chain. Nagpur alternatives: The Brew Crew (Bajaj Nagar), All That's Coffee (Sadar). | AG64: 0 of 1 read:
A65: C064 | B65: A | C65: Established | D65: Premium | E65: Pilgrim — Multi-Roaster Speciality Coffee House | F65: Multi-roaster cafe | G65: West | H65: Maharashtra | I65: Nashik | J65: Pumping Station Rd, College Road | K65: Unknown | L65: Rotating roasts 'from various parts of India'; cold brew; closed Tuesdays. | M65: Multiple Indian roasters (unnamed) | N65: ~₹800 for two | O65: Reviews flag service speed — not coffee. | P65: A monthly guest slot with story cards + barista calibration visit. | Q65: Instagram DM @pilgrimcoffee.in with a 1 kg guest-bag offer. | R65: Instagram bio: 'Multi-Roaster Speciality Coffee House'; Zomato lists it on College Road. | S65: Top target — multi-roaster model means guest bags every month. | T65: Instagram DM | U65: @pilgrimcoffee.in | V65: https://www.instagram.com/pilgrimcoffee.in/ | AA65: https://www.zomato.com/nashik/pilgrim-speciality-coffee-house-college-road | AC65: https://www.instagram.com/pilgrimcoffee.in/ | AG65: 1 of 3 read: https://wanderlog.com/place/details/12036201/pilgrim-speciality-coffee-house
A66: C065 | B66: C | C66: Established | D66: Normal | E66: Cafe Bliss | F66: All-day / food-led cafe | G66: West | H66: Maharashtra | I66: Nashik | J66: Rushiraj Tower, Jehan Circle, Gangapur Road | K66: Unknown | L66: Cafe mocha, hot chocolate, black teas, all-day breakfast. | M66: Not published — ask on first contact (look at the retail shelf / bag on the bar) | N66: ~₹650 for two; 4.1 (~1.1K) | P66: Premium house espresso blend of Indian estates + one rotating single estate + cold-brew lot. | Q66: Established: position as a second roaster / rotating single estate; walk-in cupping with the head barista. | R66: Zomato 4.3 (128); since 2010. | S66: Blend. | T66: Walk-in / Google Maps listing | AA66: https://www.zomato.com/nashik/cafe-bliss-college-road | AB66: Founded 2010 by a Culinary Institute of America graduate | AC66: https://www.zomato.com/nashik/cafe-bliss-college-road | AG66: 2 of 4 read: https://yappe.in/maharashtra/nashik/cafe-bliss/134419 https://wanderlog.com/place/details/1138754/cafe-bliss
A67: C066 | B67: B | C67: Established | D67: Normal | E67: 70 Beans | F67: Independent specialty cafe | G67: West | H67: Maharashtra | I67: Navi Mumbai | J67: Shop 19, Palm Beach Galleria, Sector 19D, Vashi | K67: Unknown | L67: Not published | M67: Not published — ask on first contact (look at the retail shelf / bag on the bar) | N67: ₹1,000–2,000 for two | P67: Premium house espresso blend of Indian estates + one rotating single estate + cold-brew lot. | Q67: Established: position as a second roaster / rotating single estate; walk-in cupping with the head barista. | R67: 'Closest thing Navi Mumbai has to a legendary cafe' (local guide 2026). | S67: Neighbourhood favourite — blend + single estate. | T67: Walk-in / Google Maps listing | AC67: https://navimumbaihub.com/best-cafes-navi-mumbai/ | AE67: Commodity brands: Starbucks; Prices: Blue Tokai Seawoods/Nerul — (closes 11PM) ₹500–700 ❌ Specialty coffee; ₹2000 for two | AF67: +91 95946 32110 · +91 91368 61570 | AG67: 4 of 5 read: https://www.district.in/dining/mumbai/70-beans-1-vashi-navi-mumbai https://navimumbaihub.com/best-cafes-navi-mumbai/ https://wanderlog.com/place/details/1506623/70beans https://curlytales.com/ice-cream-sandwiches-at-70-beans-cafe-in-navi-mumbai/
A68: C067 | B68: B | C68: Established | D68: Premium | E68: Panache Specialty Coffee | F68: All-day / food-led cafe | G68: West | H68: Maharashtra | I68: Navi Mumbai | J68: CBD Belapur | K68: Unknown | L68: Not published | M68: Not published — ask on first contact (look at the retail shelf / bag on the bar) | N68: ₹1,000–1,285 for two; EazyDiner 4.5 (917) | P68: Rotating single-estate / micro-lot for the filter bar + a single-origin espresso option. | Q68: Established: position as a second roaster / rotating single estate; walk-in cupping with the head barista. | R68: Instagram: specialty coffee + all-day breakfast + American diner; 'highest-rated coffee shop in Navi Mumbai'; SCA-certified baristas. | T68: Instagram DM | U68: @panachespecialtycoffee | V68: https://www.instagram.com/panachespecialtycoffee/ | AC68: https://www.instagram.com/panachespecialtycoffee/ | AE68: ₹ 1285 for two | AG68: 2 of 2 read: https://www.eazydiner.com/mumbai/panache-cbd-belapur-navi-mumbai-684322 https://ilovenavimumbai.com/?p=695
A69: C068 | B69: A | C69: New (opened 2026) | D69: Premium | E69: Cafe Lento — Pune | F69: All-day / food-led cafe | G69: West | H69: Maharashtra | I69: Pune | J69: Koregaon Park | K69: Unknown | L69: Single estate: Salawara Estate (Karnataka); coffee is the signature; Pune adds cocktails (raw mango wine, Lento espresso martini). | M69: Salawara Estate (roaster not named) | O69: Single-estate dependency. | P69: Second estate for a rotating pour-over + an espresso-martini-ready blend. | Q69: Luna Hospitality (also The Second House, Goa) — one pitch covers Goa + Pune. | R69: Luna Hospitality's Goa cafe opened a 2,200 sq ft Pune outpost (Nod Jun 2026; Elle Decor Sep 2026); coffee + congee concept. | S69: Single-estate-minded team — pitch an estate exclusive for Pune. | T69: Instagram DM | U69: @cafelento.in | V69: https://www.instagram.com/cafelento.in/ | AB69: Dishant Pritamani (co-founder, Luna Hospitality) | AC69: https://yourstory.com/ys-life/the-second-house-goa-lento-cafe | AG69: 0 of 2 read:
A70: C069 | B70: A | C70: New (opened 2026) | D70: Premium | E70: Momoka | F70: Independent specialty cafe | G70: West | H70: Maharashtra | I70: Pune | J70: Prabhat Rd, Pune (opened 1 Aug 2026) | K70: Unknown | L70: Japanese kissaten: ceremonial Uji matcha, hojicha; coffee jelly latte, coconut-foam cold brew. | M70: Not published — ask on first contact (look at the retail shelf / bag on the bar) | N70: ~₹900 for two | O70: Coffee is secondary to matcha; no named roaster. | P70: A kissaten-style medium-dark blend + a cold brew lot. | Q70: Chef-founder Brainard Colaco — offer to co-design a hand-drip menu. | R70: Japanese kissaten-style flagship opened Aug 2026 with specialty beverages, desserts and yoshoku food. Instagram bio: 'India's first kissaten' — Japanese coffee & tea room; Prabhat Road marked 'now open' (Jul 2026). | S70: Kissaten culture = hand-drip / siphon — pitch light-roast single estates. | T70: Instagram DM | U70: @momoka.india | V70: https://www.instagram.com/momoka.india/ | AB70: Chef Brainard Colaco | AC70: https://www.restaurantindia.in/news/momoka-opens-japanese-kissaten-inspired-caf-on-punes-prabhat-road.n16884 | AE70: Brew: Cold brew | AG70: 3 of 3 read: https://www.restaurantindia.in/news/momoka-opens-japanese-kissaten-inspired-caf-on-punes-prabhat-road.n16884 https://indianretailer.com/franchisetv/archives/news/momoka-brings-japanese-kissaten-culture-pune-new-flagship-cafe https://www.passionateinmarketing.com/momoka-brings-the-spirit-of-a-japanese-kissaten-to-pune/
A71: C070 | B71: A | C71: Established | D71: Premium | E71: One World — The Coffee Studio | F71: Multi-roaster cafe | G71: West | H71: Maharashtra | I71: Pune | J71: Shop 6 & 7, Fortaleza Complex, Kalyani Nagar | K71: Unknown | L71: 30+ coffee drinks from small-batch roasters (single origins and blends); single-malt-barrel Cold Whiskey Buzz; espresso float. | M71: Multiple small-batch roasters (unnamed) | N71: ~₹1,200 for two | P71: Guest-roaster slot. | Q71: Multi-roaster: ask for a guest-roaster month — 1 kg bags of two contrasting Indian lots + story cards. | R71: Specialty coffee studio sourcing from small-batch roasters; offers pour-over (Curly Tales). Instagram: premium coffee & global flavours, open till 2am. | S71: Already buys from multiple small roasters — straight guest-roaster pitch. | T71: Instagram DM | U71: @oneworld_thecoffeestudio | V71: https://www.instagram.com/oneworld_thecoffeestudio/ | Y71: +91 98223 44448 (LBB) | AC71: https://curlytales.com/punes-bustling-cafe-culture-gets-a-new-chic-coffee-place-one-world-the-coffee-studio/amp/ | AD71: Area not confirmed | AE71: Processes / format: Single origin; Brew: Pour over, Cold brew; Prices: The cost of two at One World - The Coffee Studio is ₹ 1200.; ₹ 1200 for two | AG71: 5 of 5 read: https://www.eazydiner.com/pune/one-world-the-coffee-studio-kalyani-nagar-pune-690333 https://www.eazydiner.com/pune/one-world-the-coffee-studio-kalyani-nagar-pune-690333/menu https://curlytales.com/punes-bustling-cafe-culture-gets-a-new-chic-coffee-place-one-world-the-coffee-studio/amp/ https://curlytales.com/punes-bustling-cafe-culture-gets-a-new-chic-coffee-place-one-world-the-coffee-studio
A72: C071 | B72: A | C72: Upcoming / Coming soon | D72: Premium | E72: Unnamed specialty cafe — Viman Nagar (in planning) | F72: Independent specialty cafe | G72: West | H72: Maharashtra | I72: Pune | J72: Viman Nagar | K72: Unknown | L72: Plans Coorg-sourced beans | M72: Not published — ask on first contact (look at the retail shelf / bag on the bar) | P72: Rotating single-estate / micro-lot for the filter bar + a single-origin espresso option. | Q72: Pre-launch: send a 3-estate tasting kit and offer a menu-development session before the menu locks; 90-day launch exclusivity in their micro-market; fixed price for the first 6 months. | R72: Founder posted on r/PuneCoffee (mid-2026) about opening a specialty cafe with Coorg beans and board-game nights. | S72: Pre-launch — reach founder via r/PuneCoffee before supplier is locked. | T72: Walk-in / Google Maps listing | AA72: https://www.reddit.com/r/PuneCoffee/new/ | AC72: r/PuneCoffee (via mirror redlib.groet-infra.nl/r/PuneCoffee/new) | AD72: Name unknown; Reddit post | AG72: 0 of 1 read:
A73: C072 | B73: B | C73: Established | D73: Normal | E73: Book Bar | F73: Cafe chain / multi-outlet | G73: West | H73: Maharashtra | I73: Pune | J73: 3 Pune outlets (incl. Kothrud) + Pali Hill, Mumbai | K73: Unknown | L73: Not published | M73: Not published — ask on first contact (look at the retail shelf / bag on the bar) | P73: Premium house espresso blend of Indian estates + one rotating single estate + cold-brew lot. | Q73: Multi-outlet: pitch central procurement — fixed roast spec, monthly volume pricing, retail bags for the shelf. | R73: Artisanal coffee + bookstore (Instagram). | T73: Instagram DM | U73: @bookbarpune | V73: https://www.instagram.com/bookbarpune/ | AB73: Avneesh Gadgil & Rushad Wadia | AC73: https://www.instagram.com/bookbarpune/ | AE73: Indian origins/estates: Ground Daulat Estate; Rs. 500 for two | AG73: 3 of 3 read: https://www.freepressjournal.in/lifestyle/more-than-a-caf-inside-avneesh-gadgils-book-bar-dream-now-brewing-in-mumbai https://www.localsamosa.com/food-and-drinks/book-cafes-in-pune-9356580 https://www.timeout.com/mumbai/restaurants/book-bar
A74: C073 | B74: B | C74: Upcoming / Coming soon | D74: Normal | E74: Cafe Serenity — Baner (relocating) | F74: Independent specialty cafe | G74: West | H74: Maharashtra | I74: Pune | J74: Baner | K74: Unknown | L74: Not published | M74: Not published — ask on first contact (look at the retail shelf / bag on the bar) | P74: Premium house espresso blend of Indian estates + one rotating single estate + cold-brew lot. | Q74: Pre-launch: send a 3-estate tasting kit and offer a menu-development session before the menu locks; 90-day launch exclusivity in their micro-market; fixed price for the first 6 months. | R74: Instagram: 'Serenity finds a new home in Baner — be back soon'. | S74: Relaunch = supplier reset moment. | T74: Instagram DM | U74: @cafeserenity_pune | V74: https://www.instagram.com/cafeserenity_pune/ | AC74: https://www.instagram.com/cafeserenity_pune/ | AD74: Wave 4: only a Kothrud (Mayur Colony) listing found; Baner move unconfirmed. | AG74: 1 of 1 read: https://www.explurger.com/pd/pkfm8zlni1mxtmjw0
A75: C074 | B75: B | C75: Established | D75: Normal | E75: Caffeowl Coffee | F75: Independent specialty cafe | G75: West | H75: Maharashtra | I75: Pune | K75: Unknown | L75: Not published | M75: Not published — ask on first contact (look at the retail shelf / bag on the bar) | P75: Premium house espresso blend of Indian estates + one rotating single estate + cold-brew lot. | Q75: Established: position as a second roaster / rotating single estate; walk-in cupping with the head barista. | R75: Quiet specialty-coffee work cafe (echai.ventures). | S75: Blend + filter. | T75: Walk-in / Google Maps listing | AC75: https://echai.ventures/grid/pune/caffeowl-coffee | AG75: 0 of 1 read:
A76: C075 | B76: B | C76: Established | D76: Normal | E76: Salt & Coffee | F76: All-day / food-led cafe | G76: West | H76: Maharashtra | I76: Pune | J76: Kalyani Nagar | K76: Unknown | L76: Not published | M76: Not published — ask on first contact (look at the retail shelf / bag on the bar) | P76: Premium house espresso blend of Indian estates + one rotating single estate + cold-brew lot. | Q76: Established: position as a second roaster / rotating single estate; walk-in cupping with the head barista. | R76: Cozy cafe known for artisanal coffee and healthy food (Yukio 2026). | S76: House blend. | T76: Walk-in / Google Maps listing | AC76: https://www.yukio.in/blog/best-coffee-places-in-pune/ | AD76: Wave 4: not found in a web search beyond its source roundup — confirm it is open (Instagram / Google Maps) before outreach. | AG76: 0 of 1 read:
